Workbook

Sheet Dropdownlist
A1: Status | B1: Country | C1: Countries (if multiple) or Region | D1: Disease/condition | E1: Pending question | F1: Need RRA | G1: RRA Risk level | H1: Need EIS | I1: Type | J1: EIS_first_draft_by | K1: Need DON | L1: GPW 13 Desc_start | M1: GPW 13 Desc_detect | N1: GPW 13 Desc_notify | O1: GPW 13 Desc_response
A2: Closed | B2: Afghanistan | C2: AFR | D2: Acute febrile jaundice syndrome | E2: No | F2: No | G2: High | H2: No | I2: Update existing EIS | J2: WHO RO | K2: No | L2: First visit to health care facility | M2: First sample collection date | O2: Incident management system set up
A3: Unknown | B3: Åland Islands | C3: AMR | D3: Acute Hemorrhagic Fever | E3: Yes | F3: Decision pending | G3: Moderate | H3: Decision pending | I3: EIS anouncement | J3: Not applicable | K3: Decision pending | L3: Date of suspected primary case | M3: Ministry of health press release date | O3: Vaccination campaign started
A4: Open | B4: Multiple | C4: Not applicable | D4: Acute kidney injury | F4: Yes | G4: Very High | H4: Yes | I4: New EIS | J4: WHO HQ | K4: Yes | L4: Symptom-onset date of first reported case (=initial case) | M4: First confirmatory laboratory test | N4: Date national governmental agency, the International Health Regulation national focal point reported to WHO | O4: Field investigation started
B5: Albania | C5: EMR | D5: AMR Klebsiella pneumoniae | G5: Low | I5: Not applicable | L5: Most likely exposure date (estimated) | M5: Rapid diagnostic test date | O5: Active surveillance initiated
B6: Algeria | C6: EUR | D6: Anthrax | G6: Not applicable | L6: First exposure date (estimated) | M6: First time diagnosed as suspected case | O6: Rapid response team deployed
B7: American Samoa | C7: SEAR | D7: Arboviruses | L7: Latest exposure date (estimated) | M7: Date other external party reported to ministry of health | O7: Active surveillance initiated
B8: Andorra | C8: WPR | D8: Avian influenza A (H10N3) | L8: Outbreak start date | M8: Date outbreak declared | O8: Risk communication started
B9: Angola | C9: Somalia, Ethiopia | D9: Avian influenza A (H10N5) + H3N2 | L9: Date of death of first reported case (=initial case) | M9: Date local health authority reported to ministry of health | O9: Date quarantine started
B10: Anguilla | C10: Mozambique, Malawi | D10: Avian influenza A (H1N1) v | L10: First report of the outbreak | M10: Date of preliminary laboratory test | O10: Vector control campaign launched
B11: Antigua and Barbuda | C11: EUR, AMR | D11: Avian influenza A (H1N2) | M11: Communication from laboratory to ministry of health | O11: Food/product recall started
B12: France | C12: Multi area | D12: Avian influenza A (H1N2)v
B13: Argentina | C13: Global | D13: Avian Influenza A (H3N8) | M13: Date first communication between third party Member States happened | O13: National emergency operation centre activated
B14: Armenia | C14: Niger, Nigeria | D14: Avian influenza A (H5N1) | M14: Date local health authority detected signal through media | O14: Expert group established
B15: Aruba | C15: Mexico, United States of America | D15: Avian influenza A (H5N6)
B16: Australia | C16: Australia, New Zealand, UAE | D16: Avian Influenza A (H9)
B17: Austria | C17: Chile, Armenia, Georgia | D17: Avian influenza A (H9N2)
B18: Azerbaijan | D18: Avian Influenza A(H3)v
B19: Bahamas | D19: Avian influenza A(H5)
B20: Bahrain | D20: Avian Influenza A(H9)
B21: Bangladesh | D21: Botulism
B22: Barbados | D22: Chandipura virus
B23: Belarus | D23: Chapare virus
B24: Belgium | D24: Chemical exposure
B25: Belize | D25: Chikungunya
B26: Benin | D26: Cholera
B27: Bermuda | D27: COVID - 19
B28: Bhutan | D28: COVID-19 (Omicron)
B29: Bolivia (Plurinational State of) | D29: Crimean-Congo hemorrhagic fever (CCHF)
... B90: Georgia | D90: Zika
B91: Germany
B92: Ghana
B93: Gibraltar
B94: Greece
B95: Greenland
B96: Grenada
B97: Guadeloupe
B98: Guam
B99: Guatemala
B100: Guernsey
B101: Guinea
B102: Guinea-Bissau
... B253: Global

Sheet product tracker
A1: Date of entry | B1: Status | C1: Product | D1: FP name | E1: disease_condition | F1: country | G1: Countries (if multiple) or Region | H1: daily signal tracker | I1: Daily signal tracker update entry | J1: EMS entry | K1: EMS event ID | L1: EMS comments | M1: Pending_question | N1: Pending question status | O1: PQ_closure_date | P1: Need_RRA | Q1: Version | R1: RRA status | S1: RRA_Decision_date | T1: RRA_start_date | U1: RRA_pub_date | V1: RRA National risk level | W1: RRA Regional risk level | X1: RRA Global risk level | Y1: Need_EIS | Z1: Type | AA1: EIS_first_draft_by | AB1: EIS status | AC1: EIS_decision_date | AD1: EIS_start_HQ_receive_date | AE1: EIS sent to Regional office | AF1: EIS sent to NFP | AG1: Feedback NFP | AH1: EIS_pub_date | AI1: Need_DON | AJ1: DON_start_date | AK1: DON_pub_date | AL1: Comments | AM1: countrycode | AN1: RRA_indic | AO1: EIS_indic | AP1: DON_indic | AQ1: PQ_indic | AR1: daily_list
A2: 36526 | B2: Closed | C2: {=IF(SUM(Table2[[#This Row],[PQ_indic]],Table2[[#This Row],[RRA_indic]],Table2[[#This Row],[EIS_indic]],Table2[[#This Row],[DON_indic]])=8, "Missing data", (IF(AND(Table2[[#This Row],[Pending_question]]="Yes", OR( Table2[[#This Row],[Need_RRA]]="No", ISBLANK(Table2[[#This Row],[Need_RRA]])), OR(Table2[[#This Row],[Need_EIS]]="No", ISBLANK(Table2[[#This Row],[Need_EIS]])), OR(Table2[[#This Row],[Need_DON]]="No", ISBLANK(Table2[[#This Row],[Need_DON]]) )),"Question, no products",( IF( AND(Table2[[#This Row],[Pending_question]]="Yes", ISBLANK(Table2[[#This Row],[PQ_closure_date]])), (IF(SUM(Table2[[#This Row],[RRA_indic]],Table2[[#This Row],[EIS_indic]],Table2[[#This Row],[DON_indic]])=0, "Open Question, all products done",(I447IF(OR(Table2[[#This Row],[RRA_indic]]=2, Table2[[#This Row],[EIS_indic]]=2, Table2[[#This Row],[DON_indic]]=2),"Question, Products unknown",IF(AND(Table2[[#This Row],[RRA_indic]]=1, Table2[[#This Row],[EIS_indic]]=1, Table2[[#This Row],[DON_indic]]=1), "Open Question, RRA, EIS, DON", IF(AND(Table2[[#This Row],[RRA_indic]]=1, Table2[[#This Row],[EIS_indic]]=1), "Open Question, RRA, EIS",IF(AND(Table2[[#This Row],[RRA_indic]]=1, Table2[[#This Row],[DON_indic]]=1), "Open Question, RRA, DON", IF(AND(Table2[[#This Row],[EIS_indic]]=1, Table2[[#This Row],[DON_indic]]=1), "Open Question, EIS, DON",IF(Table2[[#This Row],[RRA_indic]]=1, "Open Question, RRA", IF(Table2[[#This Row],[EIS_indic]]=1, "Open Question, EIS", "Open Question, DON")))))))))), (IF(SUM(Table2[[#This Row],[RRA_indic]],Table2[[#This Row],[EIS_indic]],Table2[[#This Row],[DON_indic]])=0, "All Products done",(IF(OR(Table2[[#This Row],[RRA_indic]]=2, Table2[[#This Row],[EIS_indic]]=2, Table2[[#This Row],[DON_indic]]=2),"Unknown", IF(AND(Table2[[#This Row],[RRA_indic]]=1, Table2[[#This Row],[EIS_indic]]=1, Table2[[#This Row],[DON_indic]]=1), "Open RRA, EIS, DON", IF(AND(Table2[[#This Row],[RRA_indic]]=1, Table2[[#This Row],[EIS_indic]]=1), "Open RRA, EIS", IF(AND(Table2[[#This Row],[RRA_indic]]=1, Table2[[#This Row],[DON_indic]]=1), "Open RRA, DON", IF(AND(Table2[[#This Row],[EIS_indic]]=1, Table2[[#This Row],[DON_indic]]=1), "Open EIS, DON", IF(Table2[[#This Row],[RRA_indic]]=1, "Open RRA", IF(Table2[[#This Row],[EIS_indic]]=1, "Open EIS", "Open DON")))))))))))))))} -> All Products done | D2: Lidia | E2: Acute Hemorrhagic Fever | F2: Angola | G2: Not applicable | M2: No | P2: No | Q2: Not applicable | Y2: no | AI2: no | AL2: 21 June: signal, additional information requested from AFRO / 24 June: Malaria confirmed | AM2: =VLOOKUP(Table2[[#This Row],[country]],Countrycode!A:B,2,FALSE) -> AGO | AN2: =IF(ISBLANK(Table2[[#This Row],[Need_RRA]]), 2,(IF(Table2[[#This Row],[Need_RRA]]="No", 0, (IF(AND(Table2[[#This Row],[Need_RRA]]="Yes", Table2[[#This Row],[RRA_pub_date]]=""),1, 0))))) -> 0 | AO2: =IF(ISBLANK(Table2[[#This Row],[Need_EIS]]), 2,(IF(Table2[[#This Row],[Need_EIS]]="No", 0, (IF(AND(Table2[[#This Row],[Need_EIS]]="Yes", Table2[[#This Row],[EIS_pub_date]]=""),1, 0))))) -> 0 | AP2: =IF(ISBLANK(Table2[[#This Row],[Need_DON]]), 2,(IF(Table2[[#This Row],[Need_DON]]="No", 0, (IF(AND(Table2[[#This Row],[Need_DON]]="Yes", Table2[[#This Row],[DON_pub_date]]=""),1, 0))))) -> 0 | AQ2: =IF(ISBLANK(Table2[[#This Row],[Pending_question]]), 2,(IF(Table2[[#This Row],[Pending_question]]="Yes", 1, 0))) -> 0
A3: 36526 | B3: Closed | C3: {=IF(SUM(Table2[[#This Row],[PQ_indic]],Table2[[#This Row],[RRA_indic]],Table2[[#This Row],[EIS_indic]],Table2[[#This Row],[DON_indic]])=8, "Missing data", (IF(AND(Table2[[#This Row],[Pending_question]]="Yes", OR( Table2[[#This Row],[Need_RRA]]="No", ISBLANK(Table2[[#This Row],[Need_RRA]])), OR(Table2[[#This Row],[Need_EIS]]="No", ISBLANK(Table2[[#This Row],[Need_EIS]])), OR(Table2[[#This Row],[Need_DON]]="No", ISBLANK(Table2[[#This Row],[Need_DON]]) )),"Question, no products",( IF( AND(Table2[[#This Row],[Pending_question]]="Yes", ISBLANK(Table2[[#This Row],[PQ_closure_date]])), (IF(SUM(Table2[[#This Row],[RRA_indic]],Table2[[#This Row],[EIS_indic]],Table2[[#This Row],[DON_indic]])=0, "Open Question, all products done",(I447IF(OR(Table2[[#This Row],[RRA_indic]]=2, Table2[[#This Row],[EIS_indic]]=2, Table2[[#This Row],[DON_indic]]=2),"Question, Products unknown",IF(AND(Table2[[#This Row],[RRA_indic]]=1, Table2[[#This Row],[EIS_indic]]=1, Table2[[#This Row],[DON_indic]]=1), "Open Question, RRA, EIS, DON", IF(AND(Table2[[#This Row],[RRA_indic]]=1, Table2[[#This Row],[EIS_indic]]=1), "Open Question, RRA, EIS",IF(AND(Table2[[#This Row],[RRA_indic]]=1, Table2[[#This Row],[DON_indic]]=1), "Open Question, RRA, DON", IF(AND(Table2[[#This Row],[EIS_indic]]=1, Table2[[#This Row],[DON_indic]]=1), "Open Question, EIS, DON",IF(Table2[[#This Row],[RRA_indic]]=1, "Open Question, RRA", IF(Table2[[#This Row],[EIS_indic]]=1, "Open Question, EIS", "Open Question, DON")))))))))), (IF(SUM(Table2[[#This Row],[RRA_indic]],Table2[[#This Row],[EIS_indic]],Table2[[#This Row],[DON_indic]])=0, "All Products done",(IF(OR(Table2[[#This Row],[RRA_indic]]=2, Table2[[#This Row],[EIS_indic]]=2, Table2[[#This Row],[DON_indic]]=2),"Unknown", IF(AND(Table2[[#This Row],[RRA_indic]]=1, Table2[[#This Row],[EIS_indic]]=1, Table2[[#This Row],[DON_indic]]=1), "Open RRA, EIS, DON", IF(AND(Table2[[#This Row],[RRA_indic]]=1, Table2[[#This Row],[EIS_indic]]=1), "Open RRA, EIS", IF(AND(Table2[[#This Row],[RRA_indic]]=1, Table2[[#This Row],[DON_indic]]=1), "Open RRA, DON", IF(AND(Table2[[#This Row],[EIS_indic]]=1, Table2[[#This Row],[DON_indic]]=1), "Open EIS, DON", IF(Table2[[#This Row],[RRA_indic]]=1, "Open RRA", IF(Table2[[#This Row],[EIS_indic]]=1, "Open EIS", "Open DON")))))))))))))))} -> All Products done | D3: Anastasia | E3: Cholera | F3: Democratic Republic of the Congo | G3: Not applicable | M3: No | P3: No | Q3: Not applicable | R3: 23 June: Awaiting las comments from WCO. 24 June: On 24 June, AFRO suggested to change the risk levels in the risk assessment table. 25 June: during a 3L TC it was decided to drop this RRA as the situation has changed significantly and RRA is not required at the moment. 2 July: Not required at the moment | Y3: no | AB3: 25 June: No plans | AI3: no | AM3: =VLOOKUP(Table2[[#This Row],[country]],Countrycode!A:B,2,FALSE) -> COD | AN3: =IF(ISBLANK(Table2[[#This Row],[Need_RRA]]), 2,(IF(Table2[[#This Row],[Need_RRA]]="No", 0, (IF(AND(Table2[[#This Row],[Need_RRA]]="Yes", Table2[[#This Row],[RRA_pub_date]]=""),1, 0))))) -> 0 | AO3: =IF(ISBLANK(Table2[[#This Row],[Need_EIS]]), 2,(IF(Table2[[#This Row],[Need_EIS]]="No", 0, (IF(AND(Table2[[#This Row],[Need_EIS]]="Yes", Table2[[#This Row],[EIS_pub_date]]=""),1, 0))))) -> 0 | AP3: =IF(ISBLANK(Table2[[#This Row],[Need_DON]]), 2,(IF(Table2[[#This Row],[Need_DON]]="No", 0, (IF(AND(Table2[[#This Row],[Need_DON]]="Yes", Table2[[#This Row],[DON_pub_date]]=""),1, 0))))) -> 0 | AQ3: =IF(ISBLANK(Table2[[#This Row],[Pending_question]]), 2,(IF(Table2[[#This Row],[Pending_question]]="Yes", 1, 0))) -> 0
A4: 36526 | B4: Closed | C4: {=IF(SUM(Table2[[#This Row],[PQ_indic]],Table2[[#This Row],[RRA_indic]],Table2[[#This Row],[EIS_indic]],Table2[[#This Row],[DON_indic]])=8, "Missing data", (IF(AND(Table2[[#This Row],[Pending_question]]="Yes", OR( Table2[[#This Row],[Need_RRA]]="No", ISBLANK(Table2[[#This Row],[Need_RRA]])), OR(Table2[[#This Row],[Need_EIS]]="No", ISBLANK(Table2[[#This Row],[Need_EIS]])), OR(Table2[[#This Row],[Need_DON]]="No", ISBLANK(Table2[[#This Row],[Need_DON]]) )),"Question, no products",( IF( AND(Table2[[#This Row],[Pending_question]]="Yes", ISBLANK(Table2[[#This Row],[PQ_closure_date]])), (IF(SUM(Table2[[#This Row],[RRA_indic]],Table2[[#This Row],[EIS_indic]],Table2[[#This Row],[DON_indic]])=0, "Open Question, all products done",(I447IF(OR(Table2[[#This Row],[RRA_indic]]=2, Table2[[#This Row],[EIS_indic]]=2, Table2[[#This Row],[DON_indic]]=2),"Question, Products unknown",IF(AND(Table2[[#This Row],[RRA_indic]]=1, Table2[[#This Row],[EIS_indic]]=1, Table2[[#This Row],[DON_indic]]=1), "Open Question, RRA, EIS, DON", IF(AND(Table2[[#This Row],[RRA_indic]]=1, Table2[[#This Row],[EIS_indic]]=1), "Open Question, RRA, EIS",IF(AND(Table2[[#This Row],[RRA_indic]]=1, Table2[[#This Row],[DON_indic]]=1), "Open Question, RRA, DON", IF(AND(Table2[[#This Row],[EIS_indic]]=1, Table2[[#This Row],[DON_indic]]=1), "Open Question, EIS, DON",IF(Table2[[#This Row],[RRA_indic]]=1, "Open Question, RRA", IF(Table2[[#This Row],[EIS_indic]]=1, "Open Question, EIS", "Open Question, DON")))))))))), (IF(SUM(Table2[[#This Row],[RRA_indic]],Table2[[#This Row],[EIS_indic]],Table2[[#This Row],[DON_indic]])=0, "All Products done",(IF(OR(Table2[[#This Row],[RRA_indic]]=2, Table2[[#This Row],[EIS_indic]]=2, Table2[[#This Row],[DON_indic]]=2),"Unknown", IF(AND(Table2[[#This Row],[RRA_indic]]=1, Table2[[#This Row],[EIS_indic]]=1, Table2[[#This Row],[DON_indic]]=1), "Open RRA, EIS, DON", IF(AND(Table2[[#This Row],[RRA_indic]]=1, Table2[[#This Row],[EIS_indic]]=1), "Open RRA, EIS", IF(AND(Table2[[#This Row],[RRA_indic]]=1, Table2[[#This Row],[DON_indic]]=1), "Open RRA, DON", IF(AND(Table2[[#This Row],[EIS_indic]]=1, Table2[[#This Row],[DON_indic]]=1), "Open EIS, DON", IF(Table2[[#This Row],[RRA_indic]]=1, "Open RRA", IF(Table2[[#This Row],[EIS_indic]]=1, "Open EIS", "Open DON")))))))))))))))} -> All Products done | D4: Anastasia | E4: Malaria | F4: Ethiopia | G4: Not applicable | M4: No | P4: No | Q4: Not applicable | R4: pending | Y4: no | AB4: PHSA done by FES in April | AI4: no | AM4: =VLOOKUP(Table2[[#This Row],[country]],Countrycode!A:B,2,FALSE) -> ETH | AN4: =IF(ISBLANK(Table2[[#This Row],[Need_RRA]]), 2,(IF(Table2[[#This Row],[Need_RRA]]="No", 0, (IF(AND(Table2[[#This Row],[Need_RRA]]="Yes", Table2[[#This Row],[RRA_pub_date]]=""),1, 0))))) -> 0 | AO4: =IF(ISBLANK(Table2[[#This Row],[Need_EIS]]), 2,(IF(Table2[[#This Row],[Need_EIS]]="No", 0, (IF(AND(Table2[[#This Row],[Need_EIS]]="Yes", Table2[[#This Row],[EIS_pub_date]]=""),1, 0))))) -> 0 | AP4: =IF(ISBLANK(Table2[[#This Row],[Need_DON]]), 2,(IF(Table2[[#This Row],[Need_DON]]="No", 0, (IF(AND(Table2[[#This Row],[Need_DON]]="Yes", Table2[[#This Row],[DON_pub_date]]=""),1, 0))))) -> 0 | AQ4: =IF(ISBLANK(Table2[[#This Row],[Pending_question]]), 2,(IF(Table2[[#This Row],[Pending_question]]="Yes", 1, 0))) -> 0
A5: 36526 | B5: Closed | C5: {=IF(SUM(Table2[[#This Row],[PQ_indic]],Table2[[#This Row],[RRA_indic]],Table2[[#This Row],[EIS_indic]],Table2[[#This Row],[DON_indic]])=8, "Missing data", (IF(AND(Table2[[#This Row],[Pending_question]]="Yes", OR( Table2[[#This Row],[Need_RRA]]="No", ISBLANK(Table2[[#This Row],[Need_RRA]])), OR(Table2[[#This Row],[Need_EIS]]="No", ISBLANK(Table2[[#This Row],[Need_EIS]])), OR(Table2[[#This Row],[Need_DON]]="No", ISBLANK(Table2[[#This Row],[Need_DON]]) )),"Question, no products",( IF( AND(Table2[[#This Row],[Pending_question]]="Yes", ISBLANK(Table2[[#This Row],[PQ_closure_date]])), (IF(SUM(Table2[[#This Row],[RRA_indic]],Table2[[#This Row],[EIS_indic]],Table2[[#This Row],[DON_indic]])=0, "Open Question, all products done",(I447IF(OR(Table2[[#This Row],[RRA_indic]]=2, Table2[[#This Row],[EIS_indic]]=2, Table2[[#This Row],[DON_indic]]=2),"Question, Products unknown",IF(AND(Table2[[#This Row],[RRA_indic]]=1, Table2[[#This Row],[EIS_indic]]=1, Table2[[#This Row],[DON_indic]]=1), "Open Question, RRA, EIS, DON", IF(AND(Table2[[#This Row],[RRA_indic]]=1, Table2[[#This Row],[EIS_indic]]=1), "Open Question, RRA, EIS",IF(AND(Table2[[#This Row],[RRA_indic]]=1, Table2[[#This Row],[DON_indic]]=1), "Open Question, RRA, DON", IF(AND(Table2[[#This Row],[EIS_indic]]=1, Table2[[#This Row],[DON_indic]]=1), "Open Question, EIS, DON",IF(Table2[[#This Row],[RRA_indic]]=1, "Open Question, RRA", IF(Table2[[#This Row],[EIS_indic]]=1, "Open Question, EIS", "Open Question, DON")))))))))), (IF(SUM(Table2[[#This Row],[RRA_indic]],Table2[[#This Row],[EIS_indic]],Table2[[#This Row],[DON_indic]])=0, "All Products done",(IF(OR(Table2[[#This Row],[RRA_indic]]=2, Table2[[#This Row],[EIS_indic]]=2, Table2[[#This Row],[DON_indic]]=2),"Unknown", IF(AND(Table2[[#This Row],[RRA_indic]]=1, Table2[[#This Row],[EIS_indic]]=1, Table2[[#This Row],[DON_indic]]=1), "Open RRA, EIS, DON", IF(AND(Table2[[#This Row],[RRA_indic]]=1, Table2[[#This Row],[EIS_indic]]=1), "Open RRA, EIS", IF(AND(Table2[[#This Row],[RRA_indic]]=1, Table2[[#This Row],[DON_indic]]=1), "Open RRA, DON", IF(AND(Table2[[#This Row],[EIS_indic]]=1, Table2[[#This Row],[DON_indic]]=1), "Open EIS, DON", IF(Table2[[#This Row],[RRA_indic]]=1, "Open RRA", IF(Table2[[#This Row],[EIS_indic]]=1, "Open EIS", "Open DON")))))))))))))))} -> All Products done | D5: Dunja | E5: Malaria | F5: Niger | G5: Not applicable | M5: No | P5: No | Q5: Not applicable | R5: 5 October: need RRA? | Y5: no | AI5: no | AL5: Still waiting decision from AFRO ( waiting for Malaria TT advise) | AM5: =VLOOKUP(Table2[[#This Row],[country]],Countrycode!A:B,2,FALSE) -> NER | AN5: =IF(ISBLANK(Table2[[#This Row],[Need_RRA]]), 2,(IF(Table2[[#This Row],[Need_RRA]]="No", 0, (IF(AND(Table2[[#This Row],[Need_RRA]]="Yes", Table2[[#This Row],[RRA_pub_date]]=""),1, 0))))) -> 0 | AO5: =IF(ISBLANK(Table2[[#This Row],[Need_EIS]]), 2,(IF(Table2[[#This Row],[Need_EIS]]="No", 0, (IF(AND(Table2[[#This Row],[Need_EIS]]="Yes", Table2[[#This Row],[EIS_pub_date]]=""),1, 0))))) -> 0 | AP5: =IF(ISBLANK(Table2[[#This Row],[Need_DON]]), 2,(IF(Table2[[#This Row],[Need_DON]]="No", 0, (IF(AND(Table2[[#This Row],[Need_DON]]="Yes", Table2[[#This Row],[DON_pub_date]]=""),1, 0))))) -> 0 | AQ5: =IF(ISBLANK(Table2[[#This Row],[Pending_question]]), 2,(IF(Table2[[#This Row],[Pending_question]]="Yes", 1, 0))) -> 0
A6: 36526 | B6: Closed | C6: {=IF(SUM(Table2[[#This Row],[PQ_indic]],Table2[[#This Row],[RRA_indic]],Table2[[#This Row],[EIS_indic]],Table2[[#This Row],[DON_indic]])=8, "Missing data", (IF(AND(Table2[[#This Row],[Pending_question]]="Yes", OR( Table2[[#This Row],[Need_RRA]]="No", ISBLANK(Table2[[#This Row],[Need_RRA]])), OR(Table2[[#This Row],[Need_EIS]]="No", ISBLANK(Table2[[#This Row],[Need_EIS]])), OR(Table2[[#This Row],[Need_DON]]="No", ISBLANK(Table2[[#This Row],[Need_DON]]) )),"Question, no products",( IF( AND(Table2[[#This Row],[Pending_question]]="Yes", ISBLANK(Table2[[#This Row],[PQ_closure_date]])), (IF(SUM(Table2[[#This Row],[RRA_indic]],Table2[[#This Row],[EIS_indic]],Table2[[#This Row],[DON_indic]])=0, "Open Question, all products done",(I447IF(OR(Table2[[#This Row],[RRA_indic]]=2, Table2[[#This Row],[EIS_indic]]=2, Table2[[#This Row],[DON_indic]]=2),"Question, Products unknown",IF(AND(Table2[[#This Row],[RRA_indic]]=1, Table2[[#This Row],[EIS_indic]]=1, Table2[[#This Row],[DON_indic]]=1), "Open Question, RRA, EIS, DON", IF(AND(Table2[[#This Row],[RRA_indic]]=1, Table2[[#This Row],[EIS_indic]]=1), "Open Question, RRA, EIS",IF(AND(Table2[[#This Row],[RRA_indic]]=1, Table2[[#This Row],[DON_indic]]=1), "Open Question, RRA, DON", IF(AND(Table2[[#This Row],[EIS_indic]]=1, Table2[[#This Row],[DON_indic]]=1), "Open Question, EIS, DON",IF(Table2[[#This Row],[RRA_indic]]=1, "Open Question, RRA", IF(Table2[[#This Row],[EIS_indic]]=1, "Open Question, EIS", "Open Question, DON")))))))))), (IF(SUM(Table2[[#This Row],[RRA_indic]],Table2[[#This Row],[EIS_indic]],Table2[[#This Row],[DON_indic]])=0, "All Products done",(IF(OR(Table2[[#This Row],[RRA_indic]]=2, Table2[[#This Row],[EIS_indic]]=2, Table2[[#This Row],[DON_indic]]=2),"Unknown", IF(AND(Table2[[#This Row],[RRA_indic]]=1, Table2[[#This Row],[EIS_indic]]=1, Table2[[#This Row],[DON_indic]]=1), "Open RRA, EIS, DON", IF(AND(Table2[[#This Row],[RRA_indic]]=1, Table2[[#This Row],[EIS_indic]]=1), "Open RRA, EIS", IF(AND(Table2[[#This Row],[RRA_indic]]=1, Table2[[#This Row],[DON_indic]]=1), "Open RRA, DON", IF(AND(Table2[[#This Row],[EIS_indic]]=1, Table2[[#This Row],[DON_indic]]=1), "Open EIS, DON", IF(Table2[[#This Row],[RRA_indic]]=1, "Open RRA", IF(Table2[[#This Row],[EIS_indic]]=1, "Open EIS", "Open DON")))))))))))))))} -> All Products done | D6: Dunja | E6: Undiagnosed disease - suspected Viral Hemorrhagic Fever | F6: Sao Tome and Principe | G6: Not applicable | I6: Not applicable | M6: No | P6: No | Q6: Not applicable | S6: Not applicable | U6: Not applicable | V6: Not applicable | W6: Not applicable | X6: Not applicable | Y6: No | Z6: Not applicable | AC6: Not applicable | AD6: Not applicable | AE6: Not applicable | AF6: Not applicable | AG6: Not applicable | AH6: Not applicable | AI6: No | AM6: =VLOOKUP(Table2[[#This Row],[country]],Countrycode!A:B,2,FALSE) -> STP | AN6: =IF(ISBLANK(Table2[[#This Row],[Need_RRA]]), 2,(IF(Table2[[#This Row],[Need_RRA]]="No", 0, (IF(AND(Table2[[#This Row],[Need_RRA]]="Yes", Table2[[#This Row],[RRA_pub_date]]=""),1, 0))))) -> 0 | AO6: =IF(ISBLANK(Table2[[#This Row],[Need_EIS]]), 2,(IF(Table2[[#This Row],[Need_EIS]]="No", 0, (IF(AND(Table2[[#This Row],[Need_EIS]]="Yes", Table2[[#This Row],[EIS_pub_date]]=""),1, 0))))) -> 0 | AP6: =IF(ISBLANK(Table2[[#This Row],[Need_DON]]), 2,(IF(Table2[[#This Row],[Need_DON]]="No", 0, (IF(AND(Table2[[#This Row],[Need_DON]]="Yes", Table2[[#This Row],[DON_pub_date]]=""),1, 0))))) -> 0 | AQ6: =IF(ISBLANK(Table2[[#This Row],[Pending_question]]), 2,(IF(Table2[[#This Row],[Pending_question]]="Yes", 1, 0))) -> 0
A7: 44322 | B7: Closed | C7: {=IF(SUM(Table2[[#This Row],[PQ_indic]],Table2[[#This Row],[RRA_indic]],Table2[[#This Row],[EIS_indic]],Table2[[#This Row],[DON_indic]])=8, "Missing data", (IF(AND(Table2[[#This Row],[Pending_question]]="Yes", OR( Table2[[#This Row],[Need_RRA]]="No", ISBLANK(Table2[[#This Row],[Need_RRA]])), OR(Table2[[#This Row],[Need_EIS]]="No", ISBLANK(Table2[[#This Row],[Need_EIS]])), OR(Table2[[#This Row],[Need_DON]]="No", ISBLANK(Table2[[#This Row],[Need_DON]]) )),"Question, no products",( IF( AND(Table2[[#This Row],[Pending_question]]="Yes", ISBLANK(Table2[[#This Row],[PQ_closure_date]])), (IF(SUM(Table2[[#This Row],[RRA_indic]],Table2[[#This Row],[EIS_indic]],Table2[[#This Row],[DON_indic]])=0, "Open Question, all products done",(I447IF(OR(Table2[[#This Row],[RRA_indic]]=2, Table2[[#This Row],[EIS_indic]]=2, Table2[[#This Row],[DON_indic]]=2),"Question, Products unknown",IF(AND(Table2[[#This Row],[RRA_indic]]=1, Table2[[#This Row],[EIS_indic]]=1, Table2[[#This Row],[DON_indic]]=1), "Open Question, RRA, EIS, DON", IF(AND(Table2[[#This Row],[RRA_indic]]=1, Table2[[#This Row],[EIS_indic]]=1), "Open Question, RRA, EIS",IF(AND(Table2[[#This Row],[RRA_indic]]=1, Table2[[#This Row],[DON_indic]]=1), "Open Question, RRA, DON", IF(AND(Table2[[#This Row],[EIS_indic]]=1, Table2[[#This Row],[DON_indic]]=1), "Open Question, EIS, DON",IF(Table2[[#This Row],[RRA_indic]]=1, "Open Question, RRA", IF(Table2[[#This Row],[EIS_indic]]=1, "Open Question, EIS", "Open Question, DON")))))))))), (IF(SUM(Table2[[#This Row],[RRA_indic]],Table2[[#This Row],[EIS_indic]],Table2[[#This Row],[DON_indic]])=0, "All Products done",(IF(OR(Table2[[#This Row],[RRA_indic]]=2, Table2[[#This Row],[EIS_indic]]=2, Table2[[#This Row],[DON_indic]]=2),"Unknown", IF(AND(Table2[[#This Row],[RRA_indic]]=1, Table2[[#This Row],[EIS_indic]]=1, Table2[[#This Row],[DON_indic]]=1), "Open RRA, EIS, DON", IF(AND(Table2[[#This Row],[RRA_indic]]=1, Table2[[#This Row],[EIS_indic]]=1), "Open RRA, EIS", IF(AND(Table2[[#This Row],[RRA_indic]]=1, Table2[[#This Row],[DON_indic]]=1), "Open RRA, DON", IF(AND(Table2[[#This Row],[EIS_indic]]=1, Table2[[#This Row],[DON_indic]]=1), "Open EIS, DON", IF(Table2[[#This Row],[RRA_indic]]=1, "Open RRA", IF(Table2[[#This Row],[EIS_indic]]=1, "Open EIS", "Open DON")))))))))))))))} -> All Products done | D7: Anastasia | E7: Cholera | F7: Yemen | G7: Not applicable | K7: 2017-E000187 | M7: No | P7: Yes | R7: disseminated | S7: 44322 | U7: 44364 | Y7: no | AB7: 21 June: not planned | AI7: no | AM7: =VLOOKUP(Table2[[#This Row],[country]],Countrycode!A:B,2,FALSE) -> YEM | AN7: =IF(ISBLANK(Table2[[#This Row],[Need_RRA]]), 2,(IF(Table2[[#This Row],[Need_RRA]]="No", 0, (IF(AND(Table2[[#This Row],[Need_RRA]]="Yes", Table2[[#This Row],[RRA_pub_date]]=""),1, 0))))) -> 0 | AO7: =IF(ISBLANK(Table2[[#This Row],[Need_EIS]]), 2,(IF(Table2[[#This Row],[Need_EIS]]="No", 0, (IF(AND(Table2[[#This Row],[Need_EIS]]="Yes", Table2[[#This Row],[EIS_pub_date]]=""),1, 0))))) -> 0 | AP7: =IF(ISBLANK(Table2[[#This Row],[Need_DON]]), 2,(IF(Table2[[#This Row],[Need_DON]]="No", 0, (IF(AND(Table2[[#This Row],[Need_DON]]="Yes", Table2[[#This Row],[DON_pub_date]]=""),1, 0))))) -> 0 | AQ7: =IF(ISBLANK(Table2[[#This Row],[Pending_question]]), 2,(IF(Table2[[#This Row],[Pending_question]]="Yes", 1, 0))) -> 0
A8: 44328 | B8: Closed | C8: {=IF(SUM(Table2[[#This Row],[PQ_indic]],Table2[[#This Row],[RRA_indic]],Table2[[#This Row],[EIS_indic]],Table2[[#This Row],[DON_indic]])=8, "Missing data", (IF(AND(Table2[[#This Row],[Pending_question]]="Yes", OR( Table2[[#This Row],[Need_RRA]]="No", ISBLANK(Table2[[#This Row],[Need_RRA]])), OR(Table2[[#This Row],[Need_EIS]]="No", ISBLANK(Table2[[#This Row],[Need_EIS]])), OR(Table2[[#This Row],[Need_DON]]="No", ISBLANK(Table2[[#This Row],[Need_DON]]) )),"Question, no products",( IF( AND(Table2[[#This Row],[Pending_question]]="Yes", ISBLANK(Table2[[#This Row],[PQ_closure_date]])), (IF(SUM(Table2[[#This Row],[RRA_indic]],Table2[[#This Row],[EIS_indic]],Table2[[#This Row],[DON_indic]])=0, "Open Question, all products done",(I447IF(OR(Table2[[#This Row],[RRA_indic]]=2, Table2[[#This Row],[EIS_indic]]=2, Table2[[#This Row],[DON_indic]]=2),"Question, Products unknown",IF(AND(Table2[[#This Row],[RRA_indic]]=1, Table2[[#This Row],[EIS_indic]]=1, Table2[[#This Row],[DON_indic]]=1), "Open Question, RRA, EIS, DON", IF(AND(Table2[[#This Row],[RRA_indic]]=1, Table2[[#This Row],[EIS_indic]]=1), "Open Question, RRA, EIS",IF(AND(Table2[[#This Row],[RRA_indic]]=1, Table2[[#This Row],[DON_indic]]=1), "Open Question, RRA, DON", IF(AND(Table2[[#This Row],[EIS_indic]]=1, Table2[[#This Row],[DON_indic]]=1), "Open Question, EIS, DON",IF(Table2[[#This Row],[RRA_indic]]=1, "Open Question, RRA", IF(Table2[[#This Row],[EIS_indic]]=1, "Open Question, EIS", "Open Question, DON")))))))))), (IF(SUM(Table2[[#This Row],[RRA_indic]],Table2[[#This Row],[EIS_indic]],Table2[[#This Row],[DON_indic]])=0, "All Products done",(IF(OR(Table2[[#This Row],[RRA_indic]]=2, Table2[[#This Row],[EIS_indic]]=2, Table2[[#This Row],[DON_indic]]=2),"Unknown", IF(AND(Table2[[#This Row],[RRA_indic]]=1, Table2[[#This Row],[EIS_indic]]=1, Table2[[#This Row],[DON_indic]]=1), "Open RRA, EIS, DON", IF(AND(Table2[[#This Row],[RRA_indic]]=1, Table2[[#This Row],[EIS_indic]]=1), "Open RRA, EIS", IF(AND(Table2[[#This Row],[RRA_indic]]=1, Table2[[#This Row],[DON_indic]]=1), "Open RRA, DON", IF(AND(Table2[[#This Row],[EIS_indic]]=1, Table2[[#This Row],[DON_indic]]=1), "Open EIS, DON", IF(Table2[[#This Row],[RRA_indic]]=1, "Open RRA", IF(Table2[[#This Row],[EIS_indic]]=1, "Open EIS", "Open DON")))))))))))))))} -> All Products done | D8: Anastasia | E8: Cholera | F8: Nigeria | G8: Not applicable | H8: 44328 | I8: 44342 | J8: 44336 | K8: 2021-E000172 | M8: No | P8: Yes | Q8: 1 | R8: disseminated | S8: 44344 | U8: 44357 | V8: High | W8: Moderate | X8: Low | Y8: yes | Z8: New EIS | AB8: 15 June: First draft shared with TT and TT provided comment/ 16 June: draft shared with AFRO and WCO Inputs expected by COB 17 June. Published on 21 June | AC8: 44362 | AE8: 44363 | AG8: 44368 | AH8: 44368 | AI8: no | AM8: =VLOOKUP(Table2[[#This Row],[country]],Countrycode!A:B,2,FALSE) -> NGA | AN8: =IF(ISBLANK(Table2[[#This Row],[Need_RRA]]), 2,(IF(Table2[[#This Row],[Need_RRA]]="No", 0, (IF(AND(Table2[[#This Row],[Need_RRA]]="Yes", Table2[[#This Row],[RRA_pub_date]]=""),1, 0))))) -> 0 | AO8: =IF(ISBLANK(Table2[[#This Row],[Need_EIS]]), 2,(IF(Table2[[#This Row],[Need_EIS]]="No", 0, (IF(AND(Table2[[#This Row],[Need_EIS]]="Yes", Table2[[#This Row],[EIS_pub_date]]=""),1, 0))))) -> 0 | AP8: =IF(ISBLANK(Table2[[#This Row],[Need_DON]]), 2,(IF(Table2[[#This Row],[Need_DON]]="No", 0, (IF(AND(Table2[[#This Row],[Need_DON]]="Yes", Table2[[#This Row],[DON_pub_date]]=""),1, 0))))) -> 0 | AQ8: =IF(ISBLANK(Table2[[#This Row],[Pending_question]]), 2,(IF(Table2[[#This Row],[Pending_question]]="Yes", 1, 0))) -> 0
A9: 44344 | B9: Closed | C9: {=IF(SUM(Table2[[#This Row],[PQ_indic]],Table2[[#This Row],[RRA_indic]],Table2[[#This Row],[EIS_indic]],Table2[[#This Row],[DON_indic]])=8, "Missing data", (IF(AND(Table2[[#This Row],[Pending_question]]="Yes", OR( Table2[[#This Row],[Need_RRA]]="No", ISBLANK(Table2[[#This Row],[Need_RRA]])), OR(Table2[[#This Row],[Need_EIS]]="No", ISBLANK(Table2[[#This Row],[Need_EIS]])), OR(Table2[[#This Row],[Need_DON]]="No", ISBLANK(Table2[[#This Row],[Need_DON]]) )),"Question, no products",( IF( AND(Table2[[#This Row],[Pending_question]]="Yes", ISBLANK(Table2[[#This Row],[PQ_closure_date]])), (IF(SUM(Table2[[#This Row],[RRA_indic]],Table2[[#This Row],[EIS_indic]],Table2[[#This Row],[DON_indic]])=0, "Open Question, all products done",(I447IF(OR(Table2[[#This Row],[RRA_indic]]=2, Table2[[#This Row],[EIS_indic]]=2, Table2[[#This Row],[DON_indic]]=2),"Question, Products unknown",IF(AND(Table2[[#This Row],[RRA_indic]]=1, Table2[[#This Row],[EIS_indic]]=1, Table2[[#This Row],[DON_indic]]=1), "Open Question, RRA, EIS, DON", IF(AND(Table2[[#This Row],[RRA_indic]]=1, Table2[[#This Row],[EIS_indic]]=1), "Open Question, RRA, EIS",IF(AND(Table2[[#This Row],[RRA_indic]]=1, Table2[[#This Row],[DON_indic]]=1), "Open Question, RRA, DON", IF(AND(Table2[[#This Row],[EIS_indic]]=1, Table2[[#This Row],[DON_indic]]=1), "Open Question, EIS, DON",IF(Table2[[#This Row],[RRA_indic]]=1, "Open Question, RRA", IF(Table2[[#This Row],[EIS_indic]]=1, "Open Question, EIS", "Open Question, DON")))))))))), (IF(SUM(Table2[[#This Row],[RRA_indic]],Table2[[#This Row],[EIS_indic]],Table2[[#This Row],[DON_indic]])=0, "All Products done",(IF(OR(Table2[[#This Row],[RRA_indic]]=2, Table2[[#This Row],[EIS_indic]]=2, Table2[[#This Row],[DON_indic]]=2),"Unknown", IF(AND(Table2[[#This Row],[RRA_indic]]=1, Table2[[#This Row],[EIS_indic]]=1, Table2[[#This Row],[DON_indic]]=1), "Open RRA, EIS, DON", IF(AND(Table2[[#This Row],[RRA_indic]]=1, Table2[[#This Row],[EIS_indic]]=1), "Open RRA, EIS", IF(AND(Table2[[#This Row],[RRA_indic]]=1, Table2[[#This Row],[DON_indic]]=1), "Open RRA, DON", IF(AND(Table2[[#This Row],[EIS_indic]]=1, Table2[[#This Row],[DON_indic]]=1), "Open EIS, DON", IF(Table2[[#This Row],[RRA_indic]]=1, "Open RRA", IF(Table2[[#This Row],[EIS_indic]]=1, "Open EIS", "Open DON")))))))))))))))} -> All Products done | D9: Lidia/Anastasia | E9: Plague | F9: Democratic Republic of the Congo | G9: Not applicable | K9: 2019-E000123 | M9: No | P9: Yes | R9: 18 June 2021: distributed | S9: 44344 | U9: 44365 | Y9: yes | AB9: 15 June: draft shared with AFRO and HQ colleagues/18 June: feedback from AFRO received . Awaiting WCO inputs /20 June: Reminder sent / 23 June: IHR NFP feedback received / 27 June: EIS posted | AH9: 44374 | AI9: no | AM9: =VLOOKUP(Table2[[#This Row],[country]],Countrycode!A:B,2,FALSE) -> COD | AN9: =IF(ISBLANK(Table2[[#This Row],[Need_RRA]]), 2,(IF(Table2[[#This Row],[Need_RRA]]="No", 0, (IF(AND(Table2[[#This Row],[Need_RRA]]="Yes", Table2[[#This Row],[RRA_pub_date]]=""),1, 0))))) -> 0 | AO9: =IF(ISBLANK(Table2[[#This Row],[Need_EIS]]), 2,(IF(Table2[[#This Row],[Need_EIS]]="No", 0, (IF(AND(Table2[[#This Row],[Need_EIS]]="Yes", Table2[[#This Row],[EIS_pub_date]]=""),1, 0))))) -> 0 | AP9: =IF(ISBLANK(Table2[[#This Row],[Need_DON]]), 2,(IF(Table2[[#This Row],[Need_DON]]="No", 0, (IF(AND(Table2[[#This Row],[Need_DON]]="Yes", Table2[[#This Row],[DON_pub_date]]=""),1, 0))))) -> 0 | AQ9: =IF(ISBLANK(Table2[[#This Row],[Pending_question]]), 2,(IF(Table2[[#This Row],[Pending_question]]="Yes", 1, 0))) -> 0
A10: 44357 | B10: Closed | C10: {=IF(SUM(Table2[[#This Row],[PQ_indic]],Table2[[#This Row],[RRA_indic]],Table2[[#This Row],[EIS_indic]],Table2[[#This Row],[DON_indic]])=8, "Missing data", (IF(AND(Table2[[#This Row],[Pending_question]]="Yes", OR( Table2[[#This Row],[Need_RRA]]="No", ISBLANK(Table2[[#This Row],[Need_RRA]])), OR(Table2[[#This Row],[Need_EIS]]="No", ISBLANK(Table2[[#This Row],[Need_EIS]])), OR(Table2[[#This Row],[Need_DON]]="No", ISBLANK(Table2[[#This Row],[Need_DON]]) )),"Question, no products",( IF( AND(Table2[[#This Row],[Pending_question]]="Yes", ISBLANK(Table2[[#This Row],[PQ_closure_date]])), (IF(SUM(Table2[[#This Row],[RRA_indic]],Table2[[#This Row],[EIS_indic]],Table2[[#This Row],[DON_indic]])=0, "Open Question, all products done",(I447IF(OR(Table2[[#This Row],[RRA_indic]]=2, Table2[[#This Row],[EIS_indic]]=2, Table2[[#This Row],[DON_indic]]=2),"Question, Products unknown",IF(AND(Table2[[#This Row],[RRA_indic]]=1, Table2[[#This Row],[EIS_indic]]=1, Table2[[#This Row],[DON_indic]]=1), "Open Question, RRA, EIS, DON", IF(AND(Table2[[#This Row],[RRA_indic]]=1, Table2[[#This Row],[EIS_indic]]=1), "Open Question, RRA, EIS",IF(AND(Table2[[#This Row],[RRA_indic]]=1, Table2[[#This Row],[DON_indic]]=1), "Open Question, RRA, DON", IF(AND(Table2[[#This Row],[EIS_indic]]=1, Table2[[#This Row],[DON_indic]]=1), "Open Question, EIS, DON",IF(Table2[[#This Row],[RRA_indic]]=1, "Open Question, RRA", IF(Table2[[#This Row],[EIS_indic]]=1, "Open Question, EIS", "Open Question, DON")))))))))), (IF(SUM(Table2[[#This Row],[RRA_indic]],Table2[[#This Row],[EIS_indic]],Table2[[#This Row],[DON_indic]])=0, "All Products done",(IF(OR(Table2[[#This Row],[RRA_indic]]=2, Table2[[#This Row],[EIS_indic]]=2, Table2[[#This Row],[DON_indic]]=2),"Unknown", IF(AND(Table2[[#This Row],[RRA_indic]]=1, Table2[[#This Row],[EIS_indic]]=1, Table2[[#This Row],[DON_indic]]=1), "Open RRA, EIS, DON", IF(AND(Table2[[#This Row],[RRA_indic]]=1, Table2[[#This Row],[EIS_indic]]=1), "Open RRA, EIS", IF(AND(Table2[[#This Row],[RRA_indic]]=1, Table2[[#This Row],[DON_indic]]=1), "Open RRA, DON", IF(AND(Table2[[#This Row],[EIS_indic]]=1, Table2[[#This Row],[DON_indic]]=1), "Open EIS, DON", IF(Table2[[#This Row],[RRA_indic]]=1, "Open RRA", IF(Table2[[#This Row],[EIS_indic]]=1, "Open EIS", "Open DON")))))))))))))))} -> All Products done | D10: Lidia | E10: Zika | F10: India | G10: Not applicable | H10: 09 June, 11 June | J10: 44357 | K10: 2021-E000253 | M10: No | P10: Yes | R10: 12 July 2021: Not Planned / 15 July: we need one RRA / 16 July: 3LTC: no RRA for the moment as the magnitude of the event is not clear, "we need more data and information" Email requesting 3LTC and further discussion sent on 26 July./ 28 July: SEARO agreed to have a RRA, CO will draft it. 30 July - 1st Draft RRA received by SEARO. Shared with the TTHQ. Deadline 11am on Tuesday, 2 August. RRA with major adjustments shared back with SEARO on 5 August and requested for 3 LTC. / 5 August received inputs by TT tha have been incorportaed to the final draft. On 9 August a follow up email sent regarding the status of the RRA and EIS with proposition for a 3LTC. Replied recieved on 10 August - the comments of the RRA will be addressed and decline of the 3 LTC at this stage. RRA draft received on 11 August by SEARO with some of the comments addressed in the document. 3LTC held on 17 August. RRA dissseminated on 17 August. | S10: 44407 | U10: 44425 | Y10: yes | AB10: 15 July: we need an EIS / 16 July: CO will draft an EIS, check the deadline / 20 July: reminder sent to SEARO and SEARO shared the draft with NCDC / 22 July: EIS still pending draft from WCO / 26 July: still waiting inputs from NCDC.SEARO replied on 26 July that they are expecting the draft to be likely approved by the evening of 26 July 2021. On 28 July, SEARO provided epi update and stated theat the EIS is with the MoH for clearance. We have requested the EIS draft, as it hasn't been shared with HQ +TT, for further inputs, prior to the accuracy check. EIS received on 29 July and shared with the TT for further inputs by 3PM on 29 July. Draft EIS with HQ inputs sent back to SEARO by COB on 29 July. Final draft EIS sent for NFP concurrence on 30 July.On 9 August a follow up email sent regarding the status of the RRA and EIS with proposition for a 3LTC, as the EIS is already outdated. Replied received from SEARO on 10 August, WCO and RO, just had a call this morning. WCO colleagues have kindly agreed to address the pending comments and share a new draft as soon as possible. With this in mind, and given the many other competing priorities, we would like to politely decline the invitation for a 3LTC today. Specifically on the contents, WCO colleagues will add the latest information on the subtype from vectors and human samples. With regard to the status of the EIS, WCO is in regular contact with national counterparts. Following the 3LTC on 17 August, it was agreed that PHI will update the EIS draft , including the 2nd state and will share back with WCO for NFP concurrence. 27 August: The old EIS received with withe the NFP concurrence. 3 September: a new version of the EIS has been drafted by PHI and shared for comments at HQ level . 6 September: EIS draft shared with SEARO. Awaiting SEARO to address the pending comments, prior to sharing with the NFP.10 September: Final EIS sent back to SEARO for NFP concurrence. 15 September: Reminder sent to SEARO. / 16 September: reminder to SEARO by Emilie / 20 Sep: SEARO replied that NFP/NCDC does not concur with the classification of the event as presenting a serious pubic health impact. Their reply: “Further to our discussion and as directed by the Director, NCDC, the justification for RA for Zika is as given below: Serious Public Health Impact – No Majority of people infected with Zika virus do not develop symptoms and even those who are symptomatic develop only mild symptoms lasting for 2-7 days. India is endemic for dengue, therefore, the health system is well geared to manage and respond to any unprecedented surge in Zika cases, which has almost similar presentation as dengue. There is an increased risk of neurologic complications associated with Zika virus infection in adults and children, including Guillain-Barré syndrome, neuropathy and myelitis. Although the current evidence available from the previous Zika outbreaks in the country, has not shown any conclusive evidence on Zika induced microcephaly. Therefore, the risk has been classified as low for serious public health impact. This is for info and na pls.” 21 Sptember: TC proposed for 22 September to WCO for further agreement on the EIS.22 September: 3LTC held.Outputs - Ritu will send to outbreak the EIS with comments from the NFP an update of the situation. Diana and Lidia will compile the information and update the EIS, they will circulate the EIS with SEARO and CO for final clearance (we will not go through IHR NFP) Agreed to have: *no" to IHR criteria #1 but nuanced text, an updated description of the situation, a DON will follow. Reassess the situation in a couple of months. Emilie has sent the EIS guidance to Ritu. Need trainings on RA and EIS: Lidia and Emilie to see what is feasible. On 24 September meeting held. Training materials are being prepared by LIdia in the week of 27 september. 27 September: TT shared with the RO and WCO group the preprint article for the Zika event. 29 September escaleted to the SM. 30 September: RED contacted / 4 October: EIS posting is cleared but not posted yet because of the EIS technical issues / 5 October: EIS posted | AH10: 44474 | AI10: yes | AK10: 44483 | AL10: 12 July: email sent to SEARO and TT to informaly assess the situation / 15 July: email received from TT with additional information, the situation is concerning, we need RRA and EIS. After the TC on 16 July, there is no need for RRA at the moment. | AM10: =VLOOKUP(Table2[[#This Row],[country]],Countrycode!A:B,2,FALSE) -> IND | AN10: =IF(ISBLANK(Table2[[#This Row],[Need_RRA]]), 2,(IF(Table2[[#This Row],[Need_RRA]]="No", 0, (IF(AND(Table2[[#This Row],[Need_RRA]]="Yes", Table2[[#This Row],[RRA_pub_date]]=""),1, 0))))) -> 0 | AO10: =IF(ISBLANK(Table2[[#This Row],[Need_EIS]]), 2,(IF(Table2[[#This Row],[Need_EIS]]="No", 0, (IF(AND(Table2[[#This Row],[Need_EIS]]="Yes", Table2[[#This Row],[EIS_pub_date]]=""),1, 0))))) -> 0 | AP10: =IF(ISBLANK(Table2[[#This Row],[Need_DON]]), 2,(IF(Table2[[#This Row],[Need_DON]]="No", 0, (IF(AND(Table2[[#This Row],[Need_DON]]="Yes", Table2[[#This Row],[DON_pub_date]]=""),1, 0))))) -> 0 | AQ10: =IF(ISBLANK(Table2[[#This Row],[Pending_question]]), 2,(IF(Table2[[#This Row],[Pending_question]]="Yes", 1, 0))) -> 0 | AR10: 09 June, 11 June
A11: 44358 | B11: Closed | C11: {=IF(SUM(Table2[[#This Row],[PQ_indic]],Table2[[#This Row],[RRA_indic]],Table2[[#This Row],[EIS_indic]],Table2[[#This Row],[DON_indic]])=8, "Missing data", (IF(AND(Table2[[#This Row],[Pending_question]]="Yes", OR( Table2[[#This Row],[Need_RRA]]="No", ISBLANK(Table2[[#This Row],[Need_RRA]])), OR(Table2[[#This Row],[Need_EIS]]="No", ISBLANK(Table2[[#This Row],[Need_EIS]])), OR(Table2[[#This Row],[Need_DON]]="No", ISBLANK(Table2[[#This Row],[Need_DON]]) )),"Question, no products",( IF( AND(Table2[[#This Row],[Pending_question]]="Yes", ISBLANK(Table2[[#This Row],[PQ_closure_date]])), (IF(SUM(Table2[[#This Row],[RRA_indic]],Table2[[#This Row],[EIS_indic]],Table2[[#This Row],[DON_indic]])=0, "Open Question, all products done",(I447IF(OR(Table2[[#This Row],[RRA_indic]]=2, Table2[[#This Row],[EIS_indic]]=2, Table2[[#This Row],[DON_indic]]=2),"Question, Products unknown",IF(AND(Table2[[#This Row],[RRA_indic]]=1, Table2[[#This Row],[EIS_indic]]=1, Table2[[#This Row],[DON_indic]]=1), "Open Question, RRA, EIS, DON", IF(AND(Table2[[#This Row],[RRA_indic]]=1, Table2[[#This Row],[EIS_indic]]=1), "Open Question, RRA, EIS",IF(AND(Table2[[#This Row],[RRA_indic]]=1, Table2[[#This Row],[DON_indic]]=1), "Open Question, RRA, DON", IF(AND(Table2[[#This Row],[EIS_indic]]=1, Table2[[#This Row],[DON_indic]]=1), "Open Question, EIS, DON",IF(Table2[[#This Row],[RRA_indic]]=1, "Open Question, RRA", IF(Table2[[#This Row],[EIS_indic]]=1, "Open Question, EIS", "Open Question, DON")))))))))), (IF(SUM(Table2[[#This Row],[RRA_indic]],Table2[[#This Row],[EIS_indic]],Table2[[#This Row],[DON_indic]])=0, "All Products done",(IF(OR(Table2[[#This Row],[RRA_indic]]=2, Table2[[#This Row],[EIS_indic]]=2, Table2[[#This Row],[DON_indic]]=2),"Unknown", IF(AND(Table2[[#This Row],[RRA_indic]]=1, Table2[[#This Row],[EIS_indic]]=1, Table2[[#This Row],[DON_indic]]=1), "Open RRA, EIS, DON", IF(AND(Table2[[#This Row],[RRA_indic]]=1, Table2[[#This Row],[EIS_indic]]=1), "Open RRA, EIS", IF(AND(Table2[[#This Row],[RRA_indic]]=1, Table2[[#This Row],[DON_indic]]=1), "Open RRA, DON", IF(AND(Table2[[#This Row],[EIS_indic]]=1, Table2[[#This Row],[DON_indic]]=1), "Open EIS, DON", IF(Table2[[#This Row],[RRA_indic]]=1, "Open RRA", IF(Table2[[#This Row],[EIS_indic]]=1, "Open EIS", "Open DON")))))))))))))))} -> All Products done | D11: Etsub | E11: Avian influenza A (H1N2) | F11: China, Province of Taiwan | G11: Not applicable | H11: 44358 | J11: 44356 | M11: No | P11: No | Q11: Not applicable | R11: No RRA | Y11: yes | AB11: Comments from IHR secretariat received from Fernando on 14 June. Further guidance on how to proceed pending from LEG. Reminder sent to LEG on 17 June, Input received from LEG on 18 June. Reminder sent to LEG for the guidance on the way how to get a consultation for the document. A follow up meeting with LEG and IHR conducted on 23 June. Pending LEG’s advice on how to proceed with this 23 June / 28 June: LEG replied, they are exploring how to proceed with IHR NFP consultation / 29 June: LEG replied: they will consult with the with relevant officials on 30 June / published on 2 July | AH11: 44379 | AI11: no | AL11: we don’t know how to proceed with NFP consultation, LEG does not reply. LEG is going to reply by COB 1 July 2021. LEG gave a green light for posting. It will be posted on 1 July. | AM11: =VLOOKUP(Table2[[#This Row],[country]],Countrycode!A:B,2,FALSE) -> TWN | AN11: =IF(ISBLANK(Table2[[#This Row],[Need_RRA]]), 2,(IF(Table2[[#This Row],[Need_RRA]]="No", 0, (IF(AND(Table2[[#This Row],[Need_RRA]]="Yes", Table2[[#This Row],[RRA_pub_date]]=""),1, 0))))) -> 0 | AO11: =IF(ISBLANK(Table2[[#This Row],[Need_EIS]]), 2,(IF(Table2[[#This Row],[Need_EIS]]="No", 0, (IF(AND(Table2[[#This Row],[Need_EIS]]="Yes", Table2[[#This Row],[EIS_pub_date]]=""),1, 0))))) -> 0 | AP11: =IF(ISBLANK(Table2[[#This Row],[Need_DON]]), 2,(IF(Table2[[#This Row],[Need_DON]]="No", 0, (IF(AND(Table2[[#This Row],[Need_DON]]="Yes", Table2[[#This Row],[DON_pub_date]]=""),1, 0))))) -> 0 | AQ11: =IF(ISBLANK(Table2[[#This Row],[Pending_question]]), 2,(IF(Table2[[#This Row],[Pending_question]]="Yes", 1, 0))) -> 0 | AR11: 44358
A12: 44361 | B12: Closed | C12: {=IF(SUM(Table2[[#This Row],[PQ_indic]],Table2[[#This Row],[RRA_indic]],Table2[[#This Row],[EIS_indic]],Table2[[#This Row],[DON_indic]])=8, "Missing data", (IF(AND(Table2[[#This Row],[Pending_question]]="Yes", OR( Table2[[#This Row],[Need_RRA]]="No", ISBLANK(Table2[[#This Row],[Need_RRA]])), OR(Table2[[#This Row],[Need_EIS]]="No", ISBLANK(Table2[[#This Row],[Need_EIS]])), OR(Table2[[#This Row],[Need_DON]]="No", ISBLANK(Table2[[#This Row],[Need_DON]]) )),"Question, no products",( IF( AND(Table2[[#This Row],[Pending_question]]="Yes", ISBLANK(Table2[[#This Row],[PQ_closure_date]])), (IF(SUM(Table2[[#This Row],[RRA_indic]],Table2[[#This Row],[EIS_indic]],Table2[[#This Row],[DON_indic]])=0, "Open Question, all products done",(I447IF(OR(Table2[[#This Row],[RRA_indic]]=2, Table2[[#This Row],[EIS_indic]]=2, Table2[[#This Row],[DON_indic]]=2),"Question, Products unknown",IF(AND(Table2[[#This Row],[RRA_indic]]=1, Table2[[#This Row],[EIS_indic]]=1, Table2[[#This Row],[DON_indic]]=1), "Open Question, RRA, EIS, DON", IF(AND(Table2[[#This Row],[RRA_indic]]=1, Table2[[#This Row],[EIS_indic]]=1), "Open Question, RRA, EIS",IF(AND(Table2[[#This Row],[RRA_indic]]=1, Table2[[#This Row],[DON_indic]]=1), "Open Question, RRA, DON", IF(AND(Table2[[#This Row],[EIS_indic]]=1, Table2[[#This Row],[DON_indic]]=1), "Open Question, EIS, DON",IF(Table2[[#This Row],[RRA_indic]]=1, "Open Question, RRA", IF(Table2[[#This Row],[EIS_indic]]=1, "Open Question, EIS", "Open Question, DON")))))))))), (IF(SUM(Table2[[#This Row],[RRA_indic]],Table2[[#This Row],[EIS_indic]],Table2[[#This Row],[DON_indic]])=0, "All Products done",(IF(OR(Table2[[#This Row],[RRA_indic]]=2, Table2[[#This Row],[EIS_indic]]=2, Table2[[#This Row],[DON_indic]]=2),"Unknown", IF(AND(Table2[[#This Row],[RRA_indic]]=1, Table2[[#This Row],[EIS_indic]]=1, Table2[[#This Row],[DON_indic]]=1), "Open RRA, EIS, DON", IF(AND(Table2[[#This Row],[RRA_indic]]=1, Table2[[#This Row],[EIS_indic]]=1), "Open RRA, EIS", IF(AND(Table2[[#This Row],[RRA_indic]]=1, Table2[[#This Row],[DON_indic]]=1), "Open RRA, DON", IF(AND(Table2[[#This Row],[EIS_indic]]=1, Table2[[#This Row],[DON_indic]]=1), "Open EIS, DON", IF(Table2[[#This Row],[RRA_indic]]=1, "Open RRA", IF(Table2[[#This Row],[EIS_indic]]=1, "Open EIS", "Open DON")))))))))))))))} -> All Products done | D12: Lida/Elvis | E12: Yellow Fever | F12: Cameroon | G12: Not applicable | K12: 2021-E000046 | M12: No | P12: Yes | R12: Proposal for an RRA sent to AFRO on 15 June. AFRO agreed to the proposal on 16 June. Awaiting approval from WCO. Drafted by CO, shared with AFRO, should be shared with HQ on 29 June/29 July: RRA shares with HQ/30 July: HQ adds inputs and disseminates to TT/01 July: TT adds inputs/02 July: Version from HQ+TT sent back to AFRO. Feedback expected by COB on 05 July. / 7 July: sent back to AFRO, still waiting for CO update (reminder sent on 6 July)/ 9 July: waiting for AFRO's feedback / 12 July: reply from CO / 13 July: reply recieved from WCO & AFRO, reshared with Emilie for review/14 July: to share with TT for review/16 July: RRA sent back to AFRO and WCO to address pending comments / 19 July: Feedback expected by COB Monday 19 July / 20 July: WCO and AFRO shared revised version. Risk level at national level assessed as HIGH /21 July: To share consolidated version with Esther for clearance by COB. / 23 July: disseminated | S12: 44361 | U12: 44400 | Y12: yes | AB12: 5 July: no EIS planned / 19 July: EIS planned after RRA is completed/27 July: initiated discussions on the EIS. AFRO suggested to contact WCO to get their opinion before proceding with the draft EIS in French and English. Initial draft (french and english version) shared by AFRO on 3 August. Inputs reuested from HQ TT by 1pm on 4 August.Shared back with AFRO on 5 August. Final consolidated draft EIS recieved from AFRO on 9 August. Following final clearance sent back to AFRO for NFP consultation on xx August/12 August: WCO&AFRO addressed comments/13 August: Final cleared version sent to AFRO for NFP consultation./18 August: Remider regarding the NFP concurence sent to AFRo. Reminder sent on 20 and 24 August. Folllow up sent on 26 August. /27 August: EIS posted. Reminder sent to AFRO on 30 August for the french version of the EIS. Reply received on 31 Agust that they will share soon. | AH12: 44435 | AI12: no | AL12: MOH was busy with the pilgrim season in the last two weeks | AM12: =VLOOKUP(Table2[[#This Row],[country]],Countrycode!A:B,2,FALSE) -> CMR | AN12: =IF(ISBLANK(Table2[[#This Row],[Need_RRA]]), 2,(IF(Table2[[#This Row],[Need_RRA]]="No", 0, (IF(AND(Table2[[#This Row],[Need_RRA]]="Yes", Table2[[#This Row],[RRA_pub_date]]=""),1, 0))))) -> 0 | AO12: =IF(ISBLANK(Table2[[#This Row],[Need_EIS]]), 2,(IF(Table2[[#This Row],[Need_EIS]]="No", 0, (IF(AND(Table2[[#This Row],[Need_EIS]]="Yes", Table2[[#This Row],[EIS_pub_date]]=""),1, 0))))) -> 0 | AP12: =IF(ISBLANK(Table2[[#This Row],[Need_DON]]), 2,(IF(Table2[[#This Row],[Need_DON]]="No", 0, (IF(AND(Table2[[#This Row],[Need_DON]]="Yes", Table2[[#This Row],[DON_pub_date]]=""),1, 0))))) -> 0 | AQ12: =IF(ISBLANK(Table2[[#This Row],[Pending_question]]), 2,(IF(Table2[[#This Row],[Pending_question]]="Yes", 1, 0))) -> 0
A13: 44366 | B13: Closed | C13: {=IF(SUM(Table2[[#This Row],[PQ_indic]],Table2[[#This Row],[RRA_indic]],Table2[[#This Row],[EIS_indic]],Table2[[#This Row],[DON_indic]])=8, "Missing data", (IF(AND(Table2[[#This Row],[Pending_question]]="Yes", OR( Table2[[#This Row],[Need_RRA]]="No", ISBLANK(Table2[[#This Row],[Need_RRA]])), OR(Table2[[#This Row],[Need_EIS]]="No", ISBLANK(Table2[[#This Row],[Need_EIS]])), OR(Table2[[#This Row],[Need_DON]]="No", ISBLANK(Table2[[#This Row],[Need_DON]]) )),"Question, no products",( IF( AND(Table2[[#This Row],[Pending_question]]="Yes", ISBLANK(Table2[[#This Row],[PQ_closure_date]])), (IF(SUM(Table2[[#This Row],[RRA_indic]],Table2[[#This Row],[EIS_indic]],Table2[[#This Row],[DON_indic]])=0, "Open Question, all products done",(I447IF(OR(Table2[[#This Row],[RRA_indic]]=2, Table2[[#This Row],[EIS_indic]]=2, Table2[[#This Row],[DON_indic]]=2),"Question, Products unknown",IF(AND(Table2[[#This Row],[RRA_indic]]=1, Table2[[#This Row],[EIS_indic]]=1, Table2[[#This Row],[DON_indic]]=1), "Open Question, RRA, EIS, DON", IF(AND(Table2[[#This Row],[RRA_indic]]=1, Table2[[#This Row],[EIS_indic]]=1), "Open Question, RRA, EIS",IF(AND(Table2[[#This Row],[RRA_indic]]=1, Table2[[#This Row],[DON_indic]]=1), "Open Question, RRA, DON", IF(AND(Table2[[#This Row],[EIS_indic]]=1, Table2[[#This Row],[DON_indic]]=1), "Open Question, EIS, DON",IF(Table2[[#This Row],[RRA_indic]]=1, "Open Question, RRA", IF(Table2[[#This Row],[EIS_indic]]=1, "Open Question, EIS", "Open Question, DON")))))))))), (IF(SUM(Table2[[#This Row],[RRA_indic]],Table2[[#This Row],[EIS_indic]],Table2[[#This Row],[DON_indic]])=0, "All Products done",(IF(OR(Table2[[#This Row],[RRA_indic]]=2, Table2[[#This Row],[EIS_indic]]=2, Table2[[#This Row],[DON_indic]]=2),"Unknown", IF(AND(Table2[[#This Row],[RRA_indic]]=1, Table2[[#This Row],[EIS_indic]]=1, Table2[[#This Row],[DON_indic]]=1), "Open RRA, EIS, DON", IF(AND(Table2[[#This Row],[RRA_indic]]=1, Table2[[#This Row],[EIS_indic]]=1), "Open RRA, EIS", IF(AND(Table2[[#This Row],[RRA_indic]]=1, Table2[[#This Row],[DON_indic]]=1), "Open RRA, DON", IF(AND(Table2[[#This Row],[EIS_indic]]=1, Table2[[#This Row],[DON_indic]]=1), "Open EIS, DON", IF(Table2[[#This Row],[RRA_indic]]=1, "Open RRA", IF(Table2[[#This Row],[EIS_indic]]=1, "Open EIS", "Open DON")))))))))))))))} -> All Products done | D13: Anastasia | E13: Ebola virus disease | F13: Guinea | G13: Not applicable | M13: No | P13: No | Q13: Not applicable | Y13: yes | AB13: 18 june: sent back to Ros for NFP consultation/19 June: published | AH13: 44366 | AI13: yes | AK13: 44366 | AM13: =VLOOKUP(Table2[[#This Row],[country]],Countrycode!A:B,2,FALSE) -> GIN | AN13: =IF(ISBLANK(Table2[[#This Row],[Need_RRA]]), 2,(IF(Table2[[#This Row],[Need_RRA]]="No", 0, (IF(AND(Table2[[#This Row],[Need_RRA]]="Yes", Table2[[#This Row],[RRA_pub_date]]=""),1, 0))))) -> 0 | AO13: =IF(ISBLANK(Table2[[#This Row],[Need_EIS]]), 2,(IF(Table2[[#This Row],[Need_EIS]]="No", 0, (IF(AND(Table2[[#This Row],[Need_EIS]]="Yes", Table2[[#This Row],[EIS_pub_date]]=""),1, 0))))) -> 0 | AP13: =IF(ISBLANK(Table2[[#This Row],[Need_DON]]), 2,(IF(Table2[[#This Row],[Need_DON]]="No", 0, (IF(AND(Table2[[#This Row],[Need_DON]]="Yes", Table2[[#This Row],[DON_pub_date]]=""),1, 0))))) -> 0 | AQ13: =IF(ISBLANK(Table2[[#This Row],[Pending_question]]), 2,(IF(Table2[[#This Row],[Pending_question]]="Yes", 1, 0))) -> 0
A14: 44367 | B14: Closed | C14: {=IF(SUM(Table2[[#This Row],[PQ_indic]],Table2[[#This Row],[RRA_indic]],Table2[[#This Row],[EIS_indic]],Table2[[#This Row],[DON_indic]])=8, "Missing data", (IF(AND(Table2[[#This Row],[Pending_question]]="Yes", OR( Table2[[#This Row],[Need_RRA]]="No", ISBLANK(Table2[[#This Row],[Need_RRA]])), OR(Table2[[#This Row],[Need_EIS]]="No", ISBLANK(Table2[[#This Row],[Need_EIS]])), OR(Table2[[#This Row],[Need_DON]]="No", ISBLANK(Table2[[#This Row],[Need_DON]]) )),"Question, no products",( IF( AND(Table2[[#This Row],[Pending_question]]="Yes", ISBLANK(Table2[[#This Row],[PQ_closure_date]])), (IF(SUM(Table2[[#This Row],[RRA_indic]],Table2[[#This Row],[EIS_indic]],Table2[[#This Row],[DON_indic]])=0, "Open Question, all products done",(I447IF(OR(Table2[[#This Row],[RRA_indic]]=2, Table2[[#This Row],[EIS_indic]]=2, Table2[[#This Row],[DON_indic]]=2),"Question, Products unknown",IF(AND(Table2[[#This Row],[RRA_indic]]=1, Table2[[#This Row],[EIS_indic]]=1, Table2[[#This Row],[DON_indic]]=1), "Open Question, RRA, EIS, DON", IF(AND(Table2[[#This Row],[RRA_indic]]=1, Table2[[#This Row],[EIS_indic]]=1), "Open Question, RRA, EIS",IF(AND(Table2[[#This Row],[RRA_indic]]=1, Table2[[#This Row],[DON_indic]]=1), "Open Question, RRA, DON", IF(AND(Table2[[#This Row],[EIS_indic]]=1, Table2[[#This Row],[DON_indic]]=1), "Open Question, EIS, DON",IF(Table2[[#This Row],[RRA_indic]]=1, "Open Question, RRA", IF(Table2[[#This Row],[EIS_indic]]=1, "Open Question, EIS", "Open Question, DON")))))))))), (IF(SUM(Table2[[#This Row],[RRA_indic]],Table2[[#This Row],[EIS_indic]],Table2[[#This Row],[DON_indic]])=0, "All Products done",(IF(OR(Table2[[#This Row],[RRA_indic]]=2, Table2[[#This Row],[EIS_indic]]=2, Table2[[#This Row],[DON_indic]]=2),"Unknown", IF(AND(Table2[[#This Row],[RRA_indic]]=1, Table2[[#This Row],[EIS_indic]]=1, Table2[[#This Row],[DON_indic]]=1), "Open RRA, EIS, DON", IF(AND(Table2[[#This Row],[RRA_indic]]=1, Table2[[#This Row],[EIS_indic]]=1), "Open RRA, EIS", IF(AND(Table2[[#This Row],[RRA_indic]]=1, Table2[[#This Row],[DON_indic]]=1), "Open RRA, DON", IF(AND(Table2[[#This Row],[EIS_indic]]=1, Table2[[#This Row],[DON_indic]]=1), "Open EIS, DON", IF(Table2[[#This Row],[RRA_indic]]=1, "Open RRA", IF(Table2[[#This Row],[EIS_indic]]=1, "Open EIS", "Open DON")))))))))))))))} -> All Products done | D14: Lidia/Anastasia/Elvis /Etsub | E14: Dengue | F14: Kenya | G14: Not applicable | K14: 2021-E000167 | M14: No | P14: Yes | R14: 21 June: Will start the process / 23 June: RRA shared by CO to AFRO and HQ / 24 june, AFRO provided inputs and shared with HQ. HQ then shared with TT. TT provided comments same day/25 June, HQ shared RRA with AFRO/28 June: comments received from WCO, AFRO feedback is pending / 29 June: AFRO provided inputs and changed level of risk of event spreading at national and regional level from moderate to high/2 July: Amended version shared with AFRO and WCO/3 July: WCO accepted changes / 5 July: waiting for AFRO greenlight / 7 July: more comments from Esther, needs to go back to AFRO and CO / 8 July: Finalized and distributed | S14: 44367 | U14: 44385 | Y14: yes | AB14: 21 June: need one/ EIS to be drafted immediately RRA is completed/ 9 July: HQ is drafting the EIS/ 14 July: EIS drafted by HQ and shared with TT, inputs from TT are received/ 15 July: shared with AFRO and CO for comments (deadline for tomorrow)/ 16 July: CO shared comments, reminder sent to AFRO/16 July: Revised version sent back AFRO after receving input from WCO. AFRO is expected to share with IHR NFP for consultation if there is no outstanding comment/ 20 July: reminder sent to AFRO /21 July: AFRO responded to indicate they will share with NFP for consultation /23 July: EIS has been shared with IHR NFP and is pending feedback from the NFP/ 23 July: Final EIS for posting shared by AFRO./26 July: EIS published. | AH14: 44403 | AI14: no | AL14: 20 June: sitrep received, dengue confirmed by RT PCR/latest line as of 29 June recieved on 02 July 2021 | AM14: =VLOOKUP(Table2[[#This Row],[country]],Countrycode!A:B,2,FALSE) -> KEN | AN14: =IF(ISBLANK(Table2[[#This Row],[Need_RRA]]), 2,(IF(Table2[[#This Row],[Need_RRA]]="No", 0, (IF(AND(Table2[[#This Row],[Need_RRA]]="Yes", Table2[[#This Row],[RRA_pub_date]]=""),1, 0))))) -> 0 | AO14: =IF(ISBLANK(Table2[[#This Row],[Need_EIS]]), 2,(IF(Table2[[#This Row],[Need_EIS]]="No", 0, (IF(AND(Table2[[#This Row],[Need_EIS]]="Yes", Table2[[#This Row],[EIS_pub_date]]=""),1, 0))))) -> 0 | AP14: =IF(ISBLANK(Table2[[#This Row],[Need_DON]]), 2,(IF(Table2[[#This Row],[Need_DON]]="No", 0, (IF(AND(Table2[[#This Row],[Need_DON]]="Yes", Table2[[#This Row],[DON_pub_date]]=""),1, 0))))) -> 0 | AQ14: =IF(ISBLANK(Table2[[#This Row],[Pending_question]]), 2,(IF(Table2[[#This Row],[Pending_question]]="Yes", 1, 0))) -> 0
A15: 44367 | B15: Closed | C15: {=IF(SUM(Table2[[#This Row],[PQ_indic]],Table2[[#This Row],[RRA_indic]],Table2[[#This Row],[EIS_indic]],Table2[[#This Row],[DON_indic]])=8, "Missing data", (IF(AND(Table2[[#This Row],[Pending_question]]="Yes", OR( Table2[[#This Row],[Need_RRA]]="No", ISBLANK(Table2[[#This Row],[Need_RRA]])), OR(Table2[[#This Row],[Need_EIS]]="No", ISBLANK(Table2[[#This Row],[Need_EIS]])), OR(Table2[[#This Row],[Need_DON]]="No", ISBLANK(Table2[[#This Row],[Need_DON]]) )),"Question, no products",( IF( AND(Table2[[#This Row],[Pending_question]]="Yes", ISBLANK(Table2[[#This Row],[PQ_closure_date]])), (IF(SUM(Table2[[#This Row],[RRA_indic]],Table2[[#This Row],[EIS_indic]],Table2[[#This Row],[DON_indic]])=0, "Open Question, all products done",(I447IF(OR(Table2[[#This Row],[RRA_indic]]=2, Table2[[#This Row],[EIS_indic]]=2, Table2[[#This Row],[DON_indic]]=2),"Question, Products unknown",IF(AND(Table2[[#This Row],[RRA_indic]]=1, Table2[[#This Row],[EIS_indic]]=1, Table2[[#This Row],[DON_indic]]=1), "Open Question, RRA, EIS, DON", IF(AND(Table2[[#This Row],[RRA_indic]]=1, Table2[[#This Row],[EIS_indic]]=1), "Open Question, RRA, EIS",IF(AND(Table2[[#This Row],[RRA_indic]]=1, Table2[[#This Row],[DON_indic]]=1), "Open Question, RRA, DON", IF(AND(Table2[[#This Row],[EIS_indic]]=1, Table2[[#This Row],[DON_indic]]=1), "Open Question, EIS, DON",IF(Table2[[#This Row],[RRA_indic]]=1, "Open Question, RRA", IF(Table2[[#This Row],[EIS_indic]]=1, "Open Question, EIS", "Open Question, DON")))))))))), (IF(SUM(Table2[[#This Row],[RRA_indic]],Table2[[#This Row],[EIS_indic]],Table2[[#This Row],[DON_indic]])=0, "All Products done",(IF(OR(Table2[[#This Row],[RRA_indic]]=2, Table2[[#This Row],[EIS_indic]]=2, Table2[[#This Row],[DON_indic]]=2),"Unknown", IF(AND(Table2[[#This Row],[RRA_indic]]=1, Table2[[#This Row],[EIS_indic]]=1, Table2[[#This Row],[DON_indic]]=1), "Open RRA, EIS, DON", IF(AND(Table2[[#This Row],[RRA_indic]]=1, Table2[[#This Row],[EIS_indic]]=1), "Open RRA, EIS", IF(AND(Table2[[#This Row],[RRA_indic]]=1, Table2[[#This Row],[DON_indic]]=1), "Open RRA, DON", IF(AND(Table2[[#This Row],[EIS_indic]]=1, Table2[[#This Row],[DON_indic]]=1), "Open EIS, DON", IF(Table2[[#This Row],[RRA_indic]]=1, "Open RRA", IF(Table2[[#This Row],[EIS_indic]]=1, "Open EIS", "Open DON")))))))))))))))} -> All Products done | D15: Etsub/Elvis/Plummer | E15: Undiagnosed disease | F15: Multiple | G15: Somalia, Ethiopia | H15: 44367 | J15: 44359 | K15: 2021-E000235 | L15: 12 June AFRO created an EMS/21 June: no / 22 June no / 23 June: EMRO created an EMS | M15: No | P15: Yes | R15: 18 June: RRA regional AFRO shared with HQ and HQ shared it with EMRO / 22 June Emilie called Aura to accelerate the process/24 June regional draft to be shared with TT / 28 June: input from TT received / 29 June: HQ shared with EMRO and AFRO. Feedback received from AFRO and EMRO on the regional RRA on 1 july from AFRO. A meeting is planned for monday 5 July to discuss on this matter. 3 level TC conducted on 5 July. The document to be consolidated./ 6 July: RRA sent back to AFRO and EMRO with deadline for reply by 3pm GVA time on 7 July./ 7 July: EMRO answer received, AFRO feedback received as well/8 July: Consolidated RRA with inputs from regions shared with Esther for clearance/09 July: RRA finalized and disseminated | S15: 44361 | U15: 44386 | Y15: yes | Z15: EIS anouncement | AB15: 21 June: send it to TT/21 June sent to AFRO (for Ethiopia) -> we don't know when it will be shared with the CO, TC planned on 24 June? / 22 June: AFRO shared the response from WCO, not ready to be published / 30 June: EIS received from AFRO with IHR NFP inputs but important pending questions to be addressed. PHI contacted Carmen and Eric Berterat. Also additional information shared by FAO through Pierre F (camel and human not at the same geo location and probable diagnostic for human is anthrax) / 2 July: EIS shared with AFRO. On 5 July, additional input recieved from WCO and the EIS will be consolidated. / 6 July: EIS sent back to AFRO for reply and possible onward IHR NFP consultation / 7 July: the EIS is probably with IHR NFP. Reminder sent to AFRO on 13 July./ 16 July: EIS posted | AH15: 44393 | AI15: No | AL15: 22 June: Somalia still denying the event; Event open in GLEWS; communication with GLEWS happening in outbreak / 23 June: no lab results, no clear description of the cases in terms of time, place, person/ 24 June: TC with WCO and AFRO, no significant update, Available docs to be shared with AFRO and HQ. 5 July 2 level meeting with HQ TT, AFRO and EMRO. | AM15: =VLOOKUP(Table2[[#This Row],[country]],Countrycode!A:B,2,FALSE) -> MLX | AN15: =IF(ISBLANK(Table2[[#This Row],[Need_RRA]]), 2,(IF(Table2[[#This Row],[Need_RRA]]="No", 0, (IF(AND(Table2[[#This Row],[Need_RRA]]="Yes", Table2[[#This Row],[RRA_pub_date]]=""),1, 0))))) -> 0 | AO15: =IF(ISBLANK(Table2[[#This Row],[Need_EIS]]), 2,(IF(Table2[[#This Row],[Need_EIS]]="No", 0, (IF(AND(Table2[[#This Row],[Need_EIS]]="Yes", Table2[[#This Row],[EIS_pub_date]]=""),1, 0))))) -> 0 | AP15: =IF(ISBLANK(Table2[[#This Row],[Need_DON]]), 2,(IF(Table2[[#This Row],[Need_DON]]="No", 0, (IF(AND(Table2[[#This Row],[Need_DON]]="Yes", Table2[[#This Row],[DON_pub_date]]=""),1, 0))))) -> 0 | AQ15: =IF(ISBLANK(Table2[[#This Row],[Pending_question]]), 2,(IF(Table2[[#This Row],[Pending_question]]="Yes", 1, 0))) -> 0 | AR15: 16/06/2021 17/06/2021
A16: 44369 | B16: Closed | C16: {=IF(SUM(Table2[[#This Row],[PQ_indic]],Table2[[#This Row],[RRA_indic]],Table2[[#This Row],[EIS_indic]],Table2[[#This Row],[DON_indic]])=8, "Missing data", (IF(AND(Table2[[#This Row],[Pending_question]]="Yes", OR( Table2[[#This Row],[Need_RRA]]="No", ISBLANK(Table2[[#This Row],[Need_RRA]])), OR(Table2[[#This Row],[Need_EIS]]="No", ISBLANK(Table2[[#This Row],[Need_EIS]])), OR(Table2[[#This Row],[Need_DON]]="No", ISBLANK(Table2[[#This Row],[Need_DON]]) )),"Question, no products",( IF( AND(Table2[[#This Row],[Pending_question]]="Yes", ISBLANK(Table2[[#This Row],[PQ_closure_date]])), (IF(SUM(Table2[[#This Row],[RRA_indic]],Table2[[#This Row],[EIS_indic]],Table2[[#This Row],[DON_indic]])=0, "Open Question, all products done",(I447IF(OR(Table2[[#This Row],[RRA_indic]]=2, Table2[[#This Row],[EIS_indic]]=2, Table2[[#This Row],[DON_indic]]=2),"Question, Products unknown",IF(AND(Table2[[#This Row],[RRA_indic]]=1, Table2[[#This Row],[EIS_indic]]=1, Table2[[#This Row],[DON_indic]]=1), "Open Question, RRA, EIS, DON", IF(AND(Table2[[#This Row],[RRA_indic]]=1, Table2[[#This Row],[EIS_indic]]=1), "Open Question, RRA, EIS",IF(AND(Table2[[#This Row],[RRA_indic]]=1, Table2[[#This Row],[DON_indic]]=1), "Open Question, RRA, DON", IF(AND(Table2[[#This Row],[EIS_indic]]=1, Table2[[#This Row],[DON_indic]]=1), "Open Question, EIS, DON",IF(Table2[[#This Row],[RRA_indic]]=1, "Open Question, RRA", IF(Table2[[#This Row],[EIS_indic]]=1, "Open Question, EIS", "Open Question, DON")))))))))), (IF(SUM(Table2[[#This Row],[RRA_indic]],Table2[[#This Row],[EIS_indic]],Table2[[#This Row],[DON_indic]])=0, "All Products done",(IF(OR(Table2[[#This Row],[RRA_indic]]=2, Table2[[#This Row],[EIS_indic]]=2, Table2[[#This Row],[DON_indic]]=2),"Unknown", IF(AND(Table2[[#This Row],[RRA_indic]]=1, Table2[[#This Row],[EIS_indic]]=1, Table2[[#This Row],[DON_indic]]=1), "Open RRA, EIS, DON", IF(AND(Table2[[#This Row],[RRA_indic]]=1, Table2[[#This Row],[EIS_indic]]=1), "Open RRA, EIS", IF(AND(Table2[[#This Row],[RRA_indic]]=1, Table2[[#This Row],[DON_indic]]=1), "Open RRA, DON", IF(AND(Table2[[#This Row],[EIS_indic]]=1, Table2[[#This Row],[DON_indic]]=1), "Open EIS, DON", IF(Table2[[#This Row],[RRA_indic]]=1, "Open RRA", IF(Table2[[#This Row],[EIS_indic]]=1, "Open EIS", "Open DON")))))))))))))))} -> All Products done | D16: Etsub | E16: Avian Influenza A (H3N2) v | F16: Canada | G16: Not applicable | M16: No | P16: No | Q16: Not applicable | Y16: yes | AB16: 18 June: PAHO shared draft/20 June PHI sent it back to PAHO with inputs from TT/21 June: PAHO shared it with IHR NFP, on 22 June EIS has been published | AH16: 44369 | AI16: no | AM16: =VLOOKUP(Table2[[#This Row],[country]],Countrycode!A:B,2,FALSE) -> CAN | AN16: =IF(ISBLANK(Table2[[#This Row],[Need_RRA]]), 2,(IF(Table2[[#This Row],[Need_RRA]]="No", 0, (IF(AND(Table2[[#This Row],[Need_RRA]]="Yes", Table2[[#This Row],[RRA_pub_date]]=""),1, 0))))) -> 0 | AO16: =IF(ISBLANK(Table2[[#This Row],[Need_EIS]]), 2,(IF(Table2[[#This Row],[Need_EIS]]="No", 0, (IF(AND(Table2[[#This Row],[Need_EIS]]="Yes", Table2[[#This Row],[EIS_pub_date]]=""),1, 0))))) -> 0 | AP16: =IF(ISBLANK(Table2[[#This Row],[Need_DON]]), 2,(IF(Table2[[#This Row],[Need_DON]]="No", 0, (IF(AND(Table2[[#This Row],[Need_DON]]="Yes", Table2[[#This Row],[DON_pub_date]]=""),1, 0))))) -> 0 | AQ16: =IF(ISBLANK(Table2[[#This Row],[Pending_question]]), 2,(IF(Table2[[#This Row],[Pending_question]]="Yes", 1, 0))) -> 0
A17: 44385 | B17: Closed | C17: {=IF(SUM(Table2[[#This Row],[PQ_indic]],Table2[[#This Row],[RRA_indic]],Table2[[#This Row],[EIS_indic]],Table2[[#This Row],[DON_indic]])=8, "Missing data", (IF(AND(Table2[[#This Row],[Pending_question]]="Yes", OR( Table2[[#This Row],[Need_RRA]]="No", ISBLANK(Table2[[#This Row],[Need_RRA]])), OR(Table2[[#This Row],[Need_EIS]]="No", ISBLANK(Table2[[#This Row],[Need_EIS]])), OR(Table2[[#This Row],[Need_DON]]="No", ISBLANK(Table2[[#This Row],[Need_DON]]) )),"Question, no products",( IF( AND(Table2[[#This Row],[Pending_question]]="Yes", ISBLANK(Table2[[#This Row],[PQ_closure_date]])), (IF(SUM(Table2[[#This Row],[RRA_indic]],Table2[[#This Row],[EIS_indic]],Table2[[#This Row],[DON_indic]])=0, "Open Question, all products done",(I447IF(OR(Table2[[#This Row],[RRA_indic]]=2, Table2[[#This Row],[EIS_indic]]=2, Table2[[#This Row],[DON_indic]]=2),"Question, Products unknown",IF(AND(Table2[[#This Row],[RRA_indic]]=1, Table2[[#This Row],[EIS_indic]]=1, Table2[[#This Row],[DON_indic]]=1), "Open Question, RRA, EIS, DON", IF(AND(Table2[[#This Row],[RRA_indic]]=1, Table2[[#This Row],[EIS_indic]]=1), "Open Question, RRA, EIS",IF(AND(Table2[[#This Row],[RRA_indic]]=1, Table2[[#This Row],[DON_indic]]=1), "Open Question, RRA, DON", IF(AND(Table2[[#This Row],[EIS_indic]]=1, Table2[[#This Row],[DON_indic]]=1), "Open Question, EIS, DON",IF(Table2[[#This Row],[RRA_indic]]=1, "Open Question, RRA", IF(Table2[[#This Row],[EIS_indic]]=1, "Open Question, EIS", "Open Question, DON")))))))))), (IF(SUM(Table2[[#This Row],[RRA_indic]],Table2[[#This Row],[EIS_indic]],Table2[[#This Row],[DON_indic]])=0, "All Products done",(IF(OR(Table2[[#This Row],[RRA_indic]]=2, Table2[[#This Row],[EIS_indic]]=2, Table2[[#This Row],[DON_indic]]=2),"Unknown", IF(AND(Table2[[#This Row],[RRA_indic]]=1, Table2[[#This Row],[EIS_indic]]=1, Table2[[#This Row],[DON_indic]]=1), "Open RRA, EIS, DON", IF(AND(Table2[[#This Row],[RRA_indic]]=1, Table2[[#This Row],[EIS_indic]]=1), "Open RRA, EIS", IF(AND(Table2[[#This Row],[RRA_indic]]=1, Table2[[#This Row],[DON_indic]]=1), "Open RRA, DON", IF(AND(Table2[[#This Row],[EIS_indic]]=1, Table2[[#This Row],[DON_indic]]=1), "Open EIS, DON", IF(Table2[[#This Row],[RRA_indic]]=1, "Open RRA", IF(Table2[[#This Row],[EIS_indic]]=1, "Open EIS", "Open DON")))))))))))))))} -> All Products done | D17: Plummer | E17: Avian influenza A (H5N6) | F17: China | G17: Not applicable | H17: 44385 | J17: 44385 | M17: No | P17: No | Q17: Not applicable | R17: 12 July: Not Planned | Y17: yes | AB17: 8 July: email sent to TT and Emilie to provide feedback / 9 July: draft sent to WPRO / to be sent to China NFP by WPRO/ 12 July: WPRO sent it back to HQ / 13.07.21: consolidated document recieved awaiting clearance from Esther prior to publishing, published 6.47pm | AH17: 44390 | AI17: no | AL17: WPRO opened EMS 8 July 2021; EIS Published | AM17: =VLOOKUP(Table2[[#This Row],[country]],Countrycode!A:B,2,FALSE) -> CHN | AN17: =IF(ISBLANK(Table2[[#This Row],[Need_RRA]]), 2,(IF(Table2[[#This Row],[Need_RRA]]="No", 0, (IF(AND(Table2[[#This Row],[Need_RRA]]="Yes", Table2[[#This Row],[RRA_pub_date]]=""),1, 0))))) -> 0 | AO17: =IF(ISBLANK(Table2[[#This Row],[Need_EIS]]), 2,(IF(Table2[[#This Row],[Need_EIS]]="No", 0, (IF(AND(Table2[[#This Row],[Need_EIS]]="Yes", Table2[[#This Row],[EIS_pub_date]]=""),1, 0))))) -> 0 | AP17: =IF(ISBLANK(Table2[[#This Row],[Need_DON]]), 2,(IF(Table2[[#This Row],[Need_DON]]="No", 0, (IF(AND(Table2[[#This Row],[Need_DON]]="Yes", Table2[[#This Row],[DON_pub_date]]=""),1, 0))))) -> 0 | AQ17: =IF(ISBLANK(Table2[[#This Row],[Pending_question]]), 2,(IF(Table2[[#This Row],[Pending_question]]="Yes", 1, 0))) -> 0 | AR17: 44385
A18: 44391 | B18: Closed | C18: {=IF(SUM(Table2[[#This Row],[PQ_indic]],Table2[[#This Row],[RRA_indic]],Table2[[#This Row],[EIS_indic]],Table2[[#This Row],[DON_indic]])=8, "Missing data", (IF(AND(Table2[[#This Row],[Pending_question]]="Yes", OR( Table2[[#This Row],[Need_RRA]]="No", ISBLANK(Table2[[#This Row],[Need_RRA]])), OR(Table2[[#This Row],[Need_EIS]]="No", ISBLANK(Table2[[#This Row],[Need_EIS]])), OR(Table2[[#This Row],[Need_DON]]="No", ISBLANK(Table2[[#This Row],[Need_DON]]) )),"Question, no products",( IF( AND(Table2[[#This Row],[Pending_question]]="Yes", ISBLANK(Table2[[#This Row],[PQ_closure_date]])), (IF(SUM(Table2[[#This Row],[RRA_indic]],Table2[[#This Row],[EIS_indic]],Table2[[#This Row],[DON_indic]])=0, "Open Question, all products done",(I447IF(OR(Table2[[#This Row],[RRA_indic]]=2, Table2[[#This Row],[EIS_indic]]=2, Table2[[#This Row],[DON_indic]]=2),"Question, Products unknown",IF(AND(Table2[[#This Row],[RRA_indic]]=1, Table2[[#This Row],[EIS_indic]]=1, Table2[[#This Row],[DON_indic]]=1), "Open Question, RRA, EIS, DON", IF(AND(Table2[[#This Row],[RRA_indic]]=1, Table2[[#This Row],[EIS_indic]]=1), "Open Question, RRA, EIS",IF(AND(Table2[[#This Row],[RRA_indic]]=1, Table2[[#This Row],[DON_indic]]=1), "Open Question, RRA, DON", IF(AND(Table2[[#This Row],[EIS_indic]]=1, Table2[[#This Row],[DON_indic]]=1), "Open Question, EIS, DON",IF(Table2[[#This Row],[RRA_indic]]=1, "Open Question, RRA", IF(Table2[[#This Row],[EIS_indic]]=1, "Open Question, EIS", "Open Question, DON")))))))))), (IF(SUM(Table2[[#This Row],[RRA_indic]],Table2[[#This Row],[EIS_indic]],Table2[[#This Row],[DON_indic]])=0, "All Products done",(IF(OR(Table2[[#This Row],[RRA_indic]]=2, Table2[[#This Row],[EIS_indic]]=2, Table2[[#This Row],[DON_indic]]=2),"Unknown", IF(AND(Table2[[#This Row],[RRA_indic]]=1, Table2[[#This Row],[EIS_indic]]=1, Table2[[#This Row],[DON_indic]]=1), "Open RRA, EIS, DON", IF(AND(Table2[[#This Row],[RRA_indic]]=1, Table2[[#This Row],[EIS_indic]]=1), "Open RRA, EIS", IF(AND(Table2[[#This Row],[RRA_indic]]=1, Table2[[#This Row],[DON_indic]]=1), "Open RRA, DON", IF(AND(Table2[[#This Row],[EIS_indic]]=1, Table2[[#This Row],[DON_indic]]=1), "Open EIS, DON", IF(Table2[[#This Row],[RRA_indic]]=1, "Open RRA", IF(Table2[[#This Row],[EIS_indic]]=1, "Open EIS", "Open DON")))))))))))))))} -> All Products done | D18: Etsub | E18: Avian influenza A (H5N6) | F18: China | G18: Not applicable | H18: 44391 | J18: 44391 | M18: No | P18: No | Q18: Not applicable | R18: 14 July: Not planned | Y18: yes | AB18: 14 July: First draft circulated for review with TT with a deadline by COB . Revised draft sent back to WPRO on 14 July 19 july: still with WPRO, a reminder was sent to WPRO and to IHR NFP /22 July: EIS is published | AH18: 44399 | AI18: no | AM18: =VLOOKUP(Table2[[#This Row],[country]],Countrycode!A:B,2,FALSE) -> CHN | AN18: =IF(ISBLANK(Table2[[#This Row],[Need_RRA]]), 2,(IF(Table2[[#This Row],[Need_RRA]]="No", 0, (IF(AND(Table2[[#This Row],[Need_RRA]]="Yes", Table2[[#This Row],[RRA_pub_date]]=""),1, 0))))) -> 0 | AO18: =IF(ISBLANK(Table2[[#This Row],[Need_EIS]]), 2,(IF(Table2[[#This Row],[Need_EIS]]="No", 0, (IF(AND(Table2[[#This Row],[Need_EIS]]="Yes", Table2[[#This Row],[EIS_pub_date]]=""),1, 0))))) -> 0 | AP18: =IF(ISBLANK(Table2[[#This Row],[Need_DON]]), 2,(IF(Table2[[#This Row],[Need_DON]]="No", 0, (IF(AND(Table2[[#This Row],[Need_DON]]="Yes", Table2[[#This Row],[DON_pub_date]]=""),1, 0))))) -> 0 | AQ18: =IF(ISBLANK(Table2[[#This Row],[Pending_question]]), 2,(IF(Table2[[#This Row],[Pending_question]]="Yes", 1, 0))) -> 0 | AR18: 44391
A19: 44393 | B19: Closed | C19: {=IF(SUM(Table2[[#This Row],[PQ_indic]],Table2[[#This Row],[RRA_indic]],Table2[[#This Row],[EIS_indic]],Table2[[#This Row],[DON_indic]])=8, "Missing data", (IF(AND(Table2[[#This Row],[Pending_question]]="Yes", OR( Table2[[#This Row],[Need_RRA]]="No", ISBLANK(Table2[[#This Row],[Need_RRA]])), OR(Table2[[#This Row],[Need_EIS]]="No", ISBLANK(Table2[[#This Row],[Need_EIS]])), OR(Table2[[#This Row],[Need_DON]]="No", ISBLANK(Table2[[#This Row],[Need_DON]]) )),"Question, no products",( IF( AND(Table2[[#This Row],[Pending_question]]="Yes", ISBLANK(Table2[[#This Row],[PQ_closure_date]])), (IF(SUM(Table2[[#This Row],[RRA_indic]],Table2[[#This Row],[EIS_indic]],Table2[[#This Row],[DON_indic]])=0, "Open Question, all products done",(I447IF(OR(Table2[[#This Row],[RRA_indic]]=2, Table2[[#This Row],[EIS_indic]]=2, Table2[[#This Row],[DON_indic]]=2),"Question, Products unknown",IF(AND(Table2[[#This Row],[RRA_indic]]=1, Table2[[#This Row],[EIS_indic]]=1, Table2[[#This Row],[DON_indic]]=1), "Open Question, RRA, EIS, DON", IF(AND(Table2[[#This Row],[RRA_indic]]=1, Table2[[#This Row],[EIS_indic]]=1), "Open Question, RRA, EIS",IF(AND(Table2[[#This Row],[RRA_indic]]=1, Table2[[#This Row],[DON_indic]]=1), "Open Question, RRA, DON", IF(AND(Table2[[#This Row],[EIS_indic]]=1, Table2[[#This Row],[DON_indic]]=1), "Open Question, EIS, DON",IF(Table2[[#This Row],[RRA_indic]]=1, "Open Question, RRA", IF(Table2[[#This Row],[EIS_indic]]=1, "Open Question, EIS", "Open Question, DON")))))))))), (IF(SUM(Table2[[#This Row],[RRA_indic]],Table2[[#This Row],[EIS_indic]],Table2[[#This Row],[DON_indic]])=0, "All Products done",(IF(OR(Table2[[#This Row],[RRA_indic]]=2, Table2[[#This Row],[EIS_indic]]=2, Table2[[#This Row],[DON_indic]]=2),"Unknown", IF(AND(Table2[[#This Row],[RRA_indic]]=1, Table2[[#This Row],[EIS_indic]]=1, Table2[[#This Row],[DON_indic]]=1), "Open RRA, EIS, DON", IF(AND(Table2[[#This Row],[RRA_indic]]=1, Table2[[#This Row],[EIS_indic]]=1), "Open RRA, EIS", IF(AND(Table2[[#This Row],[RRA_indic]]=1, Table2[[#This Row],[DON_indic]]=1), "Open RRA, DON", IF(AND(Table2[[#This Row],[EIS_indic]]=1, Table2[[#This Row],[DON_indic]]=1), "Open EIS, DON", IF(Table2[[#This Row],[RRA_indic]]=1, "Open RRA", IF(Table2[[#This Row],[EIS_indic]]=1, "Open EIS", "Open DON")))))))))))))))} -> All Products done | D19: Anastasia/Dunja | E19: MERS-CoV | F19: Saudi Arabia | G19: Not applicable | M19: No | P19: No | Q19: Not applicable | R19: 12 July: Not planned | Y19: yes | AB19: 8 July: check with EMRO if needed / 12 July: EMRO is drafting /27 July reminder sent to EMRO/28 July/9 August/10_ EMRO replied will follow up with NFP . On 11 August agreenment to draft a new EIS with infor from MOH , 48 h for NFP concurence. On 11 sharered by EMRO, 12 HQ inputs/ 15 EMRO tt inputs. on 16 EMRO cleared and EIS published | AH19: 44393 | AI19: yes | AK19: 44425 | AL19: 9 July waiting for EMRO reply. 16 July: we can wait until Dujna's return from vacation | AM19: =VLOOKUP(Table2[[#This Row],[country]],Countrycode!A:B,2,FALSE) -> SAU | AN19: =IF(ISBLANK(Table2[[#This Row],[Need_RRA]]), 2,(IF(Table2[[#This Row],[Need_RRA]]="No", 0, (IF(AND(Table2[[#This Row],[Need_RRA]]="Yes", Table2[[#This Row],[RRA_pub_date]]=""),1, 0))))) -> 0 | AO19: =IF(ISBLANK(Table2[[#This Row],[Need_EIS]]), 2,(IF(Table2[[#This Row],[Need_EIS]]="No", 0, (IF(AND(Table2[[#This Row],[Need_EIS]]="Yes", Table2[[#This Row],[EIS_pub_date]]=""),1, 0))))) -> 0 | AP19: =IF(ISBLANK(Table2[[#This Row],[Need_DON]]), 2,(IF(Table2[[#This Row],[Need_DON]]="No", 0, (IF(AND(Table2[[#This Row],[Need_DON]]="Yes", Table2[[#This Row],[DON_pub_date]]=""),1, 0))))) -> 0 | AQ19: =IF(ISBLANK(Table2[[#This Row],[Pending_question]]), 2,(IF(Table2[[#This Row],[Pending_question]]="Yes", 1, 0))) -> 0
A20: 44395 | B20: Closed | C20: {=IF(SUM(Table2[[#This Row],[PQ_indic]],Table2[[#This Row],[RRA_indic]],Table2[[#This Row],[EIS_indic]],Table2[[#This Row],[DON_indic]])=8, "Missing data", (IF(AND(Table2[[#This Row],[Pending_question]]="Yes", OR( Table2[[#This Row],[Need_RRA]]="No", ISBLANK(Table2[[#This Row],[Need_RRA]])), OR(Table2[[#This Row],[Need_EIS]]="No", ISBLANK(Table2[[#This Row],[Need_EIS]])), OR(Table2[[#This Row],[Need_DON]]="No", ISBLANK(Table2[[#This Row],[Need_DON]]) )),"Question, no products",( IF( AND(Table2[[#This Row],[Pending_question]]="Yes", ISBLANK(Table2[[#This Row],[PQ_closure_date]])), (IF(SUM(Table2[[#This Row],[RRA_indic]],Table2[[#This Row],[EIS_indic]],Table2[[#This Row],[DON_indic]])=0, "Open Question, all products done",(I447IF(OR(Table2[[#This Row],[RRA_indic]]=2, Table2[[#This Row],[EIS_indic]]=2, Table2[[#This Row],[DON_indic]]=2),"Question, Products unknown",IF(AND(Table2[[#This Row],[RRA_indic]]=1, Table2[[#This Row],[EIS_indic]]=1, Table2[[#This Row],[DON_indic]]=1), "Open Question, RRA, EIS, DON", IF(AND(Table2[[#This Row],[RRA_indic]]=1, Table2[[#This Row],[EIS_indic]]=1), "Open Question, RRA, EIS",IF(AND(Table2[[#This Row],[RRA_indic]]=1, Table2[[#This Row],[DON_indic]]=1), "Open Question, RRA, DON", IF(AND(Table2[[#This Row],[EIS_indic]]=1, Table2[[#This Row],[DON_indic]]=1), "Open Question, EIS, DON",IF(Table2[[#This Row],[RRA_indic]]=1, "Open Question, RRA", IF(Table2[[#This Row],[EIS_indic]]=1, "Open Question, EIS", "Open Question, DON")))))))))), (IF(SUM(Table2[[#This Row],[RRA_indic]],Table2[[#This Row],[EIS_indic]],Table2[[#This Row],[DON_indic]])=0, "All Products done",(IF(OR(Table2[[#This Row],[RRA_indic]]=2, Table2[[#This Row],[EIS_indic]]=2, Table2[[#This Row],[DON_indic]]=2),"Unknown", IF(AND(Table2[[#This Row],[RRA_indic]]=1, Table2[[#This Row],[EIS_indic]]=1, Table2[[#This Row],[DON_indic]]=1), "Open RRA, EIS, DON", IF(AND(Table2[[#This Row],[RRA_indic]]=1, Table2[[#This Row],[EIS_indic]]=1), "Open RRA, EIS", IF(AND(Table2[[#This Row],[RRA_indic]]=1, Table2[[#This Row],[DON_indic]]=1), "Open RRA, DON", IF(AND(Table2[[#This Row],[EIS_indic]]=1, Table2[[#This Row],[DON_indic]]=1), "Open EIS, DON", IF(Table2[[#This Row],[RRA_indic]]=1, "Open RRA", IF(Table2[[#This Row],[EIS_indic]]=1, "Open EIS", "Open DON")))))))))))))))} -> All Products done | D20: Etsub | E20: Monkeypox | F20: United States of America | G20: Not applicable | H20: 44395 | J20: 44393 | M20: No | P20: No | Q20: Not applicable | R20: 18 July: not planned | Y20: yes | AB20: 18 July: draft sent by PAHO and First draft circulated for review with TT with a deadline by 2 pm 19 July. /19 July: revised draft shared back with PAHO and PAHO has shared it with US IHR NFP for consultation. /21 July: final version of the EIS shared by PAHO. AFRO has been requested to confirm if the document has been shared with Nigeria NFP. Currently, it is pending final clearance and AFRO confirmation for posting. /21 July: EIS is published. | AH20: 44398 | AI20: yes | AK20: 44404 | AL20: 19 July: sent an email to AFRO to follow up as this is the second exported case from Nigeria in a short time period / 19 July: we need to give a heads up to the Nigeria IHR NFP | AM20: =VLOOKUP(Table2[[#This Row],[country]],Countrycode!A:B,2,FALSE) -> USA | AN20: =IF(ISBLANK(Table2[[#This Row],[Need_RRA]]), 2,(IF(Table2[[#This Row],[Need_RRA]]="No", 0, (IF(AND(Table2[[#This Row],[Need_RRA]]="Yes", Table2[[#This Row],[RRA_pub_date]]=""),1, 0))))) -> 0 | AO20: =IF(ISBLANK(Table2[[#This Row],[Need_EIS]]), 2,(IF(Table2[[#This Row],[Need_EIS]]="No", 0, (IF(AND(Table2[[#This Row],[Need_EIS]]="Yes", Table2[[#This Row],[EIS_pub_date]]=""),1, 0))))) -> 0 | AP20: =IF(ISBLANK(Table2[[#This Row],[Need_DON]]), 2,(IF(Table2[[#This Row],[Need_DON]]="No", 0, (IF(AND(Table2[[#This Row],[Need_DON]]="Yes", Table2[[#This Row],[DON_pub_date]]=""),1, 0))))) -> 0 | AQ20: =IF(ISBLANK(Table2[[#This Row],[Pending_question]]), 2,(IF(Table2[[#This Row],[Pending_question]]="Yes", 1, 0))) -> 0 | AR20: 44395
A21: 44398 | B21: Closed | C21: {=IF(SUM(Table2[[#This Row],[PQ_indic]],Table2[[#This Row],[RRA_indic]],Table2[[#This Row],[EIS_indic]],Table2[[#This Row],[DON_indic]])=8, "Missing data", (IF(AND(Table2[[#This Row],[Pending_question]]="Yes", OR( Table2[[#This Row],[Need_RRA]]="No", ISBLANK(Table2[[#This Row],[Need_RRA]])), OR(Table2[[#This Row],[Need_EIS]]="No", ISBLANK(Table2[[#This Row],[Need_EIS]])), OR(Table2[[#This Row],[Need_DON]]="No", ISBLANK(Table2[[#This Row],[Need_DON]]) )),"Question, no products",( IF( AND(Table2[[#This Row],[Pending_question]]="Yes", ISBLANK(Table2[[#This Row],[PQ_closure_date]])), (IF(SUM(Table2[[#This Row],[RRA_indic]],Table2[[#This Row],[EIS_indic]],Table2[[#This Row],[DON_indic]])=0, "Open Question, all products done",(I447IF(OR(Table2[[#This Row],[RRA_indic]]=2, Table2[[#This Row],[EIS_indic]]=2, Table2[[#This Row],[DON_indic]]=2),"Question, Products unknown",IF(AND(Table2[[#This Row],[RRA_indic]]=1, Table2[[#This Row],[EIS_indic]]=1, Table2[[#This Row],[DON_indic]]=1), "Open Question, RRA, EIS, DON", IF(AND(Table2[[#This Row],[RRA_indic]]=1, Table2[[#This Row],[EIS_indic]]=1), "Open Question, RRA, EIS",IF(AND(Table2[[#This Row],[RRA_indic]]=1, Table2[[#This Row],[DON_indic]]=1), "Open Question, RRA, DON", IF(AND(Table2[[#This Row],[EIS_indic]]=1, Table2[[#This Row],[DON_indic]]=1), "Open Question, EIS, DON",IF(Table2[[#This Row],[RRA_indic]]=1, "Open Question, RRA", IF(Table2[[#This Row],[EIS_indic]]=1, "Open Question, EIS", "Open Question, DON")))))))))), (IF(SUM(Table2[[#This Row],[RRA_indic]],Table2[[#This Row],[EIS_indic]],Table2[[#This Row],[DON_indic]])=0, "All Products done",(IF(OR(Table2[[#This Row],[RRA_indic]]=2, Table2[[#This Row],[EIS_indic]]=2, Table2[[#This Row],[DON_indic]]=2),"Unknown", IF(AND(Table2[[#This Row],[RRA_indic]]=1, Table2[[#This Row],[EIS_indic]]=1, Table2[[#This Row],[DON_indic]]=1), "Open RRA, EIS, DON", IF(AND(Table2[[#This Row],[RRA_indic]]=1, Table2[[#This Row],[EIS_indic]]=1), "Open RRA, EIS", IF(AND(Table2[[#This Row],[RRA_indic]]=1, Table2[[#This Row],[DON_indic]]=1), "Open RRA, DON", IF(AND(Table2[[#This Row],[EIS_indic]]=1, Table2[[#This Row],[DON_indic]]=1), "Open EIS, DON", IF(Table2[[#This Row],[RRA_indic]]=1, "Open RRA", IF(Table2[[#This Row],[EIS_indic]]=1, "Open EIS", "Open DON")))))))))))))))} -> All Products done | D21: Etsub | E21: Avian influenza A (H5N6) | F21: China | G21: Not applicable | M21: No | P21: No | Q21: Not applicable | Y21: yes | AB21: 21 June published | AH21: 44398 | AI21: no | AM21: =VLOOKUP(Table2[[#This Row],[country]],Countrycode!A:B,2,FALSE) -> CHN | AN21: =IF(ISBLANK(Table2[[#This Row],[Need_RRA]]), 2,(IF(Table2[[#This Row],[Need_RRA]]="No", 0, (IF(AND(Table2[[#This Row],[Need_RRA]]="Yes", Table2[[#This Row],[RRA_pub_date]]=""),1, 0))))) -> 0 | AO21: =IF(ISBLANK(Table2[[#This Row],[Need_EIS]]), 2,(IF(Table2[[#This Row],[Need_EIS]]="No", 0, (IF(AND(Table2[[#This Row],[Need_EIS]]="Yes", Table2[[#This Row],[EIS_pub_date]]=""),1, 0))))) -> 0 | AP21: =IF(ISBLANK(Table2[[#This Row],[Need_DON]]), 2,(IF(Table2[[#This Row],[Need_DON]]="No", 0, (IF(AND(Table2[[#This Row],[Need_DON]]="Yes", Table2[[#This Row],[DON_pub_date]]=""),1, 0))))) -> 0 | AQ21: =IF(ISBLANK(Table2[[#This Row],[Pending_question]]), 2,(IF(Table2[[#This Row],[Pending_question]]="Yes", 1, 0))) -> 0
A22: 44398 | B22: Closed | C22: {=IF(SUM(Table2[[#This Row],[PQ_indic]],Table2[[#This Row],[RRA_indic]],Table2[[#This Row],[EIS_indic]],Table2[[#This Row],[DON_indic]])=8, "Missing data", (IF(AND(Table2[[#This Row],[Pending_question]]="Yes", OR( Table2[[#This Row],[Need_RRA]]="No", ISBLANK(Table2[[#This Row],[Need_RRA]])), OR(Table2[[#This Row],[Need_EIS]]="No", ISBLANK(Table2[[#This Row],[Need_EIS]])), OR(Table2[[#This Row],[Need_DON]]="No", ISBLANK(Table2[[#This Row],[Need_DON]]) )),"Question, no products",( IF( AND(Table2[[#This Row],[Pending_question]]="Yes", ISBLANK(Table2[[#This Row],[PQ_closure_date]])), (IF(SUM(Table2[[#This Row],[RRA_indic]],Table2[[#This Row],[EIS_indic]],Table2[[#This Row],[DON_indic]])=0, "Open Question, all products done",(I447IF(OR(Table2[[#This Row],[RRA_indic]]=2, Table2[[#This Row],[EIS_indic]]=2, Table2[[#This Row],[DON_indic]]=2),"Question, Products unknown",IF(AND(Table2[[#This Row],[RRA_indic]]=1, Table2[[#This Row],[EIS_indic]]=1, Table2[[#This Row],[DON_indic]]=1), "Open Question, RRA, EIS, DON", IF(AND(Table2[[#This Row],[RRA_indic]]=1, Table2[[#This Row],[EIS_indic]]=1), "Open Question, RRA, EIS",IF(AND(Table2[[#This Row],[RRA_indic]]=1, Table2[[#This Row],[DON_indic]]=1), "Open Question, RRA, DON", IF(AND(Table2[[#This Row],[EIS_indic]]=1, Table2[[#This Row],[DON_indic]]=1), "Open Question, EIS, DON",IF(Table2[[#This Row],[RRA_indic]]=1, "Open Question, RRA", IF(Table2[[#This Row],[EIS_indic]]=1, "Open Question, EIS", "Open Question, DON")))))))))), (IF(SUM(Table2[[#This Row],[RRA_indic]],Table2[[#This Row],[EIS_indic]],Table2[[#This Row],[DON_indic]])=0, "All Products done",(IF(OR(Table2[[#This Row],[RRA_indic]]=2, Table2[[#This Row],[EIS_indic]]=2, Table2[[#This Row],[DON_indic]]=2),"Unknown", IF(AND(Table2[[#This Row],[RRA_indic]]=1, Table2[[#This Row],[EIS_indic]]=1, Table2[[#This Row],[DON_indic]]=1), "Open RRA, EIS, DON", IF(AND(Table2[[#This Row],[RRA_indic]]=1, Table2[[#This Row],[EIS_indic]]=1), "Open RRA, EIS", IF(AND(Table2[[#This Row],[RRA_indic]]=1, Table2[[#This Row],[DON_indic]]=1), "Open RRA, DON", IF(AND(Table2[[#This Row],[EIS_indic]]=1, Table2[[#This Row],[DON_indic]]=1), "Open EIS, DON", IF(Table2[[#This Row],[RRA_indic]]=1, "Open RRA", IF(Table2[[#This Row],[EIS_indic]]=1, "Open EIS", "Open DON")))))))))))))))} -> All Products done | D22: Dunja | E22: Avian influenza A (H5N1) | F22: India | G22: Not applicable | H22: 44398 | J22: 44399 | M22: No | P22: No | Q22: Not applicable | Y22: yes | AB22: • 22 July 2021: we need an EIS, SEARO will draft it./11 August, NFP concurred version recieved. EIS cleared by HQ and posted • 24 July: draft from SEARO received and shared with HQ TT • 26 July the draft EIS reviewed by HQ and sent back to SEARO, WCO in Cc. • On 28 and/30 July , reminder sent to SEARO, the EIS still pending with MoH/ 4 and 6 August sent reminder to SEARO, no reply | AH22: 44401 | AI22: yes | AK22: 44424 | AL22: Reminder for 24h reply included | AM22: =VLOOKUP(Table2[[#This Row],[country]],Countrycode!A:B,2,FALSE) -> IND | AN22: =IF(ISBLANK(Table2[[#This Row],[Need_RRA]]), 2,(IF(Table2[[#This Row],[Need_RRA]]="No", 0, (IF(AND(Table2[[#This Row],[Need_RRA]]="Yes", Table2[[#This Row],[RRA_pub_date]]=""),1, 0))))) -> 0 | AO22: =IF(ISBLANK(Table2[[#This Row],[Need_EIS]]), 2,(IF(Table2[[#This Row],[Need_EIS]]="No", 0, (IF(AND(Table2[[#This Row],[Need_EIS]]="Yes", Table2[[#This Row],[EIS_pub_date]]=""),1, 0))))) -> 0 | AP22: =IF(ISBLANK(Table2[[#This Row],[Need_DON]]), 2,(IF(Table2[[#This Row],[Need_DON]]="No", 0, (IF(AND(Table2[[#This Row],[Need_DON]]="Yes", Table2[[#This Row],[DON_pub_date]]=""),1, 0))))) -> 0 | AQ22: =IF(ISBLANK(Table2[[#This Row],[Pending_question]]), 2,(IF(Table2[[#This Row],[Pending_question]]="Yes", 1, 0))) -> 0 | AR22: 44398
A23: 44399 | B23: Closed | C23: {=IF(SUM(Table2[[#This Row],[PQ_indic]],Table2[[#This Row],[RRA_indic]],Table2[[#This Row],[EIS_indic]],Table2[[#This Row],[DON_indic]])=8, "Missing data", (IF(AND(Table2[[#This Row],[Pending_question]]="Yes", OR( Table2[[#This Row],[Need_RRA]]="No", ISBLANK(Table2[[#This Row],[Need_RRA]])), OR(Table2[[#This Row],[Need_EIS]]="No", ISBLANK(Table2[[#This Row],[Need_EIS]])), OR(Table2[[#This Row],[Need_DON]]="No", ISBLANK(Table2[[#This Row],[Need_DON]]) )),"Question, no products",( IF( AND(Table2[[#This Row],[Pending_question]]="Yes", ISBLANK(Table2[[#This Row],[PQ_closure_date]])), (IF(SUM(Table2[[#This Row],[RRA_indic]],Table2[[#This Row],[EIS_indic]],Table2[[#This Row],[DON_indic]])=0, "Open Question, all products done",(I447IF(OR(Table2[[#This Row],[RRA_indic]]=2, Table2[[#This Row],[EIS_indic]]=2, Table2[[#This Row],[DON_indic]]=2),"Question, Products unknown",IF(AND(Table2[[#This Row],[RRA_indic]]=1, Table2[[#This Row],[EIS_indic]]=1, Table2[[#This Row],[DON_indic]]=1), "Open Question, RRA, EIS, DON", IF(AND(Table2[[#This Row],[RRA_indic]]=1, Table2[[#This Row],[EIS_indic]]=1), "Open Question, RRA, EIS",IF(AND(Table2[[#This Row],[RRA_indic]]=1, Table2[[#This Row],[DON_indic]]=1), "Open Question, RRA, DON", IF(AND(Table2[[#This Row],[EIS_indic]]=1, Table2[[#This Row],[DON_indic]]=1), "Open Question, EIS, DON",IF(Table2[[#This Row],[RRA_indic]]=1, "Open Question, RRA", IF(Table2[[#This Row],[EIS_indic]]=1, "Open Question, EIS", "Open Question, DON")))))))))), (IF(SUM(Table2[[#This Row],[RRA_indic]],Table2[[#This Row],[EIS_indic]],Table2[[#This Row],[DON_indic]])=0, "All Products done",(IF(OR(Table2[[#This Row],[RRA_indic]]=2, Table2[[#This Row],[EIS_indic]]=2, Table2[[#This Row],[DON_indic]]=2),"Unknown", IF(AND(Table2[[#This Row],[RRA_indic]]=1, Table2[[#This Row],[EIS_indic]]=1, Table2[[#This Row],[DON_indic]]=1), "Open RRA, EIS, DON", IF(AND(Table2[[#This Row],[RRA_indic]]=1, Table2[[#This Row],[EIS_indic]]=1), "Open RRA, EIS", IF(AND(Table2[[#This Row],[RRA_indic]]=1, Table2[[#This Row],[DON_indic]]=1), "Open RRA, DON", IF(AND(Table2[[#This Row],[EIS_indic]]=1, Table2[[#This Row],[DON_indic]]=1), "Open EIS, DON", IF(Table2[[#This Row],[RRA_indic]]=1, "Open RRA", IF(Table2[[#This Row],[EIS_indic]]=1, "Open EIS", "Open DON")))))))))))))))} -> All Products done | D23: Plummer/Anastasia | E23: Cholera | F23: Nigeria | G23: Not applicable | K23: 2021-E000172 | M23: No | P23: Yes | R23: 22 July: need to update / 22 July: Nigeria WCO agreed to the update, AFRO to initiate draft development/ 27 July: AFRO and CO provided their contributions on the RRA draft. / 28 July: With TT and Emilie for review with a deadline 2 pm 29 July / 4 August: TT comments received, more information is expected from the TC scheduled for 4 August to be added to the RRA. Draft with compiled HQ comments shared with AFRO and CO. Deadline - COB Thursday / 10 August: RRA v2 finalized and distributed | S23: 44399 | U23: 44419 | Y23: yes | AB23: 12 August: EIS proposed to AFRO / 20 August: AFRO and WCO are drafting the updated EIS and will share with us / 24 August: draft with inputs from WCO shared by AFRO. Sent to TT for comments, deadline - today / 25 August: shared with AFRO for NFP concurrance / 31 Aug: NFP concurrance received, to be posted today/ 1 Sept: EIS published | AH23: 44440 | AI23: no | AM23: =VLOOKUP(Table2[[#This Row],[country]],Countrycode!A:B,2,FALSE) -> NGA | AN23: =IF(ISBLANK(Table2[[#This Row],[Need_RRA]]), 2,(IF(Table2[[#This Row],[Need_RRA]]="No", 0, (IF(AND(Table2[[#This Row],[Need_RRA]]="Yes", Table2[[#This Row],[RRA_pub_date]]=""),1, 0))))) -> 0 | AO23: =IF(ISBLANK(Table2[[#This Row],[Need_EIS]]), 2,(IF(Table2[[#This Row],[Need_EIS]]="No", 0, (IF(AND(Table2[[#This Row],[Need_EIS]]="Yes", Table2[[#This Row],[EIS_pub_date]]=""),1, 0))))) -> 0 | AP23: =IF(ISBLANK(Table2[[#This Row],[Need_DON]]), 2,(IF(Table2[[#This Row],[Need_DON]]="No", 0, (IF(AND(Table2[[#This Row],[Need_DON]]="Yes", Table2[[#This Row],[DON_pub_date]]=""),1, 0))))) -> 0 | AQ23: =IF(ISBLANK(Table2[[#This Row],[Pending_question]]), 2,(IF(Table2[[#This Row],[Pending_question]]="Yes", 1, 0))) -> 0
A24: 44400 | B24: Closed | C24: {=IF(SUM(Table2[[#This Row],[PQ_indic]],Table2[[#This Row],[RRA_indic]],Table2[[#This Row],[EIS_indic]],Table2[[#This Row],[DON_indic]])=8, "Missing data", (IF(AND(Table2[[#This Row],[Pending_question]]="Yes", OR( Table2[[#This Row],[Need_RRA]]="No", ISBLANK(Table2[[#This Row],[Need_RRA]])), OR(Table2[[#This Row],[Need_EIS]]="No", ISBLANK(Table2[[#This Row],[Need_EIS]])), OR(Table2[[#This Row],[Need_DON]]="No", ISBLANK(Table2[[#This Row],[Need_DON]]) )),"Question, no products",( IF( AND(Table2[[#This Row],[Pending_question]]="Yes", ISBLANK(Table2[[#This Row],[PQ_closure_date]])), (IF(SUM(Table2[[#This Row],[RRA_indic]],Table2[[#This Row],[EIS_indic]],Table2[[#This Row],[DON_indic]])=0, "Open Question, all products done",(I447IF(OR(Table2[[#This Row],[RRA_indic]]=2, Table2[[#This Row],[EIS_indic]]=2, Table2[[#This Row],[DON_indic]]=2),"Question, Products unknown",IF(AND(Table2[[#This Row],[RRA_indic]]=1, Table2[[#This Row],[EIS_indic]]=1, Table2[[#This Row],[DON_indic]]=1), "Open Question, RRA, EIS, DON", IF(AND(Table2[[#This Row],[RRA_indic]]=1, Table2[[#This Row],[EIS_indic]]=1), "Open Question, RRA, EIS",IF(AND(Table2[[#This Row],[RRA_indic]]=1, Table2[[#This Row],[DON_indic]]=1), "Open Question, RRA, DON", IF(AND(Table2[[#This Row],[EIS_indic]]=1, Table2[[#This Row],[DON_indic]]=1), "Open Question, EIS, DON",IF(Table2[[#This Row],[RRA_indic]]=1, "Open Question, RRA", IF(Table2[[#This Row],[EIS_indic]]=1, "Open Question, EIS", "Open Question, DON")))))))))), (IF(SUM(Table2[[#This Row],[RRA_indic]],Table2[[#This Row],[EIS_indic]],Table2[[#This Row],[DON_indic]])=0, "All Products done",(IF(OR(Table2[[#This Row],[RRA_indic]]=2, Table2[[#This Row],[EIS_indic]]=2, Table2[[#This Row],[DON_indic]]=2),"Unknown", IF(AND(Table2[[#This Row],[RRA_indic]]=1, Table2[[#This Row],[EIS_indic]]=1, Table2[[#This Row],[DON_indic]]=1), "Open RRA, EIS, DON", IF(AND(Table2[[#This Row],[RRA_indic]]=1, Table2[[#This Row],[EIS_indic]]=1), "Open RRA, EIS", IF(AND(Table2[[#This Row],[RRA_indic]]=1, Table2[[#This Row],[DON_indic]]=1), "Open RRA, DON", IF(AND(Table2[[#This Row],[EIS_indic]]=1, Table2[[#This Row],[DON_indic]]=1), "Open EIS, DON", IF(Table2[[#This Row],[RRA_indic]]=1, "Open RRA", IF(Table2[[#This Row],[EIS_indic]]=1, "Open EIS", "Open DON")))))))))))))))} -> All Products done | D24: Plummer / Dunja | E24: Avian influenza A (H5N6) | F24: China | G24: Not applicable | H24: 44400 | M24: No | P24: No | Q24: Not applicable | Y24: yes | AB24: 22 July 2021: WPRO shared draft with us/ 23 July: PHI and TT provided comments, document sent back to WPRO for NFP concurrence/ 29 July: WPRO still waiting for IHR NFP/ 3 Aug: received cleared document from WPRO, cleared and published to EIS | AH24: 44411 | AI24: no | AM24: =VLOOKUP(Table2[[#This Row],[country]],Countrycode!A:B,2,FALSE) -> CHN | AN24: =IF(ISBLANK(Table2[[#This Row],[Need_RRA]]), 2,(IF(Table2[[#This Row],[Need_RRA]]="No", 0, (IF(AND(Table2[[#This Row],[Need_RRA]]="Yes", Table2[[#This Row],[RRA_pub_date]]=""),1, 0))))) -> 0 | AO24: =IF(ISBLANK(Table2[[#This Row],[Need_EIS]]), 2,(IF(Table2[[#This Row],[Need_EIS]]="No", 0, (IF(AND(Table2[[#This Row],[Need_EIS]]="Yes", Table2[[#This Row],[EIS_pub_date]]=""),1, 0))))) -> 0 | AP24: =IF(ISBLANK(Table2[[#This Row],[Need_DON]]), 2,(IF(Table2[[#This Row],[Need_DON]]="No", 0, (IF(AND(Table2[[#This Row],[Need_DON]]="Yes", Table2[[#This Row],[DON_pub_date]]=""),1, 0))))) -> 0 | AQ24: =IF(ISBLANK(Table2[[#This Row],[Pending_question]]), 2,(IF(Table2[[#This Row],[Pending_question]]="Yes", 1, 0))) -> 0 | AR24: to be included
A25: 44400 | B25: Closed | C25: {=IF(SUM(Table2[[#This Row],[PQ_indic]],Table2[[#This Row],[RRA_indic]],Table2[[#This Row],[EIS_indic]],Table2[[#This Row],[DON_indic]])=8, "Missing data", (IF(AND(Table2[[#This Row],[Pending_question]]="Yes", OR( Table2[[#This Row],[Need_RRA]]="No", ISBLANK(Table2[[#This Row],[Need_RRA]])), OR(Table2[[#This Row],[Need_EIS]]="No", ISBLANK(Table2[[#This Row],[Need_EIS]])), OR(Table2[[#This Row],[Need_DON]]="No", ISBLANK(Table2[[#This Row],[Need_DON]]) )),"Question, no products",( IF( AND(Table2[[#This Row],[Pending_question]]="Yes", ISBLANK(Table2[[#This Row],[PQ_closure_date]])), (IF(SUM(Table2[[#This Row],[RRA_indic]],Table2[[#This Row],[EIS_indic]],Table2[[#This Row],[DON_indic]])=0, "Open Question, all products done",(I447IF(OR(Table2[[#This Row],[RRA_indic]]=2, Table2[[#This Row],[EIS_indic]]=2, Table2[[#This Row],[DON_indic]]=2),"Question, Products unknown",IF(AND(Table2[[#This Row],[RRA_indic]]=1, Table2[[#This Row],[EIS_indic]]=1, Table2[[#This Row],[DON_indic]]=1), "Open Question, RRA, EIS, DON", IF(AND(Table2[[#This Row],[RRA_indic]]=1, Table2[[#This Row],[EIS_indic]]=1), "Open Question, RRA, EIS",IF(AND(Table2[[#This Row],[RRA_indic]]=1, Table2[[#This Row],[DON_indic]]=1), "Open Question, RRA, DON", IF(AND(Table2[[#This Row],[EIS_indic]]=1, Table2[[#This Row],[DON_indic]]=1), "Open Question, EIS, DON",IF(Table2[[#This Row],[RRA_indic]]=1, "Open Question, RRA", IF(Table2[[#This Row],[EIS_indic]]=1, "Open Question, EIS", "Open Question, DON")))))))))), (IF(SUM(Table2[[#This Row],[RRA_indic]],Table2[[#This Row],[EIS_indic]],Table2[[#This Row],[DON_indic]])=0, "All Products done",(IF(OR(Table2[[#This Row],[RRA_indic]]=2, Table2[[#This Row],[EIS_indic]]=2, Table2[[#This Row],[DON_indic]]=2),"Unknown", IF(AND(Table2[[#This Row],[RRA_indic]]=1, Table2[[#This Row],[EIS_indic]]=1, Table2[[#This Row],[DON_indic]]=1), "Open RRA, EIS, DON", IF(AND(Table2[[#This Row],[RRA_indic]]=1, Table2[[#This Row],[EIS_indic]]=1), "Open RRA, EIS", IF(AND(Table2[[#This Row],[RRA_indic]]=1, Table2[[#This Row],[DON_indic]]=1), "Open RRA, DON", IF(AND(Table2[[#This Row],[EIS_indic]]=1, Table2[[#This Row],[DON_indic]]=1), "Open EIS, DON", IF(Table2[[#This Row],[RRA_indic]]=1, "Open RRA", IF(Table2[[#This Row],[EIS_indic]]=1, "Open EIS", "Open DON")))))))))))))))} -> All Products done | D25: Lidia | E25: Hepatitis E | F25: Sudan | G25: Not applicable | H25: 44400 | K25: 2021-E000297 | M25: No | P25: Yes | R25: 3LTC held on 11 August. WCO continues to advocate with the MoH for an EIS, although at this stage would be challenging. Agreement accross the 3 levels on initiating a RRA. EMRO/WCO started the draft on 12 August.Reminder sent on 16 August and EMRO replied that the RRA was dratfted , but were waiting for additinal inputs form the TT side and will be shared shortly. Initial RRA draft received on 18 August. Distributed at HQ level for review with deadline 11AM, on 19 August. Shared back with SEARO on 20 August. 3LTC scheduled on 20 August at 13PM. Following the 3LTC on 20 August, the comments in the RRA draft are pending to be adressed by WCO and EMRO. There is a discussion regarding re-including the SAGE recommendation and Alex will work on it as well. Aura will check with Rick Brennan regarding the grading, as it was insisted by WCO. HQ was not in favor. Final feedback from HQ received on 23 April. Follow up email sent to EMRO on 24 August, to furher share the final consolidated version and proceed with the finalisation. Disseminated on 25 August 2021 | S25: 44420 | U25: 44433 | Y25: yes | AB25: 28 July: we need an EIS. Proposition for EIS sent to EMRO on 29 July. Reminder sent on 2 August. EMRO replied that they are gathering further information. Reminder sent on 5 August and reply received from WCO , proposing a short TC for 6 August."The situation is challenging! There was due to be a meeting between all parties today to sort out the problem, but in the meantime we have limited updates".Another parallel meeting is being planed for the week of 9 August. 3LTC held on 11 August.WCO continues to advocate with the MoH for an EIS, although at this stage would be challenging. Following the 3LTC , agreement to have an EIS following the RRA. Remider sent to EMRO on 30 August. Feedback received form EMRO on 31 August that they will start the EIS draft. EIS draft shared by EMRo on 2 September. Further inputs provided by HQ and circulated back to EMRO on Saturday, 4 September. Follow up with EMRO on 6 September. EMRO is consolidating the draft and will share back ASAP . On 8 September a gentle reminder sent to EMRO.15 September : follow up email sent. EIS received the same day with the NFP conncurrence. 16 September:Cleared draft EIS shared back with EMRo for courtesy. Deadline 3 PM for posting. EIS published 16 Sept 2021 | AH25: 44455 | AI25: no | AM25: =VLOOKUP(Table2[[#This Row],[country]],Countrycode!A:B,2,FALSE) -> SDN | AN25: =IF(ISBLANK(Table2[[#This Row],[Need_RRA]]), 2,(IF(Table2[[#This Row],[Need_RRA]]="No", 0, (IF(AND(Table2[[#This Row],[Need_RRA]]="Yes", Table2[[#This Row],[RRA_pub_date]]=""),1, 0))))) -> 0 | AO25: =IF(ISBLANK(Table2[[#This Row],[Need_EIS]]), 2,(IF(Table2[[#This Row],[Need_EIS]]="No", 0, (IF(AND(Table2[[#This Row],[Need_EIS]]="Yes", Table2[[#This Row],[EIS_pub_date]]=""),1, 0))))) -> 0 | AP25: =IF(ISBLANK(Table2[[#This Row],[Need_DON]]), 2,(IF(Table2[[#This Row],[Need_DON]]="No", 0, (IF(AND(Table2[[#This Row],[Need_DON]]="Yes", Table2[[#This Row],[DON_pub_date]]=""),1, 0))))) -> 0 | AQ25: =IF(ISBLANK(Table2[[#This Row],[Pending_question]]), 2,(IF(Table2[[#This Row],[Pending_question]]="Yes", 1, 0))) -> 0 | AR25: 44400
A26: 44412 | B26: Closed | C26: {=IF(SUM(Table2[[#This Row],[PQ_indic]],Table2[[#This Row],[RRA_indic]],Table2[[#This Row],[EIS_indic]],Table2[[#This Row],[DON_indic]])=8, "Missing data", (IF(AND(Table2[[#This Row],[Pending_question]]="Yes", OR( Table2[[#This Row],[Need_RRA]]="No", ISBLANK(Table2[[#This Row],[Need_RRA]])), OR(Table2[[#This Row],[Need_EIS]]="No", ISBLANK(Table2[[#This Row],[Need_EIS]])), OR(Table2[[#This Row],[Need_DON]]="No", ISBLANK(Table2[[#This Row],[Need_DON]]) )),"Question, no products",( IF( AND(Table2[[#This Row],[Pending_question]]="Yes", ISBLANK(Table2[[#This Row],[PQ_closure_date]])), (IF(SUM(Table2[[#This Row],[RRA_indic]],Table2[[#This Row],[EIS_indic]],Table2[[#This Row],[DON_indic]])=0, "Open Question, all products done",(I447IF(OR(Table2[[#This Row],[RRA_indic]]=2, Table2[[#This Row],[EIS_indic]]=2, Table2[[#This Row],[DON_indic]]=2),"Question, Products unknown",IF(AND(Table2[[#This Row],[RRA_indic]]=1, Table2[[#This Row],[EIS_indic]]=1, Table2[[#This Row],[DON_indic]]=1), "Open Question, RRA, EIS, DON", IF(AND(Table2[[#This Row],[RRA_indic]]=1, Table2[[#This Row],[EIS_indic]]=1), "Open Question, RRA, EIS",IF(AND(Table2[[#This Row],[RRA_indic]]=1, Table2[[#This Row],[DON_indic]]=1), "Open Question, RRA, DON", IF(AND(Table2[[#This Row],[EIS_indic]]=1, Table2[[#This Row],[DON_indic]]=1), "Open Question, EIS, DON",IF(Table2[[#This Row],[RRA_indic]]=1, "Open Question, RRA", IF(Table2[[#This Row],[EIS_indic]]=1, "Open Question, EIS", "Open Question, DON")))))))))), (IF(SUM(Table2[[#This Row],[RRA_indic]],Table2[[#This Row],[EIS_indic]],Table2[[#This Row],[DON_indic]])=0, "All Products done",(IF(OR(Table2[[#This Row],[RRA_indic]]=2, Table2[[#This Row],[EIS_indic]]=2, Table2[[#This Row],[DON_indic]]=2),"Unknown", IF(AND(Table2[[#This Row],[RRA_indic]]=1, Table2[[#This Row],[EIS_indic]]=1, Table2[[#This Row],[DON_indic]]=1), "Open RRA, EIS, DON", IF(AND(Table2[[#This Row],[RRA_indic]]=1, Table2[[#This Row],[EIS_indic]]=1), "Open RRA, EIS", IF(AND(Table2[[#This Row],[RRA_indic]]=1, Table2[[#This Row],[DON_indic]]=1), "Open RRA, DON", IF(AND(Table2[[#This Row],[EIS_indic]]=1, Table2[[#This Row],[DON_indic]]=1), "Open EIS, DON", IF(Table2[[#This Row],[RRA_indic]]=1, "Open RRA", IF(Table2[[#This Row],[EIS_indic]]=1, "Open EIS", "Open DON")))))))))))))))} -> All Products done | D26: Dunja | E26: Marburg | F26: Guinea | G26: Not applicable | H26: 44412 | J26: 44414 | K26: 2021-E000287 | M26: No | P26: Yes | R26: 5 August, received draft from AFRO/ 7 August finalized and distributed | S26: 44415 | U26: 44415 | Y26: yes | AB26: 5 August the draft shared with Esther for review before sending to AFRO and TT/7 August EIS sent to NFP / on 8 email followup sent to AFRO / 8 August published | AH26: 44416 | AI26: yes | AK26: 44417 | AL26: Without NFP concurence | AM26: =VLOOKUP(Table2[[#This Row],[country]],Countrycode!A:B,2,FALSE) -> GIN | AN26: =IF(ISBLANK(Table2[[#This Row],[Need_RRA]]), 2,(IF(Table2[[#This Row],[Need_RRA]]="No", 0, (IF(AND(Table2[[#This Row],[Need_RRA]]="Yes", Table2[[#This Row],[RRA_pub_date]]=""),1, 0))))) -> 0 | AO26: =IF(ISBLANK(Table2[[#This Row],[Need_EIS]]), 2,(IF(Table2[[#This Row],[Need_EIS]]="No", 0, (IF(AND(Table2[[#This Row],[Need_EIS]]="Yes", Table2[[#This Row],[EIS_pub_date]]=""),1, 0))))) -> 0 | AP26: =IF(ISBLANK(Table2[[#This Row],[Need_DON]]), 2,(IF(Table2[[#This Row],[Need_DON]]="No", 0, (IF(AND(Table2[[#This Row],[Need_DON]]="Yes", Table2[[#This Row],[DON_pub_date]]=""),1, 0))))) -> 0 | AQ26: =IF(ISBLANK(Table2[[#This Row],[Pending_question]]), 2,(IF(Table2[[#This Row],[Pending_question]]="Yes", 1, 0))) -> 0 | AR26: 44413
A27: 44417 | B27: Closed | C27: {=IF(SUM(Table2[[#This Row],[PQ_indic]],Table2[[#This Row],[RRA_indic]],Table2[[#This Row],[EIS_indic]],Table2[[#This Row],[DON_indic]])=8, "Missing data", (IF(AND(Table2[[#This Row],[Pending_question]]="Yes", OR( Table2[[#This Row],[Need_RRA]]="No", ISBLANK(Table2[[#This Row],[Need_RRA]])), OR(Table2[[#This Row],[Need_EIS]]="No", ISBLANK(Table2[[#This Row],[Need_EIS]])), OR(Table2[[#This Row],[Need_DON]]="No", ISBLANK(Table2[[#This Row],[Need_DON]]) )),"Question, no products",( IF( AND(Table2[[#This Row],[Pending_question]]="Yes", ISBLANK(Table2[[#This Row],[PQ_closure_date]])), (IF(SUM(Table2[[#This Row],[RRA_indic]],Table2[[#This Row],[EIS_indic]],Table2[[#This Row],[DON_indic]])=0, "Open Question, all products done",(I447IF(OR(Table2[[#This Row],[RRA_indic]]=2, Table2[[#This Row],[EIS_indic]]=2, Table2[[#This Row],[DON_indic]]=2),"Question, Products unknown",IF(AND(Table2[[#This Row],[RRA_indic]]=1, Table2[[#This Row],[EIS_indic]]=1, Table2[[#This Row],[DON_indic]]=1), "Open Question, RRA, EIS, DON", IF(AND(Table2[[#This Row],[RRA_indic]]=1, Table2[[#This Row],[EIS_indic]]=1), "Open Question, RRA, EIS",IF(AND(Table2[[#This Row],[RRA_indic]]=1, Table2[[#This Row],[DON_indic]]=1), "Open Question, RRA, DON", IF(AND(Table2[[#This Row],[EIS_indic]]=1, Table2[[#This Row],[DON_indic]]=1), "Open Question, EIS, DON",IF(Table2[[#This Row],[RRA_indic]]=1, "Open Question, RRA", IF(Table2[[#This Row],[EIS_indic]]=1, "Open Question, EIS", "Open Question, DON")))))))))), (IF(SUM(Table2[[#This Row],[RRA_indic]],Table2[[#This Row],[EIS_indic]],Table2[[#This Row],[DON_indic]])=0, "All Products done",(IF(OR(Table2[[#This Row],[RRA_indic]]=2, Table2[[#This Row],[EIS_indic]]=2, Table2[[#This Row],[DON_indic]]=2),"Unknown", IF(AND(Table2[[#This Row],[RRA_indic]]=1, Table2[[#This Row],[EIS_indic]]=1, Table2[[#This Row],[DON_indic]]=1), "Open RRA, EIS, DON", IF(AND(Table2[[#This Row],[RRA_indic]]=1, Table2[[#This Row],[EIS_indic]]=1), "Open RRA, EIS", IF(AND(Table2[[#This Row],[RRA_indic]]=1, Table2[[#This Row],[DON_indic]]=1), "Open RRA, DON", IF(AND(Table2[[#This Row],[EIS_indic]]=1, Table2[[#This Row],[DON_indic]]=1), "Open EIS, DON", IF(Table2[[#This Row],[RRA_indic]]=1, "Open RRA", IF(Table2[[#This Row],[EIS_indic]]=1, "Open EIS", "Open DON")))))))))))))))} -> All Products done | D27: Elvis | E27: Avian influenza A (H5N6) | F27: China | G27: Not applicable | H27: 44417 | J27: 44417 | M27: No | P27: No | Q27: Not applicable | Y27: yes | AB27: 9 August: Draft EIS shared by WHO with PHI-HQ/10 August: PHI shared draft with TT for inputs. Feedback expected by COB/10 August TT feedback recieved and inputs shared with WPRO for NFP concurrence | AH27: 44418 | AI27: no | AM27: =VLOOKUP(Table2[[#This Row],[country]],Countrycode!A:B,2,FALSE) -> CHN | AN27: =IF(ISBLANK(Table2[[#This Row],[Need_RRA]]), 2,(IF(Table2[[#This Row],[Need_RRA]]="No", 0, (IF(AND(Table2[[#This Row],[Need_RRA]]="Yes", Table2[[#This Row],[RRA_pub_date]]=""),1, 0))))) -> 0 | AO27: =IF(ISBLANK(Table2[[#This Row],[Need_EIS]]), 2,(IF(Table2[[#This Row],[Need_EIS]]="No", 0, (IF(AND(Table2[[#This Row],[Need_EIS]]="Yes", Table2[[#This Row],[EIS_pub_date]]=""),1, 0))))) -> 0 | AP27: =IF(ISBLANK(Table2[[#This Row],[Need_DON]]), 2,(IF(Table2[[#This Row],[Need_DON]]="No", 0, (IF(AND(Table2[[#This Row],[Need_DON]]="Yes", Table2[[#This Row],[DON_pub_date]]=""),1, 0))))) -> 0 | AQ27: =IF(ISBLANK(Table2[[#This Row],[Pending_question]]), 2,(IF(Table2[[#This Row],[Pending_question]]="Yes", 1, 0))) -> 0 | AR27: 44418
A28: 44419 | B28: Closed | C28: {=IF(SUM(Table2[[#This Row],[PQ_indic]],Table2[[#This Row],[RRA_indic]],Table2[[#This Row],[EIS_indic]],Table2[[#This Row],[DON_indic]])=8, "Missing data", (IF(AND(Table2[[#This Row],[Pending_question]]="Yes", OR( Table2[[#This Row],[Need_RRA]]="No", ISBLANK(Table2[[#This Row],[Need_RRA]])), OR(Table2[[#This Row],[Need_EIS]]="No", ISBLANK(Table2[[#This Row],[Need_EIS]])), OR(Table2[[#This Row],[Need_DON]]="No", ISBLANK(Table2[[#This Row],[Need_DON]]) )),"Question, no products",( IF( AND(Table2[[#This Row],[Pending_question]]="Yes", ISBLANK(Table2[[#This Row],[PQ_closure_date]])), (IF(SUM(Table2[[#This Row],[RRA_indic]],Table2[[#This Row],[EIS_indic]],Table2[[#This Row],[DON_indic]])=0, "Open Question, all products done",(I447IF(OR(Table2[[#This Row],[RRA_indic]]=2, Table2[[#This Row],[EIS_indic]]=2, Table2[[#This Row],[DON_indic]]=2),"Question, Products unknown",IF(AND(Table2[[#This Row],[RRA_indic]]=1, Table2[[#This Row],[EIS_indic]]=1, Table2[[#This Row],[DON_indic]]=1), "Open Question, RRA, EIS, DON", IF(AND(Table2[[#This Row],[RRA_indic]]=1, Table2[[#This Row],[EIS_indic]]=1), "Open Question, RRA, EIS",IF(AND(Table2[[#This Row],[RRA_indic]]=1, Table2[[#This Row],[DON_indic]]=1), "Open Question, RRA, DON", IF(AND(Table2[[#This Row],[EIS_indic]]=1, Table2[[#This Row],[DON_indic]]=1), "Open Question, EIS, DON",IF(Table2[[#This Row],[RRA_indic]]=1, "Open Question, RRA", IF(Table2[[#This Row],[EIS_indic]]=1, "Open Question, EIS", "Open Question, DON")))))))))), (IF(SUM(Table2[[#This Row],[RRA_indic]],Table2[[#This Row],[EIS_indic]],Table2[[#This Row],[DON_indic]])=0, "All Products done",(IF(OR(Table2[[#This Row],[RRA_indic]]=2, Table2[[#This Row],[EIS_indic]]=2, Table2[[#This Row],[DON_indic]]=2),"Unknown", IF(AND(Table2[[#This Row],[RRA_indic]]=1, Table2[[#This Row],[EIS_indic]]=1, Table2[[#This Row],[DON_indic]]=1), "Open RRA, EIS, DON", IF(AND(Table2[[#This Row],[RRA_indic]]=1, Table2[[#This Row],[EIS_indic]]=1), "Open RRA, EIS", IF(AND(Table2[[#This Row],[RRA_indic]]=1, Table2[[#This Row],[DON_indic]]=1), "Open RRA, DON", IF(AND(Table2[[#This Row],[EIS_indic]]=1, Table2[[#This Row],[DON_indic]]=1), "Open EIS, DON", IF(Table2[[#This Row],[RRA_indic]]=1, "Open RRA", IF(Table2[[#This Row],[EIS_indic]]=1, "Open EIS", "Open DON")))))))))))))))} -> All Products done | D28: Dunja/Plummer/Anastasia | E28: Cholera | F28: Niger | G28: Not applicable | K28: 2021-E000293 | M28: No | P28: Yes | R28: 10 August first draft of RRA shared by WCO/12 August: HQ inputs shared, AFRO inputs shared / 17 August: finalized and distributed | S28: 44419 | U28: 44425 | Y28: yes | AB28: 19 August: first draft shared by AFRO, sent to TT for comments with a deadline today COB/ 20 Aug: Word document copy shared with AFRO for NFP concurrence/ 23 August: reminder sent to AFRO and CO / 25 August: another reminder sent to AFRO and CO. AFRO replied that EIS is still with NFP, CO is in contact with NFP. / 30 Aug: another reminder sent. CO is following up with NFP./ 2 Sept: updated EIS document received and published | AH28: 44441 | AI28: no | AM28: =VLOOKUP(Table2[[#This Row],[country]],Countrycode!A:B,2,FALSE) -> NER | AN28: =IF(ISBLANK(Table2[[#This Row],[Need_RRA]]), 2,(IF(Table2[[#This Row],[Need_RRA]]="No", 0, (IF(AND(Table2[[#This Row],[Need_RRA]]="Yes", Table2[[#This Row],[RRA_pub_date]]=""),1, 0))))) -> 0 | AO28: =IF(ISBLANK(Table2[[#This Row],[Need_EIS]]), 2,(IF(Table2[[#This Row],[Need_EIS]]="No", 0, (IF(AND(Table2[[#This Row],[Need_EIS]]="Yes", Table2[[#This Row],[EIS_pub_date]]=""),1, 0))))) -> 0 | AP28: =IF(ISBLANK(Table2[[#This Row],[Need_DON]]), 2,(IF(Table2[[#This Row],[Need_DON]]="No", 0, (IF(AND(Table2[[#This Row],[Need_DON]]="Yes", Table2[[#This Row],[DON_pub_date]]=""),1, 0))))) -> 0 | AQ28: =IF(ISBLANK(Table2[[#This Row],[Pending_question]]), 2,(IF(Table2[[#This Row],[Pending_question]]="Yes", 1, 0))) -> 0 | AR28: 44417
A29: 44422 | B29: Closed | C29: {=IF(SUM(Table2[[#This Row],[PQ_indic]],Table2[[#This Row],[RRA_indic]],Table2[[#This Row],[EIS_indic]],Table2[[#This Row],[DON_indic]])=8, "Missing data", (IF(AND(Table2[[#This Row],[Pending_question]]="Yes", OR( Table2[[#This Row],[Need_RRA]]="No", ISBLANK(Table2[[#This Row],[Need_RRA]])), OR(Table2[[#This Row],[Need_EIS]]="No", ISBLANK(Table2[[#This Row],[Need_EIS]])), OR(Table2[[#This Row],[Need_DON]]="No", ISBLANK(Table2[[#This Row],[Need_DON]]) )),"Question, no products",( IF( AND(Table2[[#This Row],[Pending_question]]="Yes", ISBLANK(Table2[[#This Row],[PQ_closure_date]])), (IF(SUM(Table2[[#This Row],[RRA_indic]],Table2[[#This Row],[EIS_indic]],Table2[[#This Row],[DON_indic]])=0, "Open Question, all products done",(I447IF(OR(Table2[[#This Row],[RRA_indic]]=2, Table2[[#This Row],[EIS_indic]]=2, Table2[[#This Row],[DON_indic]]=2),"Question, Products unknown",IF(AND(Table2[[#This Row],[RRA_indic]]=1, Table2[[#This Row],[EIS_indic]]=1, Table2[[#This Row],[DON_indic]]=1), "Open Question, RRA, EIS, DON", IF(AND(Table2[[#This Row],[RRA_indic]]=1, Table2[[#This Row],[EIS_indic]]=1), "Open Question, RRA, EIS",IF(AND(Table2[[#This Row],[RRA_indic]]=1, Table2[[#This Row],[DON_indic]]=1), "Open Question, RRA, DON", IF(AND(Table2[[#This Row],[EIS_indic]]=1, Table2[[#This Row],[DON_indic]]=1), "Open Question, EIS, DON",IF(Table2[[#This Row],[RRA_indic]]=1, "Open Question, RRA", IF(Table2[[#This Row],[EIS_indic]]=1, "Open Question, EIS", "Open Question, DON")))))))))), (IF(SUM(Table2[[#This Row],[RRA_indic]],Table2[[#This Row],[EIS_indic]],Table2[[#This Row],[DON_indic]])=0, "All Products done",(IF(OR(Table2[[#This Row],[RRA_indic]]=2, Table2[[#This Row],[EIS_indic]]=2, Table2[[#This Row],[DON_indic]]=2),"Unknown", IF(AND(Table2[[#This Row],[RRA_indic]]=1, Table2[[#This Row],[EIS_indic]]=1, Table2[[#This Row],[DON_indic]]=1), "Open RRA, EIS, DON", IF(AND(Table2[[#This Row],[RRA_indic]]=1, Table2[[#This Row],[EIS_indic]]=1), "Open RRA, EIS", IF(AND(Table2[[#This Row],[RRA_indic]]=1, Table2[[#This Row],[DON_indic]]=1), "Open RRA, DON", IF(AND(Table2[[#This Row],[EIS_indic]]=1, Table2[[#This Row],[DON_indic]]=1), "Open EIS, DON", IF(Table2[[#This Row],[RRA_indic]]=1, "Open RRA", IF(Table2[[#This Row],[EIS_indic]]=1, "Open EIS", "Open DON")))))))))))))))} -> All Products done | D29: Dunja/Elvis | E29: Ebola virus disease | F29: Cote D'Ivoire | G29: Not applicable | H29: 44422 | K29: 2021-E000300 | M29: No | P29: Yes | R29: 14 August: RRA drafted/15 August: draft RRA shared with all levels, reviewed, finalized and disseminated | S29: 44422 | U29: 44423 | Y29: yes | AB29: 15 August: EIS drafted and shared with all level. Pending lab details1/16 August: published as suspected case, received the green light from Soce. Oliver reviewed the final EIS./31 Aug a new EIS drafted /1 Sep, shared with Oliver, published | AH29: 44440 | AI29: no | AL29: EVD negative | AM29: =VLOOKUP(Table2[[#This Row],[country]],Countrycode!A:B,2,FALSE) -> CIV | AN29: =IF(ISBLANK(Table2[[#This Row],[Need_RRA]]), 2,(IF(Table2[[#This Row],[Need_RRA]]="No", 0, (IF(AND(Table2[[#This Row],[Need_RRA]]="Yes", Table2[[#This Row],[RRA_pub_date]]=""),1, 0))))) -> 0 | AO29: =IF(ISBLANK(Table2[[#This Row],[Need_EIS]]), 2,(IF(Table2[[#This Row],[Need_EIS]]="No", 0, (IF(AND(Table2[[#This Row],[Need_EIS]]="Yes", Table2[[#This Row],[EIS_pub_date]]=""),1, 0))))) -> 0 | AP29: =IF(ISBLANK(Table2[[#This Row],[Need_DON]]), 2,(IF(Table2[[#This Row],[Need_DON]]="No", 0, (IF(AND(Table2[[#This Row],[Need_DON]]="Yes", Table2[[#This Row],[DON_pub_date]]=""),1, 0))))) -> 0 | AQ29: =IF(ISBLANK(Table2[[#This Row],[Pending_question]]), 2,(IF(Table2[[#This Row],[Pending_question]]="Yes", 1, 0))) -> 0 | AR29: 44422
A30: 44426 | B30: Closed | C30: {=IF(SUM(Table2[[#This Row],[PQ_indic]],Table2[[#This Row],[RRA_indic]],Table2[[#This Row],[EIS_indic]],Table2[[#This Row],[DON_indic]])=8, "Missing data", (IF(AND(Table2[[#This Row],[Pending_question]]="Yes", OR( Table2[[#This Row],[Need_RRA]]="No", ISBLANK(Table2[[#This Row],[Need_RRA]])), OR(Table2[[#This Row],[Need_EIS]]="No", ISBLANK(Table2[[#This Row],[Need_EIS]])), OR(Table2[[#This Row],[Need_DON]]="No", ISBLANK(Table2[[#This Row],[Need_DON]]) )),"Question, no products",( IF( AND(Table2[[#This Row],[Pending_question]]="Yes", ISBLANK(Table2[[#This Row],[PQ_closure_date]])), (IF(SUM(Table2[[#This Row],[RRA_indic]],Table2[[#This Row],[EIS_indic]],Table2[[#This Row],[DON_indic]])=0, "Open Question, all products done",(I447IF(OR(Table2[[#This Row],[RRA_indic]]=2, Table2[[#This Row],[EIS_indic]]=2, Table2[[#This Row],[DON_indic]]=2),"Question, Products unknown",IF(AND(Table2[[#This Row],[RRA_indic]]=1, Table2[[#This Row],[EIS_indic]]=1, Table2[[#This Row],[DON_indic]]=1), "Open Question, RRA, EIS, DON", IF(AND(Table2[[#This Row],[RRA_indic]]=1, Table2[[#This Row],[EIS_indic]]=1), "Open Question, RRA, EIS",IF(AND(Table2[[#This Row],[RRA_indic]]=1, Table2[[#This Row],[DON_indic]]=1), "Open Question, RRA, DON", IF(AND(Table2[[#This Row],[EIS_indic]]=1, Table2[[#This Row],[DON_indic]]=1), "Open Question, EIS, DON",IF(Table2[[#This Row],[RRA_indic]]=1, "Open Question, RRA", IF(Table2[[#This Row],[EIS_indic]]=1, "Open Question, EIS", "Open Question, DON")))))))))), (IF(SUM(Table2[[#This Row],[RRA_indic]],Table2[[#This Row],[EIS_indic]],Table2[[#This Row],[DON_indic]])=0, "All Products done",(IF(OR(Table2[[#This Row],[RRA_indic]]=2, Table2[[#This Row],[EIS_indic]]=2, Table2[[#This Row],[DON_indic]]=2),"Unknown", IF(AND(Table2[[#This Row],[RRA_indic]]=1, Table2[[#This Row],[EIS_indic]]=1, Table2[[#This Row],[DON_indic]]=1), "Open RRA, EIS, DON", IF(AND(Table2[[#This Row],[RRA_indic]]=1, Table2[[#This Row],[EIS_indic]]=1), "Open RRA, EIS", IF(AND(Table2[[#This Row],[RRA_indic]]=1, Table2[[#This Row],[DON_indic]]=1), "Open RRA, DON", IF(AND(Table2[[#This Row],[EIS_indic]]=1, Table2[[#This Row],[DON_indic]]=1), "Open EIS, DON", IF(Table2[[#This Row],[RRA_indic]]=1, "Open RRA", IF(Table2[[#This Row],[EIS_indic]]=1, "Open EIS", "Open DON")))))))))))))))} -> All Products done | D30: Dunja | E30: Avian influenza A (H5N6) | F30: China | G30: Not applicable | M30: No | P30: No | Q30: Not applicable | R30: Not planned | Y30: yes | AB30: 13 August, a new, additional casebreported, household contact of the confirmed case7 EIS drafted by WPRO, on the same day Dunja contacted WPRO asking for merging 2 cases in 1 EIS ( given that previous EIS was not yet concurred by NFP). /14 August a new EIS for both cases received from WPRO, on the same day HQ provided feedback and sent it back to WPRO. /17 August reminder sent to WPRO /18 August received EIS and published | AH30: 44426 | AI30: no | AL30: EIS with NFP | AM30: =VLOOKUP(Table2[[#This Row],[country]],Countrycode!A:B,2,FALSE) -> CHN | AN30: =IF(ISBLANK(Table2[[#This Row],[Need_RRA]]), 2,(IF(Table2[[#This Row],[Need_RRA]]="No", 0, (IF(AND(Table2[[#This Row],[Need_RRA]]="Yes", Table2[[#This Row],[RRA_pub_date]]=""),1, 0))))) -> 0 | AO30: =IF(ISBLANK(Table2[[#This Row],[Need_EIS]]), 2,(IF(Table2[[#This Row],[Need_EIS]]="No", 0, (IF(AND(Table2[[#This Row],[Need_EIS]]="Yes", Table2[[#This Row],[EIS_pub_date]]=""),1, 0))))) -> 0 | AP30: =IF(ISBLANK(Table2[[#This Row],[Need_DON]]), 2,(IF(Table2[[#This Row],[Need_DON]]="No", 0, (IF(AND(Table2[[#This Row],[Need_DON]]="Yes", Table2[[#This Row],[DON_pub_date]]=""),1, 0))))) -> 0 | AQ30: =IF(ISBLANK(Table2[[#This Row],[Pending_question]]), 2,(IF(Table2[[#This Row],[Pending_question]]="Yes", 1, 0))) -> 0 | AR30: 44421
A31: 44426 | B31: Closed | C31: {=IF(SUM(Table2[[#This Row],[PQ_indic]],Table2[[#This Row],[RRA_indic]],Table2[[#This Row],[EIS_indic]],Table2[[#This Row],[DON_indic]])=8, "Missing data", (IF(AND(Table2[[#This Row],[Pending_question]]="Yes", OR( Table2[[#This Row],[Need_RRA]]="No", ISBLANK(Table2[[#This Row],[Need_RRA]])), OR(Table2[[#This Row],[Need_EIS]]="No", ISBLANK(Table2[[#This Row],[Need_EIS]])), OR(Table2[[#This Row],[Need_DON]]="No", ISBLANK(Table2[[#This Row],[Need_DON]]) )),"Question, no products",( IF( AND(Table2[[#This Row],[Pending_question]]="Yes", ISBLANK(Table2[[#This Row],[PQ_closure_date]])), (IF(SUM(Table2[[#This Row],[RRA_indic]],Table2[[#This Row],[EIS_indic]],Table2[[#This Row],[DON_indic]])=0, "Open Question, all products done",(I447IF(OR(Table2[[#This Row],[RRA_indic]]=2, Table2[[#This Row],[EIS_indic]]=2, Table2[[#This Row],[DON_indic]]=2),"Question, Products unknown",IF(AND(Table2[[#This Row],[RRA_indic]]=1, Table2[[#This Row],[EIS_indic]]=1, Table2[[#This Row],[DON_indic]]=1), "Open Question, RRA, EIS, DON", IF(AND(Table2[[#This Row],[RRA_indic]]=1, Table2[[#This Row],[EIS_indic]]=1), "Open Question, RRA, EIS",IF(AND(Table2[[#This Row],[RRA_indic]]=1, Table2[[#This Row],[DON_indic]]=1), "Open Question, RRA, DON", IF(AND(Table2[[#This Row],[EIS_indic]]=1, Table2[[#This Row],[DON_indic]]=1), "Open Question, EIS, DON",IF(Table2[[#This Row],[RRA_indic]]=1, "Open Question, RRA", IF(Table2[[#This Row],[EIS_indic]]=1, "Open Question, EIS", "Open Question, DON")))))))))), (IF(SUM(Table2[[#This Row],[RRA_indic]],Table2[[#This Row],[EIS_indic]],Table2[[#This Row],[DON_indic]])=0, "All Products done",(IF(OR(Table2[[#This Row],[RRA_indic]]=2, Table2[[#This Row],[EIS_indic]]=2, Table2[[#This Row],[DON_indic]]=2),"Unknown", IF(AND(Table2[[#This Row],[RRA_indic]]=1, Table2[[#This Row],[EIS_indic]]=1, Table2[[#This Row],[DON_indic]]=1), "Open RRA, EIS, DON", IF(AND(Table2[[#This Row],[RRA_indic]]=1, Table2[[#This Row],[EIS_indic]]=1), "Open RRA, EIS", IF(AND(Table2[[#This Row],[RRA_indic]]=1, Table2[[#This Row],[DON_indic]]=1), "Open RRA, DON", IF(AND(Table2[[#This Row],[EIS_indic]]=1, Table2[[#This Row],[DON_indic]]=1), "Open EIS, DON", IF(Table2[[#This Row],[RRA_indic]]=1, "Open RRA", IF(Table2[[#This Row],[EIS_indic]]=1, "Open EIS", "Open DON")))))))))))))))} -> All Products done | D31: Elvis and lidia | E31: Yellow Fever | F31: Nigeria | G31: Not applicable | H31: 44426 | J31: 42992 | K31: 2017-E000279 | L31: 14-Sept-2017 first created; updated on 17-Sept-21 | M31: No | P31: Yes | R31: Initial draft RRA recieved by AFRO on 18 August. Shared with the TTs at HQ for review on 18 August, with deadline by 11AM on 19 August. 25 August : disseminated | S31: 44420 | U31: 44433 | Y31: yes | AB31: To be discussed with AFRO, following the RRA. Posted on 17 September 2021 | AH31: 44456 | AI31: yes | AK31: 44470 | AL31: https://ems.who.int/Event/eventSummary.aspx?eid=2017-E000279 | AM31: =VLOOKUP(Table2[[#This Row],[country]],Countrycode!A:B,2,FALSE) -> NGA | AN31: =IF(ISBLANK(Table2[[#This Row],[Need_RRA]]), 2,(IF(Table2[[#This Row],[Need_RRA]]="No", 0, (IF(AND(Table2[[#This Row],[Need_RRA]]="Yes", Table2[[#This Row],[RRA_pub_date]]=""),1, 0))))) -> 0 | AO31: =IF(ISBLANK(Table2[[#This Row],[Need_EIS]]), 2,(IF(Table2[[#This Row],[Need_EIS]]="No", 0, (IF(AND(Table2[[#This Row],[Need_EIS]]="Yes", Table2[[#This Row],[EIS_pub_date]]=""),1, 0))))) -> 0 | AP31: =IF(ISBLANK(Table2[[#This Row],[Need_DON]]), 2,(IF(Table2[[#This Row],[Need_DON]]="No", 0, (IF(AND(Table2[[#This Row],[Need_DON]]="Yes", Table2[[#This Row],[DON_pub_date]]=""),1, 0))))) -> 0 | AQ31: =IF(ISBLANK(Table2[[#This Row],[Pending_question]]), 2,(IF(Table2[[#This Row],[Pending_question]]="Yes", 1, 0))) -> 0 | AR31: 44399
A32: 44430 | B32: Closed | C32: {=IF(SUM(Table2[[#This Row],[PQ_indic]],Table2[[#This Row],[RRA_indic]],Table2[[#This Row],[EIS_indic]],Table2[[#This Row],[DON_indic]])=8, "Missing data", (IF(AND(Table2[[#This Row],[Pending_question]]="Yes", OR( Table2[[#This Row],[Need_RRA]]="No", ISBLANK(Table2[[#This Row],[Need_RRA]])), OR(Table2[[#This Row],[Need_EIS]]="No", ISBLANK(Table2[[#This Row],[Need_EIS]])), OR(Table2[[#This Row],[Need_DON]]="No", ISBLANK(Table2[[#This Row],[Need_DON]]) )),"Question, no products",( IF( AND(Table2[[#This Row],[Pending_question]]="Yes", ISBLANK(Table2[[#This Row],[PQ_closure_date]])), (IF(SUM(Table2[[#This Row],[RRA_indic]],Table2[[#This Row],[EIS_indic]],Table2[[#This Row],[DON_indic]])=0, "Open Question, all products done",(I447IF(OR(Table2[[#This Row],[RRA_indic]]=2, Table2[[#This Row],[EIS_indic]]=2, Table2[[#This Row],[DON_indic]]=2),"Question, Products unknown",IF(AND(Table2[[#This Row],[RRA_indic]]=1, Table2[[#This Row],[EIS_indic]]=1, Table2[[#This Row],[DON_indic]]=1), "Open Question, RRA, EIS, DON", IF(AND(Table2[[#This Row],[RRA_indic]]=1, Table2[[#This Row],[EIS_indic]]=1), "Open Question, RRA, EIS",IF(AND(Table2[[#This Row],[RRA_indic]]=1, Table2[[#This Row],[DON_indic]]=1), "Open Question, RRA, DON", IF(AND(Table2[[#This Row],[EIS_indic]]=1, Table2[[#This Row],[DON_indic]]=1), "Open Question, EIS, DON",IF(Table2[[#This Row],[RRA_indic]]=1, "Open Question, RRA", IF(Table2[[#This Row],[EIS_indic]]=1, "Open Question, EIS", "Open Question, DON")))))))))), (IF(SUM(Table2[[#This Row],[RRA_indic]],Table2[[#This Row],[EIS_indic]],Table2[[#This Row],[DON_indic]])=0, "All Products done",(IF(OR(Table2[[#This Row],[RRA_indic]]=2, Table2[[#This Row],[EIS_indic]]=2, Table2[[#This Row],[DON_indic]]=2),"Unknown", IF(AND(Table2[[#This Row],[RRA_indic]]=1, Table2[[#This Row],[EIS_indic]]=1, Table2[[#This Row],[DON_indic]]=1), "Open RRA, EIS, DON", IF(AND(Table2[[#This Row],[RRA_indic]]=1, Table2[[#This Row],[EIS_indic]]=1), "Open RRA, EIS", IF(AND(Table2[[#This Row],[RRA_indic]]=1, Table2[[#This Row],[DON_indic]]=1), "Open RRA, DON", IF(AND(Table2[[#This Row],[EIS_indic]]=1, Table2[[#This Row],[DON_indic]]=1), "Open EIS, DON", IF(Table2[[#This Row],[RRA_indic]]=1, "Open RRA", IF(Table2[[#This Row],[EIS_indic]]=1, "Open EIS", "Open DON")))))))))))))))} -> All Products done | D32: Dunja | E32: Avian influenza A (H5N6) | F32: China | G32: Not applicable | H32: 44430 | M32: No | P32: No | Q32: Not applicable | R32: No RRA | Y32: yes | AB32: 21 Aug 21: draft EIS shared with TT for review with deadline by COB 23 Aug / Concurred by NFP and ready for publishing 25 Aug | AH32: 44433 | AI32: no | AM32: =VLOOKUP(Table2[[#This Row],[country]],Countrycode!A:B,2,FALSE) -> CHN | AN32: =IF(ISBLANK(Table2[[#This Row],[Need_RRA]]), 2,(IF(Table2[[#This Row],[Need_RRA]]="No", 0, (IF(AND(Table2[[#This Row],[Need_RRA]]="Yes", Table2[[#This Row],[RRA_pub_date]]=""),1, 0))))) -> 0 | AO32: =IF(ISBLANK(Table2[[#This Row],[Need_EIS]]), 2,(IF(Table2[[#This Row],[Need_EIS]]="No", 0, (IF(AND(Table2[[#This Row],[Need_EIS]]="Yes", Table2[[#This Row],[EIS_pub_date]]=""),1, 0))))) -> 0 | AP32: =IF(ISBLANK(Table2[[#This Row],[Need_DON]]), 2,(IF(Table2[[#This Row],[Need_DON]]="No", 0, (IF(AND(Table2[[#This Row],[Need_DON]]="Yes", Table2[[#This Row],[DON_pub_date]]=""),1, 0))))) -> 0 | AQ32: =IF(ISBLANK(Table2[[#This Row],[Pending_question]]), 2,(IF(Table2[[#This Row],[Pending_question]]="Yes", 1, 0))) -> 0 | AR32: 44430
A33: 44431 | B33: Closed | C33: {=IF(SUM(Table2[[#This Row],[PQ_indic]],Table2[[#This Row],[RRA_indic]],Table2[[#This Row],[EIS_indic]],Table2[[#This Row],[DON_indic]])=8, "Missing data", (IF(AND(Table2[[#This Row],[Pending_question]]="Yes", OR( Table2[[#This Row],[Need_RRA]]="No", ISBLANK(Table2[[#This Row],[Need_RRA]])), OR(Table2[[#This Row],[Need_EIS]]="No", ISBLANK(Table2[[#This Row],[Need_EIS]])), OR(Table2[[#This Row],[Need_DON]]="No", ISBLANK(Table2[[#This Row],[Need_DON]]) )),"Question, no products",( IF( AND(Table2[[#This Row],[Pending_question]]="Yes", ISBLANK(Table2[[#This Row],[PQ_closure_date]])), (IF(SUM(Table2[[#This Row],[RRA_indic]],Table2[[#This Row],[EIS_indic]],Table2[[#This Row],[DON_indic]])=0, "Open Question, all products done",(I447IF(OR(Table2[[#This Row],[RRA_indic]]=2, Table2[[#This Row],[EIS_indic]]=2, Table2[[#This Row],[DON_indic]]=2),"Question, Products unknown",IF(AND(Table2[[#This Row],[RRA_indic]]=1, Table2[[#This Row],[EIS_indic]]=1, Table2[[#This Row],[DON_indic]]=1), "Open Question, RRA, EIS, DON", IF(AND(Table2[[#This Row],[RRA_indic]]=1, Table2[[#This Row],[EIS_indic]]=1), "Open Question, RRA, EIS",IF(AND(Table2[[#This Row],[RRA_indic]]=1, Table2[[#This Row],[DON_indic]]=1), "Open Question, RRA, DON", IF(AND(Table2[[#This Row],[EIS_indic]]=1, Table2[[#This Row],[DON_indic]]=1), "Open Question, EIS, DON",IF(Table2[[#This Row],[RRA_indic]]=1, "Open Question, RRA", IF(Table2[[#This Row],[EIS_indic]]=1, "Open Question, EIS", "Open Question, DON")))))))))), (IF(SUM(Table2[[#This Row],[RRA_indic]],Table2[[#This Row],[EIS_indic]],Table2[[#This Row],[DON_indic]])=0, "All Products done",(IF(OR(Table2[[#This Row],[RRA_indic]]=2, Table2[[#This Row],[EIS_indic]]=2, Table2[[#This Row],[DON_indic]]=2),"Unknown", IF(AND(Table2[[#This Row],[RRA_indic]]=1, Table2[[#This Row],[EIS_indic]]=1, Table2[[#This Row],[DON_indic]]=1), "Open RRA, EIS, DON", IF(AND(Table2[[#This Row],[RRA_indic]]=1, Table2[[#This Row],[EIS_indic]]=1), "Open RRA, EIS", IF(AND(Table2[[#This Row],[RRA_indic]]=1, Table2[[#This Row],[DON_indic]]=1), "Open RRA, DON", IF(AND(Table2[[#This Row],[EIS_indic]]=1, Table2[[#This Row],[DON_indic]]=1), "Open EIS, DON", IF(Table2[[#This Row],[RRA_indic]]=1, "Open RRA", IF(Table2[[#This Row],[EIS_indic]]=1, "Open EIS", "Open DON")))))))))))))))} -> All Products done | D33: Dunja/Ryo | E33: Avian influenza A (H5N6) | F33: China | G33: Not applicable | H33: 44431 | M33: No | P33: No | Q33: Not applicable | R33: No RRA | Y33: yes | AB33: 23 August: EIS and an official IHR notification received on late nigh . /24 August EIS shared with TT at HQ, reqested feedback by COB on 24 August.Sent to WPRO/ 25 August Kat additional question sent by email to WPRO /27 August, WPRO contacted follow up on the status of the EIS/ 30 August published? | AH33: 44438 | AI33: no | AL33: EIS published but no one received alert email, Ryo contacted Johannes | AM33: =VLOOKUP(Table2[[#This Row],[country]],Countrycode!A:B,2,FALSE) -> CHN | AN33: =IF(ISBLANK(Table2[[#This Row],[Need_RRA]]), 2,(IF(Table2[[#This Row],[Need_RRA]]="No", 0, (IF(AND(Table2[[#This Row],[Need_RRA]]="Yes", Table2[[#This Row],[RRA_pub_date]]=""),1, 0))))) -> 0 | AO33: =IF(ISBLANK(Table2[[#This Row],[Need_EIS]]), 2,(IF(Table2[[#This Row],[Need_EIS]]="No", 0, (IF(AND(Table2[[#This Row],[Need_EIS]]="Yes", Table2[[#This Row],[EIS_pub_date]]=""),1, 0))))) -> 0 | AP33: =IF(ISBLANK(Table2[[#This Row],[Need_DON]]), 2,(IF(Table2[[#This Row],[Need_DON]]="No", 0, (IF(AND(Table2[[#This Row],[Need_DON]]="Yes", Table2[[#This Row],[DON_pub_date]]=""),1, 0))))) -> 0 | AQ33: =IF(ISBLANK(Table2[[#This Row],[Pending_question]]), 2,(IF(Table2[[#This Row],[Pending_question]]="Yes", 1, 0))) -> 0 | AR33: 44432
A34: 44435 | B34: Closed | C34: {=IF(SUM(Table2[[#This Row],[PQ_indic]],Table2[[#This Row],[RRA_indic]],Table2[[#This Row],[EIS_indic]],Table2[[#This Row],[DON_indic]])=8, "Missing data", (IF(AND(Table2[[#This Row],[Pending_question]]="Yes", OR( Table2[[#This Row],[Need_RRA]]="No", ISBLANK(Table2[[#This Row],[Need_RRA]])), OR(Table2[[#This Row],[Need_EIS]]="No", ISBLANK(Table2[[#This Row],[Need_EIS]])), OR(Table2[[#This Row],[Need_DON]]="No", ISBLANK(Table2[[#This Row],[Need_DON]]) )),"Question, no products",( IF( AND(Table2[[#This Row],[Pending_question]]="Yes", ISBLANK(Table2[[#This Row],[PQ_closure_date]])), (IF(SUM(Table2[[#This Row],[RRA_indic]],Table2[[#This Row],[EIS_indic]],Table2[[#This Row],[DON_indic]])=0, "Open Question, all products done",(I447IF(OR(Table2[[#This Row],[RRA_indic]]=2, Table2[[#This Row],[EIS_indic]]=2, Table2[[#This Row],[DON_indic]]=2),"Question, Products unknown",IF(AND(Table2[[#This Row],[RRA_indic]]=1, Table2[[#This Row],[EIS_indic]]=1, Table2[[#This Row],[DON_indic]]=1), "Open Question, RRA, EIS, DON", IF(AND(Table2[[#This Row],[RRA_indic]]=1, Table2[[#This Row],[EIS_indic]]=1), "Open Question, RRA, EIS",IF(AND(Table2[[#This Row],[RRA_indic]]=1, Table2[[#This Row],[DON_indic]]=1), "Open Question, RRA, DON", IF(AND(Table2[[#This Row],[EIS_indic]]=1, Table2[[#This Row],[DON_indic]]=1), "Open Question, EIS, DON",IF(Table2[[#This Row],[RRA_indic]]=1, "Open Question, RRA", IF(Table2[[#This Row],[EIS_indic]]=1, "Open Question, EIS", "Open Question, DON")))))))))), (IF(SUM(Table2[[#This Row],[RRA_indic]],Table2[[#This Row],[EIS_indic]],Table2[[#This Row],[DON_indic]])=0, "All Products done",(IF(OR(Table2[[#This Row],[RRA_indic]]=2, Table2[[#This Row],[EIS_indic]]=2, Table2[[#This Row],[DON_indic]]=2),"Unknown", IF(AND(Table2[[#This Row],[RRA_indic]]=1, Table2[[#This Row],[EIS_indic]]=1, Table2[[#This Row],[DON_indic]]=1), "Open RRA, EIS, DON", IF(AND(Table2[[#This Row],[RRA_indic]]=1, Table2[[#This Row],[EIS_indic]]=1), "Open RRA, EIS", IF(AND(Table2[[#This Row],[RRA_indic]]=1, Table2[[#This Row],[DON_indic]]=1), "Open RRA, DON", IF(AND(Table2[[#This Row],[EIS_indic]]=1, Table2[[#This Row],[DON_indic]]=1), "Open EIS, DON", IF(Table2[[#This Row],[RRA_indic]]=1, "Open RRA", IF(Table2[[#This Row],[EIS_indic]]=1, "Open EIS", "Open DON")))))))))))))))} -> All Products done | D34: Lidia | E34: Hepatitis E | F34: South Sudan | G34: Not applicable | H34: 44435 | J34: 43245 | K34: 2018-E000214 | M34: No | P34: Yes | R34: RRA proposed on 24 August 21. Conversation held with Valerie on 26 August. Initial RRA draft shared by AFRO on 30 Aug 21. Feedback provided by HQ on 1 September. Comments addressed by AFRO on 3 September. Pending WCO comments. Reminder sent on 4 and 6 September. WCo providedcomments on 6 September. Consolidated RRA draft sent across the 3l for further agrrement and finalisation. 8 september, RRA distributed | S34: 44438 | U34: 44447 | Y34: yes | AB34: 7 Sept: EIS box checked in the RRA draft. Pending furter agreement by AFRO and WCO. Email sent to AFRRO. No reply. 15 September : follow up email sent.16 September: EIS initial draft shared by AFRO. Under review at HQ.17 september: Sent back to AFRO with additional comments. / 18 Sep: comments provided by WCO South Sudan.20 September:Consolidated draft sent back to AFRO for NFP accuracy check.26 September: Reminder sent to AFRO and WCO. WCO has follwed up with the NFP. 29 September: WCO shared the EIS draft that was concurred bythe NFP. Shared for final clearance before posting.29 September: EIS concurrence received 30 September: EIS posted | AH34: 44468 | AI34: no | AM34: =VLOOKUP(Table2[[#This Row],[country]],Countrycode!A:B,2,FALSE) -> SSD | AN34: =IF(ISBLANK(Table2[[#This Row],[Need_RRA]]), 2,(IF(Table2[[#This Row],[Need_RRA]]="No", 0, (IF(AND(Table2[[#This Row],[Need_RRA]]="Yes", Table2[[#This Row],[RRA_pub_date]]=""),1, 0))))) -> 0 | AO34: =IF(ISBLANK(Table2[[#This Row],[Need_EIS]]), 2,(IF(Table2[[#This Row],[Need_EIS]]="No", 0, (IF(AND(Table2[[#This Row],[Need_EIS]]="Yes", Table2[[#This Row],[EIS_pub_date]]=""),1, 0))))) -> 0 | AP34: =IF(ISBLANK(Table2[[#This Row],[Need_DON]]), 2,(IF(Table2[[#This Row],[Need_DON]]="No", 0, (IF(AND(Table2[[#This Row],[Need_DON]]="Yes", Table2[[#This Row],[DON_pub_date]]=""),1, 0))))) -> 0 | AQ34: =IF(ISBLANK(Table2[[#This Row],[Pending_question]]), 2,(IF(Table2[[#This Row],[Pending_question]]="Yes", 1, 0))) -> 0 | AR34: 44310
A35: 44439 | B35: Closed | C35: {=IF(SUM(Table2[[#This Row],[PQ_indic]],Table2[[#This Row],[RRA_indic]],Table2[[#This Row],[EIS_indic]],Table2[[#This Row],[DON_indic]])=8, "Missing data", (IF(AND(Table2[[#This Row],[Pending_question]]="Yes", OR( Table2[[#This Row],[Need_RRA]]="No", ISBLANK(Table2[[#This Row],[Need_RRA]])), OR(Table2[[#This Row],[Need_EIS]]="No", ISBLANK(Table2[[#This Row],[Need_EIS]])), OR(Table2[[#This Row],[Need_DON]]="No", ISBLANK(Table2[[#This Row],[Need_DON]]) )),"Question, no products",( IF( AND(Table2[[#This Row],[Pending_question]]="Yes", ISBLANK(Table2[[#This Row],[PQ_closure_date]])), (IF(SUM(Table2[[#This Row],[RRA_indic]],Table2[[#This Row],[EIS_indic]],Table2[[#This Row],[DON_indic]])=0, "Open Question, all products done",(I447IF(OR(Table2[[#This Row],[RRA_indic]]=2, Table2[[#This Row],[EIS_indic]]=2, Table2[[#This Row],[DON_indic]]=2),"Question, Products unknown",IF(AND(Table2[[#This Row],[RRA_indic]]=1, Table2[[#This Row],[EIS_indic]]=1, Table2[[#This Row],[DON_indic]]=1), "Open Question, RRA, EIS, DON", IF(AND(Table2[[#This Row],[RRA_indic]]=1, Table2[[#This Row],[EIS_indic]]=1), "Open Question, RRA, EIS",IF(AND(Table2[[#This Row],[RRA_indic]]=1, Table2[[#This Row],[DON_indic]]=1), "Open Question, RRA, DON", IF(AND(Table2[[#This Row],[EIS_indic]]=1, Table2[[#This Row],[DON_indic]]=1), "Open Question, EIS, DON",IF(Table2[[#This Row],[RRA_indic]]=1, "Open Question, RRA", IF(Table2[[#This Row],[EIS_indic]]=1, "Open Question, EIS", "Open Question, DON")))))))))), (IF(SUM(Table2[[#This Row],[RRA_indic]],Table2[[#This Row],[EIS_indic]],Table2[[#This Row],[DON_indic]])=0, "All Products done",(IF(OR(Table2[[#This Row],[RRA_indic]]=2, Table2[[#This Row],[EIS_indic]]=2, Table2[[#This Row],[DON_indic]]=2),"Unknown", IF(AND(Table2[[#This Row],[RRA_indic]]=1, Table2[[#This Row],[EIS_indic]]=1, Table2[[#This Row],[DON_indic]]=1), "Open RRA, EIS, DON", IF(AND(Table2[[#This Row],[RRA_indic]]=1, Table2[[#This Row],[EIS_indic]]=1), "Open RRA, EIS", IF(AND(Table2[[#This Row],[RRA_indic]]=1, Table2[[#This Row],[DON_indic]]=1), "Open RRA, DON", IF(AND(Table2[[#This Row],[EIS_indic]]=1, Table2[[#This Row],[DON_indic]]=1), "Open EIS, DON", IF(Table2[[#This Row],[RRA_indic]]=1, "Open RRA", IF(Table2[[#This Row],[EIS_indic]]=1, "Open EIS", "Open DON")))))))))))))))} -> All Products done | D35: Dunja | E35: Avian influenza A (H9N2) | F35: China | G35: Not applicable | H35: 44439 | M35: No | P35: No | Q35: Not applicable | R35: No RRA | Y35: yes | AB35: 31 August received NFP notification and EIS draft/ 31 August back to WPRO / 2 Aug received and published | AH35: 44410 | AI35: no | AM35: =VLOOKUP(Table2[[#This Row],[country]],Countrycode!A:B,2,FALSE) -> CHN | AN35: =IF(ISBLANK(Table2[[#This Row],[Need_RRA]]), 2,(IF(Table2[[#This Row],[Need_RRA]]="No", 0, (IF(AND(Table2[[#This Row],[Need_RRA]]="Yes", Table2[[#This Row],[RRA_pub_date]]=""),1, 0))))) -> 0 | AO35: =IF(ISBLANK(Table2[[#This Row],[Need_EIS]]), 2,(IF(Table2[[#This Row],[Need_EIS]]="No", 0, (IF(AND(Table2[[#This Row],[Need_EIS]]="Yes", Table2[[#This Row],[EIS_pub_date]]=""),1, 0))))) -> 0 | AP35: =IF(ISBLANK(Table2[[#This Row],[Need_DON]]), 2,(IF(Table2[[#This Row],[Need_DON]]="No", 0, (IF(AND(Table2[[#This Row],[Need_DON]]="Yes", Table2[[#This Row],[DON_pub_date]]=""),1, 0))))) -> 0 | AQ35: =IF(ISBLANK(Table2[[#This Row],[Pending_question]]), 2,(IF(Table2[[#This Row],[Pending_question]]="Yes", 1, 0))) -> 0 | AR35: 44439
A36: 44441 | B36: Closed | C36: {=IF(SUM(Table2[[#This Row],[PQ_indic]],Table2[[#This Row],[RRA_indic]],Table2[[#This Row],[EIS_indic]],Table2[[#This Row],[DON_indic]])=8, "Missing data", (IF(AND(Table2[[#This Row],[Pending_question]]="Yes", OR( Table2[[#This Row],[Need_RRA]]="No", ISBLANK(Table2[[#This Row],[Need_RRA]])), OR(Table2[[#This Row],[Need_EIS]]="No", ISBLANK(Table2[[#This Row],[Need_EIS]])), OR(Table2[[#This Row],[Need_DON]]="No", ISBLANK(Table2[[#This Row],[Need_DON]]) )),"Question, no products",( IF( AND(Table2[[#This Row],[Pending_question]]="Yes", ISBLANK(Table2[[#This Row],[PQ_closure_date]])), (IF(SUM(Table2[[#This Row],[RRA_indic]],Table2[[#This Row],[EIS_indic]],Table2[[#This Row],[DON_indic]])=0, "Open Question, all products done",(I447IF(OR(Table2[[#This Row],[RRA_indic]]=2, Table2[[#This Row],[EIS_indic]]=2, Table2[[#This Row],[DON_indic]]=2),"Question, Products unknown",IF(AND(Table2[[#This Row],[RRA_indic]]=1, Table2[[#This Row],[EIS_indic]]=1, Table2[[#This Row],[DON_indic]]=1), "Open Question, RRA, EIS, DON", IF(AND(Table2[[#This Row],[RRA_indic]]=1, Table2[[#This Row],[EIS_indic]]=1), "Open Question, RRA, EIS",IF(AND(Table2[[#This Row],[RRA_indic]]=1, Table2[[#This Row],[DON_indic]]=1), "Open Question, RRA, DON", IF(AND(Table2[[#This Row],[EIS_indic]]=1, Table2[[#This Row],[DON_indic]]=1), "Open Question, EIS, DON",IF(Table2[[#This Row],[RRA_indic]]=1, "Open Question, RRA", IF(Table2[[#This Row],[EIS_indic]]=1, "Open Question, EIS", "Open Question, DON")))))))))), (IF(SUM(Table2[[#This Row],[RRA_indic]],Table2[[#This Row],[EIS_indic]],Table2[[#This Row],[DON_indic]])=0, "All Products done",(IF(OR(Table2[[#This Row],[RRA_indic]]=2, Table2[[#This Row],[EIS_indic]]=2, Table2[[#This Row],[DON_indic]]=2),"Unknown", IF(AND(Table2[[#This Row],[RRA_indic]]=1, Table2[[#This Row],[EIS_indic]]=1, Table2[[#This Row],[DON_indic]]=1), "Open RRA, EIS, DON", IF(AND(Table2[[#This Row],[RRA_indic]]=1, Table2[[#This Row],[EIS_indic]]=1), "Open RRA, EIS", IF(AND(Table2[[#This Row],[RRA_indic]]=1, Table2[[#This Row],[DON_indic]]=1), "Open RRA, DON", IF(AND(Table2[[#This Row],[EIS_indic]]=1, Table2[[#This Row],[DON_indic]]=1), "Open EIS, DON", IF(Table2[[#This Row],[RRA_indic]]=1, "Open RRA", IF(Table2[[#This Row],[EIS_indic]]=1, "Open EIS", "Open DON")))))))))))))))} -> All Products done | D36: Dunja/Elvis | E36: Plague | F36: Madagascar | G36: Not applicable | H36: 44441 | J36: 44442 | K36: 2021-E000322 | M36: No | P36: Yes | R36: 2 Sept: first draft of the RRA received by AFRO / 3 Sept: RRA updated by CO , circulated among TT and HQ/ 4 Sept: RRA finalised and disseminated | S36: 44442 | U36: 44443 | Y36: yes | AB36: 3 Sept: need t o start the process of the EIS/5 Sep AFRO confirmed , they will initiate the first draft/ 8 September received EIS draft from AFRO./ 9 September: comments from TT and HQ received / 9 Septmber: EIS sent back to AFRO/ 14 Sep reminder sent to AFRO and WCO/ 17 Sep reminder sent to WCO / 18 Sep: WCO and AFRO shared the EIS updated by NFP. Shared with Dunja, Esther and Emilie for clearance. EIS is currently in French only. /20 september: EIS cleared by Emilie with additional questions to send back to AFRO for clarifications and answers./ 20 september: AFRO answered the questions / 21 September: final clearance done by Emilie. Posted. | AH36: 44460 | AI36: yes | AK36: 44453 | AM36: =VLOOKUP(Table2[[#This Row],[country]],Countrycode!A:B,2,FALSE) -> MDG | AN36: =IF(ISBLANK(Table2[[#This Row],[Need_RRA]]), 2,(IF(Table2[[#This Row],[Need_RRA]]="No", 0, (IF(AND(Table2[[#This Row],[Need_RRA]]="Yes", Table2[[#This Row],[RRA_pub_date]]=""),1, 0))))) -> 0 | AO36: =IF(ISBLANK(Table2[[#This Row],[Need_EIS]]), 2,(IF(Table2[[#This Row],[Need_EIS]]="No", 0, (IF(AND(Table2[[#This Row],[Need_EIS]]="Yes", Table2[[#This Row],[EIS_pub_date]]=""),1, 0))))) -> 0 | AP36: =IF(ISBLANK(Table2[[#This Row],[Need_DON]]), 2,(IF(Table2[[#This Row],[Need_DON]]="No", 0, (IF(AND(Table2[[#This Row],[Need_DON]]="Yes", Table2[[#This Row],[DON_pub_date]]=""),1, 0))))) -> 0 | AQ36: =IF(ISBLANK(Table2[[#This Row],[Pending_question]]), 2,(IF(Table2[[#This Row],[Pending_question]]="Yes", 1, 0))) -> 0 | AR36: 44442
A37: 44444 | B37: Closed | C37: {=IF(SUM(Table2[[#This Row],[PQ_indic]],Table2[[#This Row],[RRA_indic]],Table2[[#This Row],[EIS_indic]],Table2[[#This Row],[DON_indic]])=8, "Missing data", (IF(AND(Table2[[#This Row],[Pending_question]]="Yes", OR( Table2[[#This Row],[Need_RRA]]="No", ISBLANK(Table2[[#This Row],[Need_RRA]])), OR(Table2[[#This Row],[Need_EIS]]="No", ISBLANK(Table2[[#This Row],[Need_EIS]])), OR(Table2[[#This Row],[Need_DON]]="No", ISBLANK(Table2[[#This Row],[Need_DON]]) )),"Question, no products",( IF( AND(Table2[[#This Row],[Pending_question]]="Yes", ISBLANK(Table2[[#This Row],[PQ_closure_date]])), (IF(SUM(Table2[[#This Row],[RRA_indic]],Table2[[#This Row],[EIS_indic]],Table2[[#This Row],[DON_indic]])=0, "Open Question, all products done",(I447IF(OR(Table2[[#This Row],[RRA_indic]]=2, Table2[[#This Row],[EIS_indic]]=2, Table2[[#This Row],[DON_indic]]=2),"Question, Products unknown",IF(AND(Table2[[#This Row],[RRA_indic]]=1, Table2[[#This Row],[EIS_indic]]=1, Table2[[#This Row],[DON_indic]]=1), "Open Question, RRA, EIS, DON", IF(AND(Table2[[#This Row],[RRA_indic]]=1, Table2[[#This Row],[EIS_indic]]=1), "Open Question, RRA, EIS",IF(AND(Table2[[#This Row],[RRA_indic]]=1, Table2[[#This Row],[DON_indic]]=1), "Open Question, RRA, DON", IF(AND(Table2[[#This Row],[EIS_indic]]=1, Table2[[#This Row],[DON_indic]]=1), "Open Question, EIS, DON",IF(Table2[[#This Row],[RRA_indic]]=1, "Open Question, RRA", IF(Table2[[#This Row],[EIS_indic]]=1, "Open Question, EIS", "Open Question, DON")))))))))), (IF(SUM(Table2[[#This Row],[RRA_indic]],Table2[[#This Row],[EIS_indic]],Table2[[#This Row],[DON_indic]])=0, "All Products done",(IF(OR(Table2[[#This Row],[RRA_indic]]=2, Table2[[#This Row],[EIS_indic]]=2, Table2[[#This Row],[DON_indic]]=2),"Unknown", IF(AND(Table2[[#This Row],[RRA_indic]]=1, Table2[[#This Row],[EIS_indic]]=1, Table2[[#This Row],[DON_indic]]=1), "Open RRA, EIS, DON", IF(AND(Table2[[#This Row],[RRA_indic]]=1, Table2[[#This Row],[EIS_indic]]=1), "Open RRA, EIS", IF(AND(Table2[[#This Row],[RRA_indic]]=1, Table2[[#This Row],[DON_indic]]=1), "Open RRA, DON", IF(AND(Table2[[#This Row],[EIS_indic]]=1, Table2[[#This Row],[DON_indic]]=1), "Open EIS, DON", IF(Table2[[#This Row],[RRA_indic]]=1, "Open RRA", IF(Table2[[#This Row],[EIS_indic]]=1, "Open EIS", "Open DON")))))))))))))))} -> All Products done | D37: Dunja/Anastasia | E37: Nipah | F37: India | G37: Not applicable | H37: 44444 | J37: 44445 | K37: 2021-E000323 | M37: No | P37: Yes | R37: 06 Sept: RRA is drafted by SEARO colleagues./ 08 September: RRA draft shared with HQ and sent back to SEARO with commnts. Deadline for finalisation on 10 Sept.10 September: Inputs received from SEARO and WCO. Consolidated draft with the table for the agreement annd finalisation, instead of 3LTC sent back to SERAO and WCO.12 September: Further inputs received bt SEARO. Pendinf WCO feedback./ 13 Sep SEARO propose moderate risk at Sub National level, HQ agree /14 Sep WCO agree on all proposed risk levels , RRA sent to Esther for review before distribution./ 15 September waiting Esther approval fro RRA distribution /15 September published | S37: 44453 | U37: 44454 | Y37: yes | AB37: 06 Sept: EIS drafted by PHI HQ and shared with TT. / 07 Sept: EIS shared from HQ to SEARO/10 September: Reminder sent to SEARO regarding the EIS status/13 WCO confirmed EIS with NFP/ 15 September Reminder sent to WCO, at morning by Dunja and afternnon by EMILIE.20 September / 21 Sep: draft EIS received with edits from NCDC. Sent for final clearance to Esther. Published on 21 Sep. | AH37: 44460 | AI37: yes | AK37: 44461 | AL37: 1 confirmed case, 2 HCW symptomatic, As of now 188 people are in quarantine including 136 Health Workers (from both the private hospital and Medical College) and 5 close family contacts. | AM37: =VLOOKUP(Table2[[#This Row],[country]],Countrycode!A:B,2,FALSE) -> IND | AN37: =IF(ISBLANK(Table2[[#This Row],[Need_RRA]]), 2,(IF(Table2[[#This Row],[Need_RRA]]="No", 0, (IF(AND(Table2[[#This Row],[Need_RRA]]="Yes", Table2[[#This Row],[RRA_pub_date]]=""),1, 0))))) -> 0 | AO37: =IF(ISBLANK(Table2[[#This Row],[Need_EIS]]), 2,(IF(Table2[[#This Row],[Need_EIS]]="No", 0, (IF(AND(Table2[[#This Row],[Need_EIS]]="Yes", Table2[[#This Row],[EIS_pub_date]]=""),1, 0))))) -> 0 | AP37: =IF(ISBLANK(Table2[[#This Row],[Need_DON]]), 2,(IF(Table2[[#This Row],[Need_DON]]="No", 0, (IF(AND(Table2[[#This Row],[Need_DON]]="Yes", Table2[[#This Row],[DON_pub_date]]=""),1, 0))))) -> 0 | AQ37: =IF(ISBLANK(Table2[[#This Row],[Pending_question]]), 2,(IF(Table2[[#This Row],[Pending_question]]="Yes", 1, 0))) -> 0 | AR37: 44444
A38: 44446 | B38: Closed | C38: {=IF(SUM(Table2[[#This Row],[PQ_indic]],Table2[[#This Row],[RRA_indic]],Table2[[#This Row],[EIS_indic]],Table2[[#This Row],[DON_indic]])=8, "Missing data", (IF(AND(Table2[[#This Row],[Pending_question]]="Yes", OR( Table2[[#This Row],[Need_RRA]]="No", ISBLANK(Table2[[#This Row],[Need_RRA]])), OR(Table2[[#This Row],[Need_EIS]]="No", ISBLANK(Table2[[#This Row],[Need_EIS]])), OR(Table2[[#This Row],[Need_DON]]="No", ISBLANK(Table2[[#This Row],[Need_DON]]) )),"Question, no products",( IF( AND(Table2[[#This Row],[Pending_question]]="Yes", ISBLANK(Table2[[#This Row],[PQ_closure_date]])), (IF(SUM(Table2[[#This Row],[RRA_indic]],Table2[[#This Row],[EIS_indic]],Table2[[#This Row],[DON_indic]])=0, "Open Question, all products done",(I447IF(OR(Table2[[#This Row],[RRA_indic]]=2, Table2[[#This Row],[EIS_indic]]=2, Table2[[#This Row],[DON_indic]]=2),"Question, Products unknown",IF(AND(Table2[[#This Row],[RRA_indic]]=1, Table2[[#This Row],[EIS_indic]]=1, Table2[[#This Row],[DON_indic]]=1), "Open Question, RRA, EIS, DON", IF(AND(Table2[[#This Row],[RRA_indic]]=1, Table2[[#This Row],[EIS_indic]]=1), "Open Question, RRA, EIS",IF(AND(Table2[[#This Row],[RRA_indic]]=1, Table2[[#This Row],[DON_indic]]=1), "Open Question, RRA, DON", IF(AND(Table2[[#This Row],[EIS_indic]]=1, Table2[[#This Row],[DON_indic]]=1), "Open Question, EIS, DON",IF(Table2[[#This Row],[RRA_indic]]=1, "Open Question, RRA", IF(Table2[[#This Row],[EIS_indic]]=1, "Open Question, EIS", "Open Question, DON")))))))))), (IF(SUM(Table2[[#This Row],[RRA_indic]],Table2[[#This Row],[EIS_indic]],Table2[[#This Row],[DON_indic]])=0, "All Products done",(IF(OR(Table2[[#This Row],[RRA_indic]]=2, Table2[[#This Row],[EIS_indic]]=2, Table2[[#This Row],[DON_indic]]=2),"Unknown", IF(AND(Table2[[#This Row],[RRA_indic]]=1, Table2[[#This Row],[EIS_indic]]=1, Table2[[#This Row],[DON_indic]]=1), "Open RRA, EIS, DON", IF(AND(Table2[[#This Row],[RRA_indic]]=1, Table2[[#This Row],[EIS_indic]]=1), "Open RRA, EIS", IF(AND(Table2[[#This Row],[RRA_indic]]=1, Table2[[#This Row],[DON_indic]]=1), "Open RRA, DON", IF(AND(Table2[[#This Row],[EIS_indic]]=1, Table2[[#This Row],[DON_indic]]=1), "Open EIS, DON", IF(Table2[[#This Row],[RRA_indic]]=1, "Open RRA", IF(Table2[[#This Row],[EIS_indic]]=1, "Open EIS", "Open DON")))))))))))))))} -> All Products done | D38: Lidia/Ryo/Elvis | E38: Undiagnosed disease - suspected Meningitis | F38: Democratic Republic of the Congo | G38: Not applicable | K38: 2021-E000303 | M38: No | P38: Yes | R38: 10 August, agreed among all 3 levels. Deadline to WCO to share the initial draft with AFRO and HQ on 12 August by 1PM. Reminder sent on 13 , 16 and 17 August. Initial draft RRA finally recieved from the WCO on 17 August and shared within HQ for review the same day with deadline COB on 17 August. No feedback received as per 18 August. Feedback received on 19 August. Cosolidated draft shared back with AFRO and WCO on 19 August. AFRO sent back to WCO on 20 August to address the pending comments. Final feedback received from WCO on 25 August./27 August: RRA finalized and distributed.9 September: RRA v.2 shared by AFRO at the evening. To be finalised by 13 September, prior to the grading call scheduled the same day. 13 September: finalised and ditributed. | S38: 44446 | U38: 44452 | Y38: yes | AB38: 19 August: EIS has been checked in the box of the RRA, pending agreement from the 3LTC./27 August: EIS agreed / 5 September: EIS received from AFRO and shared with HQ with deadline by noon on 6 September (on Monday, 5 September, lab results received from IPP - N. meningitidis W). 8 September, eis draft shared back with AFRO. 9 September, AFRO shared with WCO to address the comments. 10 September :clean version shared back to AFRO for furthre NFP concurrance. 12 September- EIS posted | AH38: 44451 | AI38: yes | AK38: 44454 | AM38: =VLOOKUP(Table2[[#This Row],[country]],Countrycode!A:B,2,FALSE) -> COD | AN38: =IF(ISBLANK(Table2[[#This Row],[Need_RRA]]), 2,(IF(Table2[[#This Row],[Need_RRA]]="No", 0, (IF(AND(Table2[[#This Row],[Need_RRA]]="Yes", Table2[[#This Row],[RRA_pub_date]]=""),1, 0))))) -> 0 | AO38: =IF(ISBLANK(Table2[[#This Row],[Need_EIS]]), 2,(IF(Table2[[#This Row],[Need_EIS]]="No", 0, (IF(AND(Table2[[#This Row],[Need_EIS]]="Yes", Table2[[#This Row],[EIS_pub_date]]=""),1, 0))))) -> 0 | AP38: =IF(ISBLANK(Table2[[#This Row],[Need_DON]]), 2,(IF(Table2[[#This Row],[Need_DON]]="No", 0, (IF(AND(Table2[[#This Row],[Need_DON]]="Yes", Table2[[#This Row],[DON_pub_date]]=""),1, 0))))) -> 0 | AQ38: =IF(ISBLANK(Table2[[#This Row],[Pending_question]]), 2,(IF(Table2[[#This Row],[Pending_question]]="Yes", 1, 0))) -> 0 | AR38: 44407
A39: 44447 | B39: Closed | C39: {=IF(SUM(Table2[[#This Row],[PQ_indic]],Table2[[#This Row],[RRA_indic]],Table2[[#This Row],[EIS_indic]],Table2[[#This Row],[DON_indic]])=8, "Missing data", (IF(AND(Table2[[#This Row],[Pending_question]]="Yes", OR( Table2[[#This Row],[Need_RRA]]="No", ISBLANK(Table2[[#This Row],[Need_RRA]])), OR(Table2[[#This Row],[Need_EIS]]="No", ISBLANK(Table2[[#This Row],[Need_EIS]])), OR(Table2[[#This Row],[Need_DON]]="No", ISBLANK(Table2[[#This Row],[Need_DON]]) )),"Question, no products",( IF( AND(Table2[[#This Row],[Pending_question]]="Yes", ISBLANK(Table2[[#This Row],[PQ_closure_date]])), (IF(SUM(Table2[[#This Row],[RRA_indic]],Table2[[#This Row],[EIS_indic]],Table2[[#This Row],[DON_indic]])=0, "Open Question, all products done",(I447IF(OR(Table2[[#This Row],[RRA_indic]]=2, Table2[[#This Row],[EIS_indic]]=2, Table2[[#This Row],[DON_indic]]=2),"Question, Products unknown",IF(AND(Table2[[#This Row],[RRA_indic]]=1, Table2[[#This Row],[EIS_indic]]=1, Table2[[#This Row],[DON_indic]]=1), "Open Question, RRA, EIS, DON", IF(AND(Table2[[#This Row],[RRA_indic]]=1, Table2[[#This Row],[EIS_indic]]=1), "Open Question, RRA, EIS",IF(AND(Table2[[#This Row],[RRA_indic]]=1, Table2[[#This Row],[DON_indic]]=1), "Open Question, RRA, DON", IF(AND(Table2[[#This Row],[EIS_indic]]=1, Table2[[#This Row],[DON_indic]]=1), "Open Question, EIS, DON",IF(Table2[[#This Row],[RRA_indic]]=1, "Open Question, RRA", IF(Table2[[#This Row],[EIS_indic]]=1, "Open Question, EIS", "Open Question, DON")))))))))), (IF(SUM(Table2[[#This Row],[RRA_indic]],Table2[[#This Row],[EIS_indic]],Table2[[#This Row],[DON_indic]])=0, "All Products done",(IF(OR(Table2[[#This Row],[RRA_indic]]=2, Table2[[#This Row],[EIS_indic]]=2, Table2[[#This Row],[DON_indic]]=2),"Unknown", IF(AND(Table2[[#This Row],[RRA_indic]]=1, Table2[[#This Row],[EIS_indic]]=1, Table2[[#This Row],[DON_indic]]=1), "Open RRA, EIS, DON", IF(AND(Table2[[#This Row],[RRA_indic]]=1, Table2[[#This Row],[EIS_indic]]=1), "Open RRA, EIS", IF(AND(Table2[[#This Row],[RRA_indic]]=1, Table2[[#This Row],[DON_indic]]=1), "Open RRA, DON", IF(AND(Table2[[#This Row],[EIS_indic]]=1, Table2[[#This Row],[DON_indic]]=1), "Open EIS, DON", IF(Table2[[#This Row],[RRA_indic]]=1, "Open RRA", IF(Table2[[#This Row],[EIS_indic]]=1, "Open EIS", "Open DON")))))))))))))))} -> All Products done | D39: Elvis/Dunja | E39: Avian influenza A (H5N6) | F39: China | G39: Not applicable | H39: 44447 | M39: No | P39: No | Q39: Not applicable | Y39: yes | AB39: 8 September: Recieved notification and draft EIS from WPRO: Shared EIS with TT for inputs. 9 September> sent back for NFP concurrence .13 September. received from the NFP for posting | AH39: 44452 | AI39: no | AM39: =VLOOKUP(Table2[[#This Row],[country]],Countrycode!A:B,2,FALSE) -> CHN | AN39: =IF(ISBLANK(Table2[[#This Row],[Need_RRA]]), 2,(IF(Table2[[#This Row],[Need_RRA]]="No", 0, (IF(AND(Table2[[#This Row],[Need_RRA]]="Yes", Table2[[#This Row],[RRA_pub_date]]=""),1, 0))))) -> 0 | AO39: =IF(ISBLANK(Table2[[#This Row],[Need_EIS]]), 2,(IF(Table2[[#This Row],[Need_EIS]]="No", 0, (IF(AND(Table2[[#This Row],[Need_EIS]]="Yes", Table2[[#This Row],[EIS_pub_date]]=""),1, 0))))) -> 0 | AP39: =IF(ISBLANK(Table2[[#This Row],[Need_DON]]), 2,(IF(Table2[[#This Row],[Need_DON]]="No", 0, (IF(AND(Table2[[#This Row],[Need_DON]]="Yes", Table2[[#This Row],[DON_pub_date]]=""),1, 0))))) -> 0 | AQ39: =IF(ISBLANK(Table2[[#This Row],[Pending_question]]), 2,(IF(Table2[[#This Row],[Pending_question]]="Yes", 1, 0))) -> 0 | AR39: 44447
A40: 44455 | B40: Closed | C40: {=IF(SUM(Table2[[#This Row],[PQ_indic]],Table2[[#This Row],[RRA_indic]],Table2[[#This Row],[EIS_indic]],Table2[[#This Row],[DON_indic]])=8, "Missing data", (IF(AND(Table2[[#This Row],[Pending_question]]="Yes", OR( Table2[[#This Row],[Need_RRA]]="No", ISBLANK(Table2[[#This Row],[Need_RRA]])), OR(Table2[[#This Row],[Need_EIS]]="No", ISBLANK(Table2[[#This Row],[Need_EIS]])), OR(Table2[[#This Row],[Need_DON]]="No", ISBLANK(Table2[[#This Row],[Need_DON]]) )),"Question, no products",( IF( AND(Table2[[#This Row],[Pending_question]]="Yes", ISBLANK(Table2[[#This Row],[PQ_closure_date]])), (IF(SUM(Table2[[#This Row],[RRA_indic]],Table2[[#This Row],[EIS_indic]],Table2[[#This Row],[DON_indic]])=0, "Open Question, all products done",(I447IF(OR(Table2[[#This Row],[RRA_indic]]=2, Table2[[#This Row],[EIS_indic]]=2, Table2[[#This Row],[DON_indic]]=2),"Question, Products unknown",IF(AND(Table2[[#This Row],[RRA_indic]]=1, Table2[[#This Row],[EIS_indic]]=1, Table2[[#This Row],[DON_indic]]=1), "Open Question, RRA, EIS, DON", IF(AND(Table2[[#This Row],[RRA_indic]]=1, Table2[[#This Row],[EIS_indic]]=1), "Open Question, RRA, EIS",IF(AND(Table2[[#This Row],[RRA_indic]]=1, Table2[[#This Row],[DON_indic]]=1), "Open Question, RRA, DON", IF(AND(Table2[[#This Row],[EIS_indic]]=1, Table2[[#This Row],[DON_indic]]=1), "Open Question, EIS, DON",IF(Table2[[#This Row],[RRA_indic]]=1, "Open Question, RRA", IF(Table2[[#This Row],[EIS_indic]]=1, "Open Question, EIS", "Open Question, DON")))))))))), (IF(SUM(Table2[[#This Row],[RRA_indic]],Table2[[#This Row],[EIS_indic]],Table2[[#This Row],[DON_indic]])=0, "All Products done",(IF(OR(Table2[[#This Row],[RRA_indic]]=2, Table2[[#This Row],[EIS_indic]]=2, Table2[[#This Row],[DON_indic]]=2),"Unknown", IF(AND(Table2[[#This Row],[RRA_indic]]=1, Table2[[#This Row],[EIS_indic]]=1, Table2[[#This Row],[DON_indic]]=1), "Open RRA, EIS, DON", IF(AND(Table2[[#This Row],[RRA_indic]]=1, Table2[[#This Row],[EIS_indic]]=1), "Open RRA, EIS", IF(AND(Table2[[#This Row],[RRA_indic]]=1, Table2[[#This Row],[DON_indic]]=1), "Open RRA, DON", IF(AND(Table2[[#This Row],[EIS_indic]]=1, Table2[[#This Row],[DON_indic]]=1), "Open EIS, DON", IF(Table2[[#This Row],[RRA_indic]]=1, "Open RRA", IF(Table2[[#This Row],[EIS_indic]]=1, "Open EIS", "Open DON")))))))))))))))} -> All Products done | D40: Dunja | E40: Avian influenza A (H9N2) | F40: China | G40: Not applicable | M40: No | P40: No | Q40: Not applicable | R40: No | Y40: yes | AB40: 15 September: EIS draft received from WPRO and shared with TT/ 15 September EIS back to WPRO/Sep 16 published | AH40: 44455 | AI40: no | AL40: feedback reqested by 3 PM , 15 Sept | AM40: =VLOOKUP(Table2[[#This Row],[country]],Countrycode!A:B,2,FALSE) -> CHN | AN40: =IF(ISBLANK(Table2[[#This Row],[Need_RRA]]), 2,(IF(Table2[[#This Row],[Need_RRA]]="No", 0, (IF(AND(Table2[[#This Row],[Need_RRA]]="Yes", Table2[[#This Row],[RRA_pub_date]]=""),1, 0))))) -> 0 | AO40: =IF(ISBLANK(Table2[[#This Row],[Need_EIS]]), 2,(IF(Table2[[#This Row],[Need_EIS]]="No", 0, (IF(AND(Table2[[#This Row],[Need_EIS]]="Yes", Table2[[#This Row],[EIS_pub_date]]=""),1, 0))))) -> 0 | AP40: =IF(ISBLANK(Table2[[#This Row],[Need_DON]]), 2,(IF(Table2[[#This Row],[Need_DON]]="No", 0, (IF(AND(Table2[[#This Row],[Need_DON]]="Yes", Table2[[#This Row],[DON_pub_date]]=""),1, 0))))) -> 0 | AQ40: =IF(ISBLANK(Table2[[#This Row],[Pending_question]]), 2,(IF(Table2[[#This Row],[Pending_question]]="Yes", 1, 0))) -> 0
A41: 44455 | B41: Closed | C41: {=IF(SUM(Table2[[#This Row],[PQ_indic]],Table2[[#This Row],[RRA_indic]],Table2[[#This Row],[EIS_indic]],Table2[[#This Row],[DON_indic]])=8, "Missing data", (IF(AND(Table2[[#This Row],[Pending_question]]="Yes", OR( Table2[[#This Row],[Need_RRA]]="No", ISBLANK(Table2[[#This Row],[Need_RRA]])), OR(Table2[[#This Row],[Need_EIS]]="No", ISBLANK(Table2[[#This Row],[Need_EIS]])), OR(Table2[[#This Row],[Need_DON]]="No", ISBLANK(Table2[[#This Row],[Need_DON]]) )),"Question, no products",( IF( AND(Table2[[#This Row],[Pending_question]]="Yes", ISBLANK(Table2[[#This Row],[PQ_closure_date]])), (IF(SUM(Table2[[#This Row],[RRA_indic]],Table2[[#This Row],[EIS_indic]],Table2[[#This Row],[DON_indic]])=0, "Open Question, all products done",(I447IF(OR(Table2[[#This Row],[RRA_indic]]=2, Table2[[#This Row],[EIS_indic]]=2, Table2[[#This Row],[DON_indic]]=2),"Question, Products unknown",IF(AND(Table2[[#This Row],[RRA_indic]]=1, Table2[[#This Row],[EIS_indic]]=1, Table2[[#This Row],[DON_indic]]=1), "Open Question, RRA, EIS, DON", IF(AND(Table2[[#This Row],[RRA_indic]]=1, Table2[[#This Row],[EIS_indic]]=1), "Open Question, RRA, EIS",IF(AND(Table2[[#This Row],[RRA_indic]]=1, Table2[[#This Row],[DON_indic]]=1), "Open Question, RRA, DON", IF(AND(Table2[[#This Row],[EIS_indic]]=1, Table2[[#This Row],[DON_indic]]=1), "Open Question, EIS, DON",IF(Table2[[#This Row],[RRA_indic]]=1, "Open Question, RRA", IF(Table2[[#This Row],[EIS_indic]]=1, "Open Question, EIS", "Open Question, DON")))))))))), (IF(SUM(Table2[[#This Row],[RRA_indic]],Table2[[#This Row],[EIS_indic]],Table2[[#This Row],[DON_indic]])=0, "All Products done",(IF(OR(Table2[[#This Row],[RRA_indic]]=2, Table2[[#This Row],[EIS_indic]]=2, Table2[[#This Row],[DON_indic]]=2),"Unknown", IF(AND(Table2[[#This Row],[RRA_indic]]=1, Table2[[#This Row],[EIS_indic]]=1, Table2[[#This Row],[DON_indic]]=1), "Open RRA, EIS, DON", IF(AND(Table2[[#This Row],[RRA_indic]]=1, Table2[[#This Row],[EIS_indic]]=1), "Open RRA, EIS", IF(AND(Table2[[#This Row],[RRA_indic]]=1, Table2[[#This Row],[DON_indic]]=1), "Open RRA, DON", IF(AND(Table2[[#This Row],[EIS_indic]]=1, Table2[[#This Row],[DON_indic]]=1), "Open EIS, DON", IF(Table2[[#This Row],[RRA_indic]]=1, "Open RRA", IF(Table2[[#This Row],[EIS_indic]]=1, "Open EIS", "Open DON")))))))))))))))} -> All Products done | D41: Dunja | E41: Avian influenza A (H5N6) | F41: China | G41: Not applicable | M41: No | P41: No | Q41: Not applicable | R41: No | Y41: yes | AB41: 15 September: EIS draft received from WPRO and shared with TT/ 15 September EIS back to WPRO/ 16 Sep published | AH41: 44455 | AI41: no | AL41: feedback reqested by 3 PM , 15 Sept | AM41: =VLOOKUP(Table2[[#This Row],[country]],Countrycode!A:B,2,FALSE) -> CHN | AN41: =IF(ISBLANK(Table2[[#This Row],[Need_RRA]]), 2,(IF(Table2[[#This Row],[Need_RRA]]="No", 0, (IF(AND(Table2[[#This Row],[Need_RRA]]="Yes", Table2[[#This Row],[RRA_pub_date]]=""),1, 0))))) -> 0 | AO41: =IF(ISBLANK(Table2[[#This Row],[Need_EIS]]), 2,(IF(Table2[[#This Row],[Need_EIS]]="No", 0, (IF(AND(Table2[[#This Row],[Need_EIS]]="Yes", Table2[[#This Row],[EIS_pub_date]]=""),1, 0))))) -> 0 | AP41: =IF(ISBLANK(Table2[[#This Row],[Need_DON]]), 2,(IF(Table2[[#This Row],[Need_DON]]="No", 0, (IF(AND(Table2[[#This Row],[Need_DON]]="Yes", Table2[[#This Row],[DON_pub_date]]=""),1, 0))))) -> 0 | AQ41: =IF(ISBLANK(Table2[[#This Row],[Pending_question]]), 2,(IF(Table2[[#This Row],[Pending_question]]="Yes", 1, 0))) -> 0
A42: 44455 | B42: Closed | C42: {=IF(SUM(Table2[[#This Row],[PQ_indic]],Table2[[#This Row],[RRA_indic]],Table2[[#This Row],[EIS_indic]],Table2[[#This Row],[DON_indic]])=8, "Missing data", (IF(AND(Table2[[#This Row],[Pending_question]]="Yes", OR( Table2[[#This Row],[Need_RRA]]="No", ISBLANK(Table2[[#This Row],[Need_RRA]])), OR(Table2[[#This Row],[Need_EIS]]="No", ISBLANK(Table2[[#This Row],[Need_EIS]])), OR(Table2[[#This Row],[Need_DON]]="No", ISBLANK(Table2[[#This Row],[Need_DON]]) )),"Question, no products",( IF( AND(Table2[[#This Row],[Pending_question]]="Yes", ISBLANK(Table2[[#This Row],[PQ_closure_date]])), (IF(SUM(Table2[[#This Row],[RRA_indic]],Table2[[#This Row],[EIS_indic]],Table2[[#This Row],[DON_indic]])=0, "Open Question, all products done",(I447IF(OR(Table2[[#This Row],[RRA_indic]]=2, Table2[[#This Row],[EIS_indic]]=2, Table2[[#This Row],[DON_indic]]=2),"Question, Products unknown",IF(AND(Table2[[#This Row],[RRA_indic]]=1, Table2[[#This Row],[EIS_indic]]=1, Table2[[#This Row],[DON_indic]]=1), "Open Question, RRA, EIS, DON", IF(AND(Table2[[#This Row],[RRA_indic]]=1, Table2[[#This Row],[EIS_indic]]=1), "Open Question, RRA, EIS",IF(AND(Table2[[#This Row],[RRA_indic]]=1, Table2[[#This Row],[DON_indic]]=1), "Open Question, RRA, DON", IF(AND(Table2[[#This Row],[EIS_indic]]=1, Table2[[#This Row],[DON_indic]]=1), "Open Question, EIS, DON",IF(Table2[[#This Row],[RRA_indic]]=1, "Open Question, RRA", IF(Table2[[#This Row],[EIS_indic]]=1, "Open Question, EIS", "Open Question, DON")))))))))), (IF(SUM(Table2[[#This Row],[RRA_indic]],Table2[[#This Row],[EIS_indic]],Table2[[#This Row],[DON_indic]])=0, "All Products done",(IF(OR(Table2[[#This Row],[RRA_indic]]=2, Table2[[#This Row],[EIS_indic]]=2, Table2[[#This Row],[DON_indic]]=2),"Unknown", IF(AND(Table2[[#This Row],[RRA_indic]]=1, Table2[[#This Row],[EIS_indic]]=1, Table2[[#This Row],[DON_indic]]=1), "Open RRA, EIS, DON", IF(AND(Table2[[#This Row],[RRA_indic]]=1, Table2[[#This Row],[EIS_indic]]=1), "Open RRA, EIS", IF(AND(Table2[[#This Row],[RRA_indic]]=1, Table2[[#This Row],[DON_indic]]=1), "Open RRA, DON", IF(AND(Table2[[#This Row],[EIS_indic]]=1, Table2[[#This Row],[DON_indic]]=1), "Open EIS, DON", IF(Table2[[#This Row],[RRA_indic]]=1, "Open RRA", IF(Table2[[#This Row],[EIS_indic]]=1, "Open EIS", "Open DON")))))))))))))))} -> All Products done | D42: Dunja | E42: Marburg | F42: Guinea | G42: Not applicable | M42: No | P42: No | Q42: Not applicable | Y42: yes | AB42: 13 September: need an EIS for the end of the outbreak; EIS sent to HQ and TT for feedback on 14 September/14 Sep EIS sent to AFRO/ 15 September reminder sent to Afro/16 published | AH42: 44455 | AI42: yes | AK42: 44455 | AL42: the end declaration on 16 September | AM42: =VLOOKUP(Table2[[#This Row],[country]],Countrycode!A:B,2,FALSE) -> GIN | AN42: =IF(ISBLANK(Table2[[#This Row],[Need_RRA]]), 2,(IF(Table2[[#This Row],[Need_RRA]]="No", 0, (IF(AND(Table2[[#This Row],[Need_RRA]]="Yes", Table2[[#This Row],[RRA_pub_date]]=""),1, 0))))) -> 0 | AO42: =IF(ISBLANK(Table2[[#This Row],[Need_EIS]]), 2,(IF(Table2[[#This Row],[Need_EIS]]="No", 0, (IF(AND(Table2[[#This Row],[Need_EIS]]="Yes", Table2[[#This Row],[EIS_pub_date]]=""),1, 0))))) -> 0 | AP42: =IF(ISBLANK(Table2[[#This Row],[Need_DON]]), 2,(IF(Table2[[#This Row],[Need_DON]]="No", 0, (IF(AND(Table2[[#This Row],[Need_DON]]="Yes", Table2[[#This Row],[DON_pub_date]]=""),1, 0))))) -> 0 | AQ42: =IF(ISBLANK(Table2[[#This Row],[Pending_question]]), 2,(IF(Table2[[#This Row],[Pending_question]]="Yes", 1, 0))) -> 0
A43: 44461 | B43: Closed | C43: {=IF(SUM(Table2[[#This Row],[PQ_indic]],Table2[[#This Row],[RRA_indic]],Table2[[#This Row],[EIS_indic]],Table2[[#This Row],[DON_indic]])=8, "Missing data", (IF(AND(Table2[[#This Row],[Pending_question]]="Yes", OR( Table2[[#This Row],[Need_RRA]]="No", ISBLANK(Table2[[#This Row],[Need_RRA]])), OR(Table2[[#This Row],[Need_EIS]]="No", ISBLANK(Table2[[#This Row],[Need_EIS]])), OR(Table2[[#This Row],[Need_DON]]="No", ISBLANK(Table2[[#This Row],[Need_DON]]) )),"Question, no products",( IF( AND(Table2[[#This Row],[Pending_question]]="Yes", ISBLANK(Table2[[#This Row],[PQ_closure_date]])), (IF(SUM(Table2[[#This Row],[RRA_indic]],Table2[[#This Row],[EIS_indic]],Table2[[#This Row],[DON_indic]])=0, "Open Question, all products done",(I447IF(OR(Table2[[#This Row],[RRA_indic]]=2, Table2[[#This Row],[EIS_indic]]=2, Table2[[#This Row],[DON_indic]]=2),"Question, Products unknown",IF(AND(Table2[[#This Row],[RRA_indic]]=1, Table2[[#This Row],[EIS_indic]]=1, Table2[[#This Row],[DON_indic]]=1), "Open Question, RRA, EIS, DON", IF(AND(Table2[[#This Row],[RRA_indic]]=1, Table2[[#This Row],[EIS_indic]]=1), "Open Question, RRA, EIS",IF(AND(Table2[[#This Row],[RRA_indic]]=1, Table2[[#This Row],[DON_indic]]=1), "Open Question, RRA, DON", IF(AND(Table2[[#This Row],[EIS_indic]]=1, Table2[[#This Row],[DON_indic]]=1), "Open Question, EIS, DON",IF(Table2[[#This Row],[RRA_indic]]=1, "Open Question, RRA", IF(Table2[[#This Row],[EIS_indic]]=1, "Open Question, EIS", "Open Question, DON")))))))))), (IF(SUM(Table2[[#This Row],[RRA_indic]],Table2[[#This Row],[EIS_indic]],Table2[[#This Row],[DON_indic]])=0, "All Products done",(IF(OR(Table2[[#This Row],[RRA_indic]]=2, Table2[[#This Row],[EIS_indic]]=2, Table2[[#This Row],[DON_indic]]=2),"Unknown", IF(AND(Table2[[#This Row],[RRA_indic]]=1, Table2[[#This Row],[EIS_indic]]=1, Table2[[#This Row],[DON_indic]]=1), "Open RRA, EIS, DON", IF(AND(Table2[[#This Row],[RRA_indic]]=1, Table2[[#This Row],[EIS_indic]]=1), "Open RRA, EIS", IF(AND(Table2[[#This Row],[RRA_indic]]=1, Table2[[#This Row],[DON_indic]]=1), "Open RRA, DON", IF(AND(Table2[[#This Row],[EIS_indic]]=1, Table2[[#This Row],[DON_indic]]=1), "Open EIS, DON", IF(Table2[[#This Row],[RRA_indic]]=1, "Open RRA", IF(Table2[[#This Row],[EIS_indic]]=1, "Open EIS", "Open DON")))))))))))))))} -> All Products done | D43: Anastasia | E43: Cholera | F43: Afghanistan | G43: Not applicable | H43: 44461 | K43: 2021-E000343 | M43: No | P43: Yes | R43: 22 September 2021: we need an RRA./24 September: RRA will be initiated by HQ; drafted by HQ and shared with TT / 1 October: EMRO shared comments. Need to go back to EMRO as information is still missing / 5 October: reviewed draft shared with EMRO / 7 October: a reminder was sent to EMRO / 11 October: RRA call is planned for 12 Oct / 13 October: updated RRA is with EMRO for Pierre's clearance / 15 October: RRA cleared and distributed | S43: 44481 | U43: 44484 | Y43: no | AI43: no | AM43: =VLOOKUP(Table2[[#This Row],[country]],Countrycode!A:B,2,FALSE) -> AFG | AN43: =IF(ISBLANK(Table2[[#This Row],[Need_RRA]]), 2,(IF(Table2[[#This Row],[Need_RRA]]="No", 0, (IF(AND(Table2[[#This Row],[Need_RRA]]="Yes", Table2[[#This Row],[RRA_pub_date]]=""),1, 0))))) -> 0 | AO43: =IF(ISBLANK(Table2[[#This Row],[Need_EIS]]), 2,(IF(Table2[[#This Row],[Need_EIS]]="No", 0, (IF(AND(Table2[[#This Row],[Need_EIS]]="Yes", Table2[[#This Row],[EIS_pub_date]]=""),1, 0))))) -> 0 | AP43: =IF(ISBLANK(Table2[[#This Row],[Need_DON]]), 2,(IF(Table2[[#This Row],[Need_DON]]="No", 0, (IF(AND(Table2[[#This Row],[Need_DON]]="Yes", Table2[[#This Row],[DON_pub_date]]=""),1, 0))))) -> 0 | AQ43: =IF(ISBLANK(Table2[[#This Row],[Pending_question]]), 2,(IF(Table2[[#This Row],[Pending_question]]="Yes", 1, 0))) -> 0 | AR43: 44461
A44: 44461 | B44: Closed | C44: {=IF(SUM(Table2[[#This Row],[PQ_indic]],Table2[[#This Row],[RRA_indic]],Table2[[#This Row],[EIS_indic]],Table2[[#This Row],[DON_indic]])=8, "Missing data", (IF(AND(Table2[[#This Row],[Pending_question]]="Yes", OR( Table2[[#This Row],[Need_RRA]]="No", ISBLANK(Table2[[#This Row],[Need_RRA]])), OR(Table2[[#This Row],[Need_EIS]]="No", ISBLANK(Table2[[#This Row],[Need_EIS]])), OR(Table2[[#This Row],[Need_DON]]="No", ISBLANK(Table2[[#This Row],[Need_DON]]) )),"Question, no products",( IF( AND(Table2[[#This Row],[Pending_question]]="Yes", ISBLANK(Table2[[#This Row],[PQ_closure_date]])), (IF(SUM(Table2[[#This Row],[RRA_indic]],Table2[[#This Row],[EIS_indic]],Table2[[#This Row],[DON_indic]])=0, "Open Question, all products done",(I447IF(OR(Table2[[#This Row],[RRA_indic]]=2, Table2[[#This Row],[EIS_indic]]=2, Table2[[#This Row],[DON_indic]]=2),"Question, Products unknown",IF(AND(Table2[[#This Row],[RRA_indic]]=1, Table2[[#This Row],[EIS_indic]]=1, Table2[[#This Row],[DON_indic]]=1), "Open Question, RRA, EIS, DON", IF(AND(Table2[[#This Row],[RRA_indic]]=1, Table2[[#This Row],[EIS_indic]]=1), "Open Question, RRA, EIS",IF(AND(Table2[[#This Row],[RRA_indic]]=1, Table2[[#This Row],[DON_indic]]=1), "Open Question, RRA, DON", IF(AND(Table2[[#This Row],[EIS_indic]]=1, Table2[[#This Row],[DON_indic]]=1), "Open Question, EIS, DON",IF(Table2[[#This Row],[RRA_indic]]=1, "Open Question, RRA", IF(Table2[[#This Row],[EIS_indic]]=1, "Open Question, EIS", "Open Question, DON")))))))))), (IF(SUM(Table2[[#This Row],[RRA_indic]],Table2[[#This Row],[EIS_indic]],Table2[[#This Row],[DON_indic]])=0, "All Products done",(IF(OR(Table2[[#This Row],[RRA_indic]]=2, Table2[[#This Row],[EIS_indic]]=2, Table2[[#This Row],[DON_indic]]=2),"Unknown", IF(AND(Table2[[#This Row],[RRA_indic]]=1, Table2[[#This Row],[EIS_indic]]=1, Table2[[#This Row],[DON_indic]]=1), "Open RRA, EIS, DON", IF(AND(Table2[[#This Row],[RRA_indic]]=1, Table2[[#This Row],[EIS_indic]]=1), "Open RRA, EIS", IF(AND(Table2[[#This Row],[RRA_indic]]=1, Table2[[#This Row],[DON_indic]]=1), "Open RRA, DON", IF(AND(Table2[[#This Row],[EIS_indic]]=1, Table2[[#This Row],[DON_indic]]=1), "Open EIS, DON", IF(Table2[[#This Row],[RRA_indic]]=1, "Open RRA", IF(Table2[[#This Row],[EIS_indic]]=1, "Open EIS", "Open DON")))))))))))))))} -> All Products done | D44: Plummer | E44: Avian influenza A (H1N2)v | F44: France | G44: Not applicable | M44: No | P44: No | Q44: Not applicable | Y44: yes | AB44: 13 September: EIS received from EURO/ 15 September: HQ colleagues provided comments, document returned to EURO colleagues./ 16 September: EURO shared cleaned document with NFP for clearance.21 September: EURO shared the consolidated draft. Sent for final clearance / 22 Septembre: posted on EIS | AH44: 44461 | AI44: no | AM44: =VLOOKUP(Table2[[#This Row],[country]],Countrycode!A:B,2,FALSE) -> FRA | AN44: =IF(ISBLANK(Table2[[#This Row],[Need_RRA]]), 2,(IF(Table2[[#This Row],[Need_RRA]]="No", 0, (IF(AND(Table2[[#This Row],[Need_RRA]]="Yes", Table2[[#This Row],[RRA_pub_date]]=""),1, 0))))) -> 0 | AO44: =IF(ISBLANK(Table2[[#This Row],[Need_EIS]]), 2,(IF(Table2[[#This Row],[Need_EIS]]="No", 0, (IF(AND(Table2[[#This Row],[Need_EIS]]="Yes", Table2[[#This Row],[EIS_pub_date]]=""),1, 0))))) -> 0 | AP44: =IF(ISBLANK(Table2[[#This Row],[Need_DON]]), 2,(IF(Table2[[#This Row],[Need_DON]]="No", 0, (IF(AND(Table2[[#This Row],[Need_DON]]="Yes", Table2[[#This Row],[DON_pub_date]]=""),1, 0))))) -> 0 | AQ44: =IF(ISBLANK(Table2[[#This Row],[Pending_question]]), 2,(IF(Table2[[#This Row],[Pending_question]]="Yes", 1, 0))) -> 0
A45: 44462 | B45: Closed | C45: {=IF(SUM(Table2[[#This Row],[PQ_indic]],Table2[[#This Row],[RRA_indic]],Table2[[#This Row],[EIS_indic]],Table2[[#This Row],[DON_indic]])=8, "Missing data", (IF(AND(Table2[[#This Row],[Pending_question]]="Yes", OR( Table2[[#This Row],[Need_RRA]]="No", ISBLANK(Table2[[#This Row],[Need_RRA]])), OR(Table2[[#This Row],[Need_EIS]]="No", ISBLANK(Table2[[#This Row],[Need_EIS]])), OR(Table2[[#This Row],[Need_DON]]="No", ISBLANK(Table2[[#This Row],[Need_DON]]) )),"Question, no products",( IF( AND(Table2[[#This Row],[Pending_question]]="Yes", ISBLANK(Table2[[#This Row],[PQ_closure_date]])), (IF(SUM(Table2[[#This Row],[RRA_indic]],Table2[[#This Row],[EIS_indic]],Table2[[#This Row],[DON_indic]])=0, "Open Question, all products done",(I447IF(OR(Table2[[#This Row],[RRA_indic]]=2, Table2[[#This Row],[EIS_indic]]=2, Table2[[#This Row],[DON_indic]]=2),"Question, Products unknown",IF(AND(Table2[[#This Row],[RRA_indic]]=1, Table2[[#This Row],[EIS_indic]]=1, Table2[[#This Row],[DON_indic]]=1), "Open Question, RRA, EIS, DON", IF(AND(Table2[[#This Row],[RRA_indic]]=1, Table2[[#This Row],[EIS_indic]]=1), "Open Question, RRA, EIS",IF(AND(Table2[[#This Row],[RRA_indic]]=1, Table2[[#This Row],[DON_indic]]=1), "Open Question, RRA, DON", IF(AND(Table2[[#This Row],[EIS_indic]]=1, Table2[[#This Row],[DON_indic]]=1), "Open Question, EIS, DON",IF(Table2[[#This Row],[RRA_indic]]=1, "Open Question, RRA", IF(Table2[[#This Row],[EIS_indic]]=1, "Open Question, EIS", "Open Question, DON")))))))))), (IF(SUM(Table2[[#This Row],[RRA_indic]],Table2[[#This Row],[EIS_indic]],Table2[[#This Row],[DON_indic]])=0, "All Products done",(IF(OR(Table2[[#This Row],[RRA_indic]]=2, Table2[[#This Row],[EIS_indic]]=2, Table2[[#This Row],[DON_indic]]=2),"Unknown", IF(AND(Table2[[#This Row],[RRA_indic]]=1, Table2[[#This Row],[EIS_indic]]=1, Table2[[#This Row],[DON_indic]]=1), "Open RRA, EIS, DON", IF(AND(Table2[[#This Row],[RRA_indic]]=1, Table2[[#This Row],[EIS_indic]]=1), "Open RRA, EIS", IF(AND(Table2[[#This Row],[RRA_indic]]=1, Table2[[#This Row],[DON_indic]]=1), "Open RRA, DON", IF(AND(Table2[[#This Row],[EIS_indic]]=1, Table2[[#This Row],[DON_indic]]=1), "Open EIS, DON", IF(Table2[[#This Row],[RRA_indic]]=1, "Open RRA", IF(Table2[[#This Row],[EIS_indic]]=1, "Open EIS", "Open DON")))))))))))))))} -> All Products done | D45: Plummer/Dunja | E45: Avian influenza A (H5N6) | F45: China | G45: Not applicable | H45: 44462 | M45: No | P45: No | Q45: Not applicable | R45: No | Y45: yes | AB45: 23 September: Initial EIS draft shared by WPRO. Circulated for review at HQ/ published on 27 September | AH45: 44466 | AI45: no | AM45: =VLOOKUP(Table2[[#This Row],[country]],Countrycode!A:B,2,FALSE) -> CHN | AN45: =IF(ISBLANK(Table2[[#This Row],[Need_RRA]]), 2,(IF(Table2[[#This Row],[Need_RRA]]="No", 0, (IF(AND(Table2[[#This Row],[Need_RRA]]="Yes", Table2[[#This Row],[RRA_pub_date]]=""),1, 0))))) -> 0 | AO45: =IF(ISBLANK(Table2[[#This Row],[Need_EIS]]), 2,(IF(Table2[[#This Row],[Need_EIS]]="No", 0, (IF(AND(Table2[[#This Row],[Need_EIS]]="Yes", Table2[[#This Row],[EIS_pub_date]]=""),1, 0))))) -> 0 | AP45: =IF(ISBLANK(Table2[[#This Row],[Need_DON]]), 2,(IF(Table2[[#This Row],[Need_DON]]="No", 0, (IF(AND(Table2[[#This Row],[Need_DON]]="Yes", Table2[[#This Row],[DON_pub_date]]=""),1, 0))))) -> 0 | AQ45: =IF(ISBLANK(Table2[[#This Row],[Pending_question]]), 2,(IF(Table2[[#This Row],[Pending_question]]="Yes", 1, 0))) -> 0 | AR45: 44462
A46: 44466 | B46: Closed | C46: {=IF(SUM(Table2[[#This Row],[PQ_indic]],Table2[[#This Row],[RRA_indic]],Table2[[#This Row],[EIS_indic]],Table2[[#This Row],[DON_indic]])=8, "Missing data", (IF(AND(Table2[[#This Row],[Pending_question]]="Yes", OR( Table2[[#This Row],[Need_RRA]]="No", ISBLANK(Table2[[#This Row],[Need_RRA]])), OR(Table2[[#This Row],[Need_EIS]]="No", ISBLANK(Table2[[#This Row],[Need_EIS]])), OR(Table2[[#This Row],[Need_DON]]="No", ISBLANK(Table2[[#This Row],[Need_DON]]) )),"Question, no products",( IF( AND(Table2[[#This Row],[Pending_question]]="Yes", ISBLANK(Table2[[#This Row],[PQ_closure_date]])), (IF(SUM(Table2[[#This Row],[RRA_indic]],Table2[[#This Row],[EIS_indic]],Table2[[#This Row],[DON_indic]])=0, "Open Question, all products done",(I447IF(OR(Table2[[#This Row],[RRA_indic]]=2, Table2[[#This Row],[EIS_indic]]=2, Table2[[#This Row],[DON_indic]]=2),"Question, Products unknown",IF(AND(Table2[[#This Row],[RRA_indic]]=1, Table2[[#This Row],[EIS_indic]]=1, Table2[[#This Row],[DON_indic]]=1), "Open Question, RRA, EIS, DON", IF(AND(Table2[[#This Row],[RRA_indic]]=1, Table2[[#This Row],[EIS_indic]]=1), "Open Question, RRA, EIS",IF(AND(Table2[[#This Row],[RRA_indic]]=1, Table2[[#This Row],[DON_indic]]=1), "Open Question, RRA, DON", IF(AND(Table2[[#This Row],[EIS_indic]]=1, Table2[[#This Row],[DON_indic]]=1), "Open Question, EIS, DON",IF(Table2[[#This Row],[RRA_indic]]=1, "Open Question, RRA", IF(Table2[[#This Row],[EIS_indic]]=1, "Open Question, EIS", "Open Question, DON")))))))))), (IF(SUM(Table2[[#This Row],[RRA_indic]],Table2[[#This Row],[EIS_indic]],Table2[[#This Row],[DON_indic]])=0, "All Products done",(IF(OR(Table2[[#This Row],[RRA_indic]]=2, Table2[[#This Row],[EIS_indic]]=2, Table2[[#This Row],[DON_indic]]=2),"Unknown", IF(AND(Table2[[#This Row],[RRA_indic]]=1, Table2[[#This Row],[EIS_indic]]=1, Table2[[#This Row],[DON_indic]]=1), "Open RRA, EIS, DON", IF(AND(Table2[[#This Row],[RRA_indic]]=1, Table2[[#This Row],[EIS_indic]]=1), "Open RRA, EIS", IF(AND(Table2[[#This Row],[RRA_indic]]=1, Table2[[#This Row],[DON_indic]]=1), "Open RRA, DON", IF(AND(Table2[[#This Row],[EIS_indic]]=1, Table2[[#This Row],[DON_indic]]=1), "Open EIS, DON", IF(Table2[[#This Row],[RRA_indic]]=1, "Open RRA", IF(Table2[[#This Row],[EIS_indic]]=1, "Open EIS", "Open DON")))))))))))))))} -> All Products done | D46: Dunja | E46: Avian influenza A (H5N6) | F46: China | G46: Not applicable | H46: 44466 | M46: No | P46: No | Q46: Not applicable | R46: No | Y46: yes | AB46: 27 Sep received notification for 2 cases and draft EIS . HQ feedback sent back to WPRO on 27 Sep/ 29 EIS received from WPRO, approved and published | AH46: 44468 | AI46: no | AM46: =VLOOKUP(Table2[[#This Row],[country]],Countrycode!A:B,2,FALSE) -> CHN | AN46: =IF(ISBLANK(Table2[[#This Row],[Need_RRA]]), 2,(IF(Table2[[#This Row],[Need_RRA]]="No", 0, (IF(AND(Table2[[#This Row],[Need_RRA]]="Yes", Table2[[#This Row],[RRA_pub_date]]=""),1, 0))))) -> 0 | AO46: =IF(ISBLANK(Table2[[#This Row],[Need_EIS]]), 2,(IF(Table2[[#This Row],[Need_EIS]]="No", 0, (IF(AND(Table2[[#This Row],[Need_EIS]]="Yes", Table2[[#This Row],[EIS_pub_date]]=""),1, 0))))) -> 0 | AP46: =IF(ISBLANK(Table2[[#This Row],[Need_DON]]), 2,(IF(Table2[[#This Row],[Need_DON]]="No", 0, (IF(AND(Table2[[#This Row],[Need_DON]]="Yes", Table2[[#This Row],[DON_pub_date]]=""),1, 0))))) -> 0 | AQ46: =IF(ISBLANK(Table2[[#This Row],[Pending_question]]), 2,(IF(Table2[[#This Row],[Pending_question]]="Yes", 1, 0))) -> 0 | AR46: 44466
A47: 44467 | B47: Closed | C47: {=IF(SUM(Table2[[#This Row],[PQ_indic]],Table2[[#This Row],[RRA_indic]],Table2[[#This Row],[EIS_indic]],Table2[[#This Row],[DON_indic]])=8, "Missing data", (IF(AND(Table2[[#This Row],[Pending_question]]="Yes", OR( Table2[[#This Row],[Need_RRA]]="No", ISBLANK(Table2[[#This Row],[Need_RRA]])), OR(Table2[[#This Row],[Need_EIS]]="No", ISBLANK(Table2[[#This Row],[Need_EIS]])), OR(Table2[[#This Row],[Need_DON]]="No", ISBLANK(Table2[[#This Row],[Need_DON]]) )),"Question, no products",( IF( AND(Table2[[#This Row],[Pending_question]]="Yes", ISBLANK(Table2[[#This Row],[PQ_closure_date]])), (IF(SUM(Table2[[#This Row],[RRA_indic]],Table2[[#This Row],[EIS_indic]],Table2[[#This Row],[DON_indic]])=0, "Open Question, all products done",(I447IF(OR(Table2[[#This Row],[RRA_indic]]=2, Table2[[#This Row],[EIS_indic]]=2, Table2[[#This Row],[DON_indic]]=2),"Question, Products unknown",IF(AND(Table2[[#This Row],[RRA_indic]]=1, Table2[[#This Row],[EIS_indic]]=1, Table2[[#This Row],[DON_indic]]=1), "Open Question, RRA, EIS, DON", IF(AND(Table2[[#This Row],[RRA_indic]]=1, Table2[[#This Row],[EIS_indic]]=1), "Open Question, RRA, EIS",IF(AND(Table2[[#This Row],[RRA_indic]]=1, Table2[[#This Row],[DON_indic]]=1), "Open Question, RRA, DON", IF(AND(Table2[[#This Row],[EIS_indic]]=1, Table2[[#This Row],[DON_indic]]=1), "Open Question, EIS, DON",IF(Table2[[#This Row],[RRA_indic]]=1, "Open Question, RRA", IF(Table2[[#This Row],[EIS_indic]]=1, "Open Question, EIS", "Open Question, DON")))))))))), (IF(SUM(Table2[[#This Row],[RRA_indic]],Table2[[#This Row],[EIS_indic]],Table2[[#This Row],[DON_indic]])=0, "All Products done",(IF(OR(Table2[[#This Row],[RRA_indic]]=2, Table2[[#This Row],[EIS_indic]]=2, Table2[[#This Row],[DON_indic]]=2),"Unknown", IF(AND(Table2[[#This Row],[RRA_indic]]=1, Table2[[#This Row],[EIS_indic]]=1, Table2[[#This Row],[DON_indic]]=1), "Open RRA, EIS, DON", IF(AND(Table2[[#This Row],[RRA_indic]]=1, Table2[[#This Row],[EIS_indic]]=1), "Open RRA, EIS", IF(AND(Table2[[#This Row],[RRA_indic]]=1, Table2[[#This Row],[DON_indic]]=1), "Open RRA, DON", IF(AND(Table2[[#This Row],[EIS_indic]]=1, Table2[[#This Row],[DON_indic]]=1), "Open EIS, DON", IF(Table2[[#This Row],[RRA_indic]]=1, "Open RRA", IF(Table2[[#This Row],[EIS_indic]]=1, "Open EIS", "Open DON")))))))))))))))} -> All Products done | D47: Dunja | E47: Avian influenza A (H5N6) | F47: China | G47: Not applicable | H47: 44467 | M47: No | P47: No | Q47: Not applicable | R47: No | Y47: yes | AB47: 28 Sep received notification and the draft EIS. HQ feedback expected by CoB/28 September the EIS with HQ feedback sent back to WPRO/30 Sep, received EIS , cleared and published | AH47: 44469 | AI47: no | AM47: =VLOOKUP(Table2[[#This Row],[country]],Countrycode!A:B,2,FALSE) -> CHN | AN47: =IF(ISBLANK(Table2[[#This Row],[Need_RRA]]), 2,(IF(Table2[[#This Row],[Need_RRA]]="No", 0, (IF(AND(Table2[[#This Row],[Need_RRA]]="Yes", Table2[[#This Row],[RRA_pub_date]]=""),1, 0))))) -> 0 | AO47: =IF(ISBLANK(Table2[[#This Row],[Need_EIS]]), 2,(IF(Table2[[#This Row],[Need_EIS]]="No", 0, (IF(AND(Table2[[#This Row],[Need_EIS]]="Yes", Table2[[#This Row],[EIS_pub_date]]=""),1, 0))))) -> 0 | AP47: =IF(ISBLANK(Table2[[#This Row],[Need_DON]]), 2,(IF(Table2[[#This Row],[Need_DON]]="No", 0, (IF(AND(Table2[[#This Row],[Need_DON]]="Yes", Table2[[#This Row],[DON_pub_date]]=""),1, 0))))) -> 0 | AQ47: =IF(ISBLANK(Table2[[#This Row],[Pending_question]]), 2,(IF(Table2[[#This Row],[Pending_question]]="Yes", 1, 0))) -> 0 | AR47: 44467
A48: 44468 | B48: Closed | C48: {=IF(SUM(Table2[[#This Row],[PQ_indic]],Table2[[#This Row],[RRA_indic]],Table2[[#This Row],[EIS_indic]],Table2[[#This Row],[DON_indic]])=8, "Missing data", (IF(AND(Table2[[#This Row],[Pending_question]]="Yes", OR( Table2[[#This Row],[Need_RRA]]="No", ISBLANK(Table2[[#This Row],[Need_RRA]])), OR(Table2[[#This Row],[Need_EIS]]="No", ISBLANK(Table2[[#This Row],[Need_EIS]])), OR(Table2[[#This Row],[Need_DON]]="No", ISBLANK(Table2[[#This Row],[Need_DON]]) )),"Question, no products",( IF( AND(Table2[[#This Row],[Pending_question]]="Yes", ISBLANK(Table2[[#This Row],[PQ_closure_date]])), (IF(SUM(Table2[[#This Row],[RRA_indic]],Table2[[#This Row],[EIS_indic]],Table2[[#This Row],[DON_indic]])=0, "Open Question, all products done",(I447IF(OR(Table2[[#This Row],[RRA_indic]]=2, Table2[[#This Row],[EIS_indic]]=2, Table2[[#This Row],[DON_indic]]=2),"Question, Products unknown",IF(AND(Table2[[#This Row],[RRA_indic]]=1, Table2[[#This Row],[EIS_indic]]=1, Table2[[#This Row],[DON_indic]]=1), "Open Question, RRA, EIS, DON", IF(AND(Table2[[#This Row],[RRA_indic]]=1, Table2[[#This Row],[EIS_indic]]=1), "Open Question, RRA, EIS",IF(AND(Table2[[#This Row],[RRA_indic]]=1, Table2[[#This Row],[DON_indic]]=1), "Open Question, RRA, DON", IF(AND(Table2[[#This Row],[EIS_indic]]=1, Table2[[#This Row],[DON_indic]]=1), "Open Question, EIS, DON",IF(Table2[[#This Row],[RRA_indic]]=1, "Open Question, RRA", IF(Table2[[#This Row],[EIS_indic]]=1, "Open Question, EIS", "Open Question, DON")))))))))), (IF(SUM(Table2[[#This Row],[RRA_indic]],Table2[[#This Row],[EIS_indic]],Table2[[#This Row],[DON_indic]])=0, "All Products done",(IF(OR(Table2[[#This Row],[RRA_indic]]=2, Table2[[#This Row],[EIS_indic]]=2, Table2[[#This Row],[DON_indic]]=2),"Unknown", IF(AND(Table2[[#This Row],[RRA_indic]]=1, Table2[[#This Row],[EIS_indic]]=1, Table2[[#This Row],[DON_indic]]=1), "Open RRA, EIS, DON", IF(AND(Table2[[#This Row],[RRA_indic]]=1, Table2[[#This Row],[EIS_indic]]=1), "Open RRA, EIS", IF(AND(Table2[[#This Row],[RRA_indic]]=1, Table2[[#This Row],[DON_indic]]=1), "Open RRA, DON", IF(AND(Table2[[#This Row],[EIS_indic]]=1, Table2[[#This Row],[DON_indic]]=1), "Open EIS, DON", IF(Table2[[#This Row],[RRA_indic]]=1, "Open RRA", IF(Table2[[#This Row],[EIS_indic]]=1, "Open EIS", "Open DON")))))))))))))))} -> All Products done | D48: Dunja | E48: Avian influenza A (H1N2) v | F48: Austria | G48: Not applicable | H48: 44468 | J48: 44468 | M48: No | P48: No | Q48: Not applicable | R48: No | Y48: yes | AB48: 29 September: EMS open by EURO where they say they asked the notification from IHR NFP / 30 September: HQ contacted EURO and requested EIS/ 2 October ( sat at 6.45 PM) received draft EIS from EURO/ on Sun 3 Oct shared EIS with TT, feedback reqested by 1PM , 4 Oct/ 4 Oct EIS sent to EURO / 6 October: Austria NFP replied to EURO with comments on EIS draft and added information. EURO shared the final draft with HQ for consolidation of comments, finalization and posting. 7 October published | AH48: 44476 | AI48: no | AL48: EURO waiting NFP official confirmation to drafting the EIS | AM48: =VLOOKUP(Table2[[#This Row],[country]],Countrycode!A:B,2,FALSE) -> AUT | AN48: =IF(ISBLANK(Table2[[#This Row],[Need_RRA]]), 2,(IF(Table2[[#This Row],[Need_RRA]]="No", 0, (IF(AND(Table2[[#This Row],[Need_RRA]]="Yes", Table2[[#This Row],[RRA_pub_date]]=""),1, 0))))) -> 0 | AO48: =IF(ISBLANK(Table2[[#This Row],[Need_EIS]]), 2,(IF(Table2[[#This Row],[Need_EIS]]="No", 0, (IF(AND(Table2[[#This Row],[Need_EIS]]="Yes", Table2[[#This Row],[EIS_pub_date]]=""),1, 0))))) -> 0 | AP48: =IF(ISBLANK(Table2[[#This Row],[Need_DON]]), 2,(IF(Table2[[#This Row],[Need_DON]]="No", 0, (IF(AND(Table2[[#This Row],[Need_DON]]="Yes", Table2[[#This Row],[DON_pub_date]]=""),1, 0))))) -> 0 | AQ48: =IF(ISBLANK(Table2[[#This Row],[Pending_question]]), 2,(IF(Table2[[#This Row],[Pending_question]]="Yes", 1, 0))) -> 0 | AR48: 44469
A49: 44472 | B49: Closed | C49: {=IF(SUM(Table2[[#This Row],[PQ_indic]],Table2[[#This Row],[RRA_indic]],Table2[[#This Row],[EIS_indic]],Table2[[#This Row],[DON_indic]])=8, "Missing data", (IF(AND(Table2[[#This Row],[Pending_question]]="Yes", OR( Table2[[#This Row],[Need_RRA]]="No", ISBLANK(Table2[[#This Row],[Need_RRA]])), OR(Table2[[#This Row],[Need_EIS]]="No", ISBLANK(Table2[[#This Row],[Need_EIS]])), OR(Table2[[#This Row],[Need_DON]]="No", ISBLANK(Table2[[#This Row],[Need_DON]]) )),"Question, no products",( IF( AND(Table2[[#This Row],[Pending_question]]="Yes", ISBLANK(Table2[[#This Row],[PQ_closure_date]])), (IF(SUM(Table2[[#This Row],[RRA_indic]],Table2[[#This Row],[EIS_indic]],Table2[[#This Row],[DON_indic]])=0, "Open Question, all products done",(I447IF(OR(Table2[[#This Row],[RRA_indic]]=2, Table2[[#This Row],[EIS_indic]]=2, Table2[[#This Row],[DON_indic]]=2),"Question, Products unknown",IF(AND(Table2[[#This Row],[RRA_indic]]=1, Table2[[#This Row],[EIS_indic]]=1, Table2[[#This Row],[DON_indic]]=1), "Open Question, RRA, EIS, DON", IF(AND(Table2[[#This Row],[RRA_indic]]=1, Table2[[#This Row],[EIS_indic]]=1), "Open Question, RRA, EIS",IF(AND(Table2[[#This Row],[RRA_indic]]=1, Table2[[#This Row],[DON_indic]]=1), "Open Question, RRA, DON", IF(AND(Table2[[#This Row],[EIS_indic]]=1, Table2[[#This Row],[DON_indic]]=1), "Open Question, EIS, DON",IF(Table2[[#This Row],[RRA_indic]]=1, "Open Question, RRA", IF(Table2[[#This Row],[EIS_indic]]=1, "Open Question, EIS", "Open Question, DON")))))))))), (IF(SUM(Table2[[#This Row],[RRA_indic]],Table2[[#This Row],[EIS_indic]],Table2[[#This Row],[DON_indic]])=0, "All Products done",(IF(OR(Table2[[#This Row],[RRA_indic]]=2, Table2[[#This Row],[EIS_indic]]=2, Table2[[#This Row],[DON_indic]]=2),"Unknown", IF(AND(Table2[[#This Row],[RRA_indic]]=1, Table2[[#This Row],[EIS_indic]]=1, Table2[[#This Row],[DON_indic]]=1), "Open RRA, EIS, DON", IF(AND(Table2[[#This Row],[RRA_indic]]=1, Table2[[#This Row],[EIS_indic]]=1), "Open RRA, EIS", IF(AND(Table2[[#This Row],[RRA_indic]]=1, Table2[[#This Row],[DON_indic]]=1), "Open RRA, DON", IF(AND(Table2[[#This Row],[EIS_indic]]=1, Table2[[#This Row],[DON_indic]]=1), "Open EIS, DON", IF(Table2[[#This Row],[RRA_indic]]=1, "Open RRA", IF(Table2[[#This Row],[EIS_indic]]=1, "Open EIS", "Open DON")))))))))))))))} -> All Products done | D49: Dunja/Etsub | E49: cVDPV2 | F49: Ukraine | G49: Not applicable | H49: 44472 | J49: 44471 | K49: 2021-E000352 | M49: No | P49: Yes | R49: 12 October 2021: Yes, EURO is drafting. /15 October 2021: First draft received for review. The draft has been circulated with TT for review with deadline by COB 18 October./20 Oct 2021: Revised clean draft shared back with us./ 21 October 2021: RRA distributed | S49: 44481 | U49: 44490 | Y49: yes | AB49: 4 Oct, EURO informed NFP that EIS is needed/4 Oct waiting NFP reply 4 Oct, EURO informed NFP that EIS is needed/ 8 October EIS is being drafted by EURO and is under review by EURO polio TT. A consolidated version to be shared with HQ PHI for review/ 11 October: draft EIS shared with us and is currently under review by PHI.The revised draft shared back with TT and EURO. /12 October 2021: cleaned EIS with pending question shared with IHR NFP for accuracy check./13 October 2021: There is an ongoing discussion on the classification of the case between EURO and IHR NFP. Pending clarifying this issue to proceed with the final posting. /14 October: EIS is published. | AH49: 44483 | AI49: yes | AK49: 44491 | AM49: =VLOOKUP(Table2[[#This Row],[country]],Countrycode!A:B,2,FALSE) -> UKR | AN49: =IF(ISBLANK(Table2[[#This Row],[Need_RRA]]), 2,(IF(Table2[[#This Row],[Need_RRA]]="No", 0, (IF(AND(Table2[[#This Row],[Need_RRA]]="Yes", Table2[[#This Row],[RRA_pub_date]]=""),1, 0))))) -> 0 | AO49: =IF(ISBLANK(Table2[[#This Row],[Need_EIS]]), 2,(IF(Table2[[#This Row],[Need_EIS]]="No", 0, (IF(AND(Table2[[#This Row],[Need_EIS]]="Yes", Table2[[#This Row],[EIS_pub_date]]=""),1, 0))))) -> 0 | AP49: =IF(ISBLANK(Table2[[#This Row],[Need_DON]]), 2,(IF(Table2[[#This Row],[Need_DON]]="No", 0, (IF(AND(Table2[[#This Row],[Need_DON]]="Yes", Table2[[#This Row],[DON_pub_date]]=""),1, 0))))) -> 0 | AQ49: =IF(ISBLANK(Table2[[#This Row],[Pending_question]]), 2,(IF(Table2[[#This Row],[Pending_question]]="Yes", 1, 0))) -> 0 | AR49: 44473
A50: 44473 | B50: Closed | C50: {=IF(SUM(Table2[[#This Row],[PQ_indic]],Table2[[#This Row],[RRA_indic]],Table2[[#This Row],[EIS_indic]],Table2[[#This Row],[DON_indic]])=8, "Missing data", (IF(AND(Table2[[#This Row],[Pending_question]]="Yes", OR( Table2[[#This Row],[Need_RRA]]="No", ISBLANK(Table2[[#This Row],[Need_RRA]])), OR(Table2[[#This Row],[Need_EIS]]="No", ISBLANK(Table2[[#This Row],[Need_EIS]])), OR(Table2[[#This Row],[Need_DON]]="No", ISBLANK(Table2[[#This Row],[Need_DON]]) )),"Question, no products",( IF( AND(Table2[[#This Row],[Pending_question]]="Yes", ISBLANK(Table2[[#This Row],[PQ_closure_date]])), (IF(SUM(Table2[[#This Row],[RRA_indic]],Table2[[#This Row],[EIS_indic]],Table2[[#This Row],[DON_indic]])=0, "Open Question, all products done",(I447IF(OR(Table2[[#This Row],[RRA_indic]]=2, Table2[[#This Row],[EIS_indic]]=2, Table2[[#This Row],[DON_indic]]=2),"Question, Products unknown",IF(AND(Table2[[#This Row],[RRA_indic]]=1, Table2[[#This Row],[EIS_indic]]=1, Table2[[#This Row],[DON_indic]]=1), "Open Question, RRA, EIS, DON", IF(AND(Table2[[#This Row],[RRA_indic]]=1, Table2[[#This Row],[EIS_indic]]=1), "Open Question, RRA, EIS",IF(AND(Table2[[#This Row],[RRA_indic]]=1, Table2[[#This Row],[DON_indic]]=1), "Open Question, RRA, DON", IF(AND(Table2[[#This Row],[EIS_indic]]=1, Table2[[#This Row],[DON_indic]]=1), "Open Question, EIS, DON",IF(Table2[[#This Row],[RRA_indic]]=1, "Open Question, RRA", IF(Table2[[#This Row],[EIS_indic]]=1, "Open Question, EIS", "Open Question, DON")))))))))), (IF(SUM(Table2[[#This Row],[RRA_indic]],Table2[[#This Row],[EIS_indic]],Table2[[#This Row],[DON_indic]])=0, "All Products done",(IF(OR(Table2[[#This Row],[RRA_indic]]=2, Table2[[#This Row],[EIS_indic]]=2, Table2[[#This Row],[DON_indic]]=2),"Unknown", IF(AND(Table2[[#This Row],[RRA_indic]]=1, Table2[[#This Row],[EIS_indic]]=1, Table2[[#This Row],[DON_indic]]=1), "Open RRA, EIS, DON", IF(AND(Table2[[#This Row],[RRA_indic]]=1, Table2[[#This Row],[EIS_indic]]=1), "Open RRA, EIS", IF(AND(Table2[[#This Row],[RRA_indic]]=1, Table2[[#This Row],[DON_indic]]=1), "Open RRA, DON", IF(AND(Table2[[#This Row],[EIS_indic]]=1, Table2[[#This Row],[DON_indic]]=1), "Open EIS, DON", IF(Table2[[#This Row],[RRA_indic]]=1, "Open RRA", IF(Table2[[#This Row],[EIS_indic]]=1, "Open EIS", "Open DON")))))))))))))))} -> All Products done | D50: Dunja | E50: Avian influenza A (H9N2) | F50: China | G50: Not applicable | M50: No | P50: No | Q50: Not applicable | R50: No | Y50: yes | AB50: 2 Oct received the draft EIS from WPRO/ the link to EIS draft document stored at sharepoint shared with TT for feedback by 1 PM 4 Oct/ 4 Oct EIS sent back to WPRO/11 Oct received NFP concurrence and published | AH50: 44473 | AI50: no | AL50: to be reported on 9 AEM on Monday 4 October | AM50: =VLOOKUP(Table2[[#This Row],[country]],Countrycode!A:B,2,FALSE) -> CHN | AN50: =IF(ISBLANK(Table2[[#This Row],[Need_RRA]]), 2,(IF(Table2[[#This Row],[Need_RRA]]="No", 0, (IF(AND(Table2[[#This Row],[Need_RRA]]="Yes", Table2[[#This Row],[RRA_pub_date]]=""),1, 0))))) -> 0 | AO50: =IF(ISBLANK(Table2[[#This Row],[Need_EIS]]), 2,(IF(Table2[[#This Row],[Need_EIS]]="No", 0, (IF(AND(Table2[[#This Row],[Need_EIS]]="Yes", Table2[[#This Row],[EIS_pub_date]]=""),1, 0))))) -> 0 | AP50: =IF(ISBLANK(Table2[[#This Row],[Need_DON]]), 2,(IF(Table2[[#This Row],[Need_DON]]="No", 0, (IF(AND(Table2[[#This Row],[Need_DON]]="Yes", Table2[[#This Row],[DON_pub_date]]=""),1, 0))))) -> 0 | AQ50: =IF(ISBLANK(Table2[[#This Row],[Pending_question]]), 2,(IF(Table2[[#This Row],[Pending_question]]="Yes", 1, 0))) -> 0 | AR50: 44473
